Workbook
Name CAJA_DE_CAPTACION: #REF!
Name CAJA_DE_CAPTACION: #REF!
Name CAJA_DE_CAPTACION: #REF!
Name LIN_DISTR_ELECT.: '[1]PRES 1'!#REF!
Name LIN_DISTR_ELECT.: #REF!
Name LIN_DISTR_ELECT.: '[1]PRES 1'!#REF!
Name LIN_DISTR_ELECT.: #REF!
Name SUBEST_ELECTR: '[1]PRES 1'!#REF!
Name SUBEST_ELECTR: #REF!
Name SUBEST_ELECTR: '[1]PRES 1'!#REF!
Name SUBEST_ELECTR: #REF!

Sheet DATOS
C1: ESTUDIO FINANCIERO
C3: DATOS ADICIONALES
C5: Inflación | D5: 0.09 | E5: Anual
C6: Incremento salarial | D6: 0.12 | E6: Anual
C7: Incremento volumen | D7: 0.03 | E7: cada 3 meses durante el primer año
C8: Incremento precio unitario de venta | D8: 0.09 | E8: A partir del segundo semestre del primer año y durante los sig años
C10: Depreciación en línea recta | E10: LISR
C12: Amortización de la deuda de acuerdo a la
C13: dependencia que otorgará el financiamiento

Sheet CUADRO DE INVERSION
B3: TAQUERIA TAKIRIN "LA CHIMENEA"
B8: CONCEPTO | C8: FIRA | D8: TAKIRIN | E8: TOTAL
B9: Cap. Trabajo | C9: 0 | D9: 0 | E9: =SUM(C9:D9) -> 0
B10: Inv. Fija | C10: =G32 -> 1127676.7 | D10: =H32 -> 820000 | E10: =SUM(C10:D10) -> 1947676.7
B11: Inv. Diferida | C11: =F37 -> 312151.51 | D11: 0 | E11: =SUM(C11:D11) -> 312151.51
B12: Total | C12: =SUM(C9:C11) -> 1439828.2 | D12: =SUM(D9:D11) -> 820000 | E12: =SUM(E9:E11) -> 2259828.2
B13: % | C13: =C12/E12 -> 0.63714056 | D13: =D12/E12 -> 0.36285944 | E13: =SUM(C13:D13) -> 1
B16: CAPITAL DE TRABAJO | C16: CANTIDAD | D16: UNIDAD | E16: COSTO | F16: TOTAL | G16: FIRA | H16: TAKIRIN
B17: INVERSION FIJA
B18: EDIFICIO | C18: 1 | D18: UNIDAD | E18: 604576.32 | F18: =C18*E18 -> 604576.32 | G18: 604576.32
B19: TERRENO | C19: 1 | D19: LOTE | E19: 820000 | F19: =C19*E19 -> 820000 | H19: =F19 -> 820000
B20: MAQUINARIA DE EMPAQUETADO | C20: 2 | D20: UNIDADES | E20: 59908.16 | F20: =C20*E20 -> 119816.32 | G20: =F20 -> 119816.32
B21: PLANCHAS | C21: 2 | D21: UNIDADES | E21: 42380 | F21: =C21*E21 -> 84760 | G21: =F21 -> 84760
B22: TRAMPA DE ACEITE | C22: 1 | D22: UNIDAD | E22: 2 | F22: 8131.73 | G22: =F22 -> 8131.73
B23: TROMPOS | C23: 2 | D23: UNIDADES | E23: 10944.25 | F23: =C23*E23 -> 21888.5 | G23: =F23 -> 21888.5
B24: CAMPANA | C24: 2 | D24: UNIDADES | E24: 9174.44 | F24: =C24*E24 -> 18348.88 | G24: =F24 -> 18348.88
B25: MOLINOS INDUSTRIALES | C25: 2 | D25: UNIDADES | E25: 29135.72 | F25: =C25*E25 -> 58271.44 | G25: =F25 -> 58271.44
B26: CONGELADORES | C26: 2 | D26: UNIDADES | E26: 17699.28 | F26: =C26*E26 -> 35398.56 | G26: =F26 -> 35398.56
B27: MOBILIARIO | C27: 20 | D27: JUEGOS | E27: 3951 | F27: =C27*E27 -> 79020 | G27: =F27 -> 79020
B28: MESAS DE TRABAJO | C28: 4 | D28: UNIDADES | E28: 21412.46 | F28: =E28*C28 -> 85649.84 | G28: =F28 -> 85649.84
B29: INSTRUMENTOS DE COCINA | C29: 4 | D29: JUEGOS | E29: 906.53 | F29: =E29*C29 -> 3626.12 | G29: =F29 -> 3626.12
B30: EQUIPO DE PUNTO DE VENTA | C30: 1 | D30: UNIDADES | E30: 3599 | F30: =E30 -> 3599 | G30: =F30 -> 3599
B31: EQUIPO DE REGISTRO DE VENTA TERMINAL | C31: 3 | D31: UNIDADES | E31: 1530 | F31: =E31*C31 -> 4590 | G31: =F31 -> 4590
F32: =SUM(F18:F31) -> 1947676.7 | G32: =SUM(G18:G31) -> 1127676.7 | H32: =SUM(H18:H31) -> 820000
B34: INVERSION DIFERIDA
B35: CAPACITACION | C35: 1 | D35: SERVICIO | E35: 20000 | F35: =C35*E35 -> 20000 | G35: =F35 -> 20000
B36: PAGO DE HONORARIOS | C36: 1 | D36: SERVICIO | F36: =F32*0.15 -> 292151.51
F37: =SUM(F35:F36) -> 312151.51 | G37: =SUM(G35) -> 20000 | H37: =SUM(H35) -> 0
C40: CONCEPTO | E40: FIRA | F40: TAKIRIN | G40: TOTAL | H40: %
B41: =E41/E44 -> 0 | C41: Cap. Trab. | E41: =0 -> 0 | F41: 0 | G41: =SUM(E41:F41) -> 0 | H41: =G41/G44 -> 0
C42: Inv. Fija | E42: =G32 -> 1127676.7 | F42: =H32 -> 820000 | G42: =SUM(E42:F42) -> 1947676.7 | H42: =G42/G44 -> 0.86186937
C43: Inv. Diferida | E43: =F37 -> 312151.51 | F43: 0 | G43: =SUM(E43:F43) -> 312151.51 | H43: =G43/G44 -> 0.13813063
B44: =100 -> 100 | C44: Total | E44: =SUM(E41:E43) -> 1439828.2 | F44: =SUM(F41:F43) -> 820000 | G44: =SUM(G41:G43) -> 2259828.2 | H44: 1
C45: % | E45: =(E44/G44)*100 -> 63.714056 | F45: =(F44/G44)*100 -> 36.285944 | G45: 1

Sheet ESTRUCTURA FINANCIERA
A1: ESTUDIO FINANCIERO
A3: ESTRUCTURA FINANCIERA
A5: PROYECTO: Nueva sucursal y maquinaria
A6: SOCIEDAD: Taqueria el takirin "La chimenea"
A7: BENEFICIARIOS:
A9: DESGLOSE DE INVERSION PARA UN AÑO
A10: CONCEPTO | B10: UNIDAD DE | C10: CANTIDAD | D10: PRECIO | E10: COSTO | F10: APORTACION
B11: MEDIDA | D11: UNITARIO | E11: TOTAL | F11: DEPENDENCIA | G11: GRUPO
A12: INVERSION FIJA | F12: FIRA | G12: TAKIRIN
A13: TERRENO | B13: 1 | C13: LOTE | D13: 820000 | E13: =B13*D13 -> 820000 | G13: =E13 -> 820000
A14: MAQUINARIA DE EMPAQUETADO | B14: 2 | C14: UNIDADES | D14: 59908.16 | E14: =B14*D14 -> 119816.32 | F14: =E14 -> 119816.32
A15: PLANCHAS | B15: 2 | C15: UNIDADES | D15: 42380 | E15: =B15*D15 -> 84760 | F15: =E15 -> 84760
A16: TRAMPA DE ACEITE | B16: 1 | C16: UNIDAD | D16: 8131.73 | E16: 8131.73 | F16: =E16 -> 8131.73
A17: TROMPOS | B17: 2 | C17: UNIDADES | D17: 10944.25 | E17: =B17*D17 -> 21888.5 | F17: =E17 -> 21888.5
A18: CAMPANA | B18: 2 | C18: UNIDADES | D18: 9174.44 | E18: =B18*D18 -> 18348.88 | F18: =E18 -> 18348.88
A19: MOLINOS INDUSTRIALES | B19: 2 | C19: UNIDADES | D19: 29135.72 | E19: =B19*D19 -> 58271.44 | F19: =E19 -> 58271.44
A20: CONGELADORES | B20: 2 | C20: UNIDADES | D20: 17699.28 | E20: =B20*D20 -> 35398.56 | F20: =E20 -> 35398.56
A21: MOBILIARIO | B21: 20 | C21: JUEGOS | D21: 3951 | E21: =B21*D21 -> 79020 | F21: =E21 -> 79020
A22: MESAS DE TRABAJO | B22: 4 | C22: UNIDADES | D22: 21412.46 | E22: =D22*B22 -> 85649.84 | F22: =E22 -> 85649.84
A23: INSTRUMENTOS DE COCINA | B23: 4 | C23: JUEGOS | D23: 906.53 | E23: =D23*B23 -> 3626.12 | F23: =E23 -> 3626.12
A24: EQUIPO DE REGISTRO DE VENTA | B24: 1 | C24: UNIDADES | D24: 3599 | E24: =D24 -> 3599 | F24: =E24 -> 3599
A25: EQUIPO DE REGISTRO DE VENTA TERMINAL | B25: 3 | C25: UNIDADES | D25: 1530 | E25: =D25*B25 -> 4590 | F25: =E25 -> 4590
A27: Subtotal | E27: =SUM(E13:E26) -> 1343100.4 | F27: =SUM(F14:F26) -> 523100.39 | G27: =SUM(G13:G26) -> 820000
A28: OBRA CIVIL
A29: Salarios
A30: Arquitecto | B30: 2 | C30: Trabajador | D30: 20000 | E30: =D30*B30 -> 40000 | F30: =E30 -> 40000
A31: Albañiles | B31: 20 | C31: Trabajador | D31: 11100 | E31: =D31*B31 -> 222000 | F31: =E31 -> 222000
A32: Electricistas | B32: 4 | C32: Trabajador | D32: 12100 | E32: =D32*B32 -> 48400 | F32: =E32 -> 48400
A33: Carpinteros | B33: 1 | C33: Trabajador | D33: 12000 | E33: =D33*B33 -> 12000 | F33: =E33 -> 12000
A34: Impuestos
A35: Permisos del Ayuntamiento | B35: 1 | C35: Paquete | D35: 15000.5 | E35: =D35*B35 -> 15000.5 | F35: =E35 -> 15000.5
A36: Impuestos de construcción | B36: 1 | C36: Global | D36: 10000.82 | E36: =D36*B36 -> 10000.82 | F36: =E36 -> 10000.82
A37: Materiales para construcción
A38: Cemento | B38: 91 | C38: Saco | D38: 150 | E38: =D38*B38 -> 13650 | F38: =E38 -> 13650
A39: Tablaroca | B39: 60 | C39: Panel | D39: 209 | E39: =D39*B39 -> 12540 | F39: =E39 -> 12540
A40: Clavos | B40: 50 | C40: Caja | D40: 100 | E40: =D40*B40 -> 5000 | F40: =E40 -> 5000
A41: Cables electricos | B41: 600 | C41: Metro | D41: 30 | E41: =D41*B41 -> 18000 | F41: =E41 -> 18000
A42: Tubos PVC | B42: 207 | C42: Tubo | D42: 30 | E42: =D42*B42 -> 6210 | F42: =E42 -> 6210
A43: Pintura | B43: 40 | C43: Lata | D43: 1000 | E43: =D43*B43 -> 40000 | F43: =E43 -> 40000
A44: Arena | B44: 80 | C44: Saco | D44: 80 | E44: =D44*B44 -> 6400 | F44: =E44 -> 6400
A45: Grava | B45: 80 | C45: Saco | D45: 90 | E45: =D45*B45 -> 7200 | F45: =E45 -> 7200
A46: Varilla | B46: 90 | C46: Pza. | D46: 200 | E46: =D46*B46 -> 18000 | F46: =E46 -> 18000
A47: Madera para encofrado | B47: 50 | C47: Tabla | D47: 150 | E47: =D47*B47 -> 7500 | F47: =E47 -> 7500
A48: Mortero | B48: 60 | C48: Saco | D48: 70 | E48: =D48*B48 -> 4200 | F48: =E48 -> 4200
A49: Yeso | B49: 50 | C49: Saco | D49: 60 | E49: =D49*B49 -> 3000 | F49: =E49 -> 3000
... A54: Herramientas (martillos, taladros, palas) | B54: 19 | C54: Set | D54: 5000 | E54: =D54*B54 -> 95000 | F54: =E54 -> 95000
E55: =D55*B55 -> 0
E56: =D56*B56 -> 0
E57: =D57*B57 -> 0
E58: =SUM(E30:E57) -> 604576.32 | F58: =SUM(F30:F57) -> 604576.32
A59: TOTAL | E59: =+E58+E27 -> 1947676.7 | F59: =F58+F27 -> 1127676.7 | G59: =+G58+G27 -> 820000
A60: PORCENTAJE | E60: =+E59/E59 -> 1 | F60: =+F59/E59 -> 0.57898557 | G60: 0.55

Sheet CUADRO DE EGRESOS E INGRESOS
A1: ESTRUCTURA DE INGRESOS Y EGERESOS
A3: SITUACION FINANCIERA ACTUAL Y PROYECTADA
A5: PROYECTO:
A6: SOCIEDAD
A7: BENEFICIARIOS:
B9: FLUJO DE I N G R E S O S Y E G R E S O S
A10: PRIMER AÑO DE INVERSIÓN
A11: C O N C E P T O | C11: 1 MES | D11: 2 MES | E11: 3 MES | F11: 4 MES | G11: 5 MES | H11: 6 MES | I11: 7 MES | J11: 8 MES | K11: 9 MES | L11: 10 MES | M11: 11 MES | N11: 12 MES | O11: TOTAL
A12: INGRESOS POR VENTAS | C12: ='INGRESOS '!B24 -> 1202850 | D12: ='INGRESOS '!C24 -> 1202850 | E12: ='INGRESOS '!D24 -> 1202850 | F12: ='INGRESOS '!E24 -> 1239090 | G12: ='INGRESOS '!F24 -> 1239090 | H12: ='INGRESOS '!G24 -> 1239090 | I12: ='INGRESOS '!H24 -> 1278360 | J12: ='INGRESOS '!I24 -> 1278360 | ... N12: ='INGRESOS '!M24 -> 1320810 | O12: =SUM(C12:N12) -> 15123330
A13: TOTAL DE INGRESOS | C13: =C12 -> 1202850 | D13: =D12 -> 1202850 | E13: =E12 -> 1202850 | F13: =F12 -> 1239090 | G13: =G12 -> 1239090 | H13: =H12 -> 1239090 | I13: =I12 -> 1278360 | J13: =J12 -> 1278360 | ... N13: =N12 -> 1320810 | O13: =SUM(C13:N13) -> 15123330
A14: EGRESOS
A15: VARIABLE | C15: ='COSTOS '!B4 -> 193560 | D15: ='COSTOS '!C4 -> 197431.2 | E15: ='COSTOS '!D4 -> 193482.58 | F15: ='COSTOS '!E4 -> 199287.05 | G15: ='COSTOS '!F4 -> 203272.79 | H15: ='COSTOS '!G4 -> 197174.61 | I15: ='COSTOS '!H4 -> 195202.86 | J15: ='COSTOS '!I4 -> 199106.92 | ... N15: ='COSTOS '!M4 -> 200977.75 | O15: =SUM(C15:N15) -> 2364831.1 | P15: TOTAL DE EGRESOS
A16: FIJOS | C16: ='COSTOS '!B16 -> 207422.46 | D16: ='COSTOS '!C16 -> 207422.46 | E16: ='COSTOS '!D16 -> 207422.46 | F16: ='COSTOS '!E16 -> 207422.46 | G16: ='COSTOS '!F16 -> 207422.46 | H16: ='COSTOS '!G16 -> 207422.46 | I16: ='COSTOS '!H16 -> 207422.46 | J16: ='COSTOS '!I16 -> 207422.46 | ... N16: ='COSTOS '!M16 -> 207422.46 | O16: =SUM(C16:N16) -> 2489069.5 | P16: =O15+O16 -> 4853900.6
A17: SALDO | C17: =C12-(C15+C16) -> 801867.54 | D17: =D12-(D15+D16) -> 797996.34 | E17: =E12-(E15+E16) -> 801944.97 | F17: =F12-(F15+F16) -> 832380.49 | G17: =G12-(G15+G16) -> 828394.75 | H17: =H12-(H15+H16) -> 834492.93 | I17: =I12-(I15+I16) -> 875734.68 | J17: =J12-(J15+J16) -> 871830.62 | ... O17: =O12-(O15+O16) -> 10269429
A18: SALDO ACUMULADO | C18: =+C17 -> 801867.54 | D18: =+D17+C18 -> 1599863.9 | E18: =+E17+D18 -> 2401808.9 | F18: =+F17+E18 -> 3234189.3 | G18: =+G17+F18 -> 4062584.1 | H18: =+H17+G18 -> 4897077 | I18: =+I17+H18 -> 5772811.7 | J18: =+J17+I18 -> 6644642.3 | K18: =+K17+J18 -> 7520455.1 | ... N18: =+N17+M18 -> 10269429 | O18: =+N18 -> 10269429
A22: PROYECCION FINANCIERA ANUAL
A24: SEGUNDO AÑO DE INVERSIÓN
A25: C O N C E P T O | C25: 1 MES | D25: 2 MES | E25: 3 MES | F25: 4 MES | G25: 5 MES | H25: 6 MES | I25: 7 MES | J25: 8 MES | K25: 9 MES | L25: 10 MES | M25: 11 MES | N25: 12 MES | O25: TOTAL
A26: INGRESOS POR VENTAS | C26: ='INGRESOS '!B44 -> 1439682.9 | D26: ='INGRESOS '!C44 -> 1439682.9 | E26: ='INGRESOS '!D44 -> 1439682.9 | F26: ='INGRESOS '!E44 -> 1439682.9 | G26: ='INGRESOS '!F44 -> 1439682.9 | H26: ='INGRESOS '!G44 -> 1439682.9 | I26: ='INGRESOS '!H44 -> 1439682.9 | J26: ='INGRESOS '!I44 -> 1439682.9 | ... N26: ='INGRESOS '!M44 -> 1439682.9 | O26: =SUM(C26:N26) -> 17276195
A27: TOTAL DE INGRESOS | C27: =C26 -> 1439682.9 | D27: =D26 -> 1439682.9 | E27: =E26 -> 1439682.9 | F27: =F26 -> 1439682.9 | G27: =G26 -> 1439682.9 | H27: =H26 -> 1439682.9 | I27: =I26 -> 1439682.9 | J27: =J26 -> 1439682.9 | ... N27: =N26 -> 1439682.9 | O27: =SUM(C27:N27) -> 17276195
K28: 0 | L28: 0 | M28: =+M26*A28 -> 0 | O28: =+J28 -> 0
A29: EGRESOS
A30: VARIABLE | C30: ='COSTOS '!B57 -> 200977.75 | D30: ='COSTOS '!C57 -> 204997.3 | E30: ='COSTOS '!D57 -> 200897.36 | F30: ='COSTOS '!E57 -> 206924.28 | G30: ='COSTOS '!F57 -> 211062.76 | H30: ='COSTOS '!G57 -> 204730.88 | I30: ='COSTOS '!H57 -> 202683.57 | J30: ='COSTOS '!I57 -> 206737.24 | ... O30: ='COSTOS '!N57 -> 2455457.9 | P30: TOTAL DE EGRESOS
A31: FIJOS | C31: ='COSTOS '!B69 -> 207422.46 | D31: ='COSTOS '!C69 -> 207422.46 | E31: ='COSTOS '!D69 -> 207422.46 | F31: ='COSTOS '!E69 -> 207422.46 | G31: ='COSTOS '!F69 -> 207422.46 | H31: ='COSTOS '!G69 -> 207422.46 | I31: ='COSTOS '!H69 -> 207422.46 | J31: ='COSTOS '!I69 -> 207422.46 | ... O31: ='COSTOS '!N69 -> 2489069.5 | P31: =O30+O31 -> 4944527.3
A32: SALDO | C32: =C26-(C30+C31) -> 1031282.7 | D32: =D26-(D30+D31) -> 1027263.1 | E32: =E26-(E30+E31) -> 1031363.1 | F32: =F26-(F30+F31) -> 1025336.2 | G32: =G26-(G30+G31) -> 1021197.7 | H32: =H26-(H30+H31) -> 1027529.6 | I32: =I26-(I30+I31) -> 1029576.9 | J32: =J26-(J30+J31) -> 1025523.2 | ... O32: =O26-(O30+O31) -> 12331667
A33: SALDO ACUMULADO | C33: =+C32 -> 1031282.7 | D33: =+D32+C33 -> 2058545.8 | E33: =+E32+D33 -> 3089908.9 | F33: =+F32+E33 -> 4115245.1 | G33: =+G32+F33 -> 5136442.8 | H33: =+H32+G33 -> 6163972.3 | I33: =+I32+H33 -> 7193549.2 | J33: =+J32+I33 -> 8219072.4 | K33: =+K32+J33 -> 9248730.4 | ... N33: =+N32+M33 -> 12331667 | O33: =+N33 -> 12331667
A35: TERCER AÑO DE INVERSIÓN
A36: C O N C E P T O | C36: 1 MES | D36: 2 MES | E36: 3 MES | F36: 4 MES | G36: 5 MES | H36: 6 MES | I36: 7 MES | J36: 8 MES | K36: 9 MES | L36: 10 MES | M36: 11 MES | N36: 12 MES | O36: TOTAL
A37: INGRESOS POR VENTAS | C37: ='INGRESOS '!B64 -> 1569254.4 | D37: ='INGRESOS '!C64 -> 1569254.4 | E37: ='INGRESOS '!D64 -> 1569254.4 | F37: ='INGRESOS '!E64 -> 1569254.4 | G37: ='INGRESOS '!F64 -> 1569254.4 | H37: ='INGRESOS '!G64 -> 1569254.4 | I37: ='INGRESOS '!H64 -> 1569254.4 | J37: ='INGRESOS '!I64 -> 1569254.4 | ... N37: ='INGRESOS '!M64 -> 1569254.4 | O37: =SUM(C37:N37) -> 18831052
A38: TOTAL DE INGRESOS | C38: =C37 -> 1569254.4 | D38: =D37 -> 1569254.4 | E38: =E37 -> 1569254.4 | F38: =F37 -> 1569254.4 | G38: =G37 -> 1569254.4 | H38: =H37 -> 1569254.4 | I38: =I37 -> 1569254.4 | J38: =J37 -> 1569254.4 | ... N38: =N37 -> 1569254.4 | O38: =SUM(C38:N38) -> 18831052
K39: 0 | L39: 0 | M39: =+M37*A39 -> 0 | O39: =+J39 -> 0
A40: EGRESOS
A41: VARIABLE | C41: ='COSTOS '!B110 -> 208679.76 | D41: ='COSTOS '!C110 -> 212853.36 | E41: ='COSTOS '!D110 -> 208596.29 | F41: ='COSTOS '!E110 -> 214854.18 | G41: ='COSTOS '!F110 -> 219151.26 | H41: ='COSTOS '!G110 -> 212576.72 | I41: ='COSTOS '!H110 -> 210450.96 | J41: ='COSTOS '!I110 -> 214659.98 | ... N41: ='COSTOS '!M110 -> 216676.94 | O41: =SUM(C41:N41) -> 2549557.7 | P41: TOTAL DE EGRESOS
A42: FIJOS | C42: ='COSTOS '!B122 -> 207422.46 | D42: ='COSTOS '!C122 -> 207422.46 | E42: ='COSTOS '!D122 -> 207422.46 | F42: ='COSTOS '!E122 -> 207422.46 | G42: ='COSTOS '!F122 -> 207422.46 | H42: ='COSTOS '!G122 -> 207422.46 | I42: ='COSTOS '!H122 -> 207422.46 | J42: ='COSTOS '!I122 -> 207422.46 | ... O42: ='COSTOS '!N122 -> 2489069.5 | P42: =O41+O42 -> 5038627.2
A43: SALDO | C43: =C37-(C41+C42) -> 1153152.1 | D43: =D37-(D41+D42) -> 1148978.5 | E43: =E37-(E41+E42) -> 1153235.6 | F43: =F37-(F41+F42) -> 1146977.7 | G43: =G37-(G41+G42) -> 1142680.6 | H43: =H37-(H41+H42) -> 1149255.2 | I43: =I37-(I41+I42) -> 1151380.9 | J43: =J37-(J41+J42) -> 1147171.9 | ... O43: =O37-(O41+O42) -> 13792425
A44: SALDO ACUMULADO | C44: =+C43 -> 1153152.1 | D44: =+D43+C44 -> 2302130.7 | E44: =+E43+D44 -> 3455366.3 | F44: =+F43+E44 -> 4602344 | G44: =+G43+F44 -> 5745024.7 | H44: =+H43+G44 -> 6894279.9 | I44: =+I43+H44 -> 8045660.8 | J44: =+J43+I44 -> 9192832.7 | K44: =+K43+J44 -> 10344298 | ... N44: =+N43+M44 -> 13792425 | O44: =+N44 -> 13792425
A46: CUARTO AÑO DE INVERSIÓN
A47: C O N C E P T O | C47: 1 MES | D47: 2 MES | E47: 3 MES | F47: 4 MES | G47: 5 MES | H47: 6 MES | I47: 7 MES | J47: 8 MES | K47: 9 MES | L47: 10 MES | M47: 11 MES | N47: 12 MES | O47: TOTAL
A48: INGRESOS POR VENTAS | C48: ='INGRESOS '!B84 -> 1710487.3 | D48: ='INGRESOS '!C84 -> 1710487.3 | E48: ='INGRESOS '!D84 -> 1710487.3 | F48: ='INGRESOS '!E84 -> 1710487.3 | G48: ='INGRESOS '!F84 -> 1710487.3 | H48: ='INGRESOS '!G84 -> 1710487.3 | I48: ='INGRESOS '!H84 -> 1710487.3 | J48: ='INGRESOS '!I84 -> 1710487.3 | ... N48: ='INGRESOS '!M84 -> 1710487.3 | O48: =SUM(C48:N48) -> 20525847
A49: TOTAL DE INGRESOS | C49: =C48 -> 1710487.3 | D49: =D48 -> 1710487.3 | E49: =E48 -> 1710487.3 | F49: =F48 -> 1710487.3 | G49: =G48 -> 1710487.3 | H49: =H48 -> 1710487.3 | I49: =I48 -> 1710487.3 | J49: =J48 -> 1710487.3 | ... N49: =N48 -> 1710487.3 | O49: =SUM(C49:N49) -> 20525847
K50: 0 | L50: 0 | M50: =+M48*A50 -> 0 | O50: =+J50 -> 0
A51: EGRESOS
A52: VARIABLE | C52: ='COSTOS '!B163 -> 216676.94 | D52: ='COSTOS '!C163 -> 221010.48 | E52: ='COSTOS '!D163 -> 216590.27 | F52: ='COSTOS '!E163 -> 223087.97 | G52: ='COSTOS '!F163 -> 227549.73 | H52: ='COSTOS '!G163 -> 220723.24 | I52: ='COSTOS '!H163 -> 218516.01 | J52: ='COSTOS '!I163 -> 222886.33 | ... N52: ='COSTOS '!M163 -> 224980.59 | O52: =SUM(C52:N52) -> 2647263.7 | P52: TOTAL DE EGRESOS
A53: FIJOS | C53: ='COSTOS '!B175 -> 207422.46 | D53: ='COSTOS '!C175 -> 207422.46 | E53: ='COSTOS '!D175 -> 207422.46 | F53: ='COSTOS '!E175 -> 207422.46 | G53: ='COSTOS '!F175 -> 207422.46 | H53: ='COSTOS '!G175 -> 207422.46 | I53: ='COSTOS '!H175 -> 207422.46 | J53: ='COSTOS '!I175 -> 207422.46 | ... N53: ='COSTOS '!M175 -> 207422.46 | O53: =SUM(C53:N53) -> 2489069.5 | P53: =O52+O53 -> 5136333.2
A54: SALDO | C54: =C48-(C52+C53) -> 1286387.9 | D54: =D48-(D52+D53) -> 1282054.3 | E54: =E48-(E52+E53) -> 1286474.5 | F54: =F48-(F52+F53) -> 1279976.8 | G54: =G48-(G52+G53) -> 1275515.1 | H54: =H48-(H52+H53) -> 1282341.6 | I54: =I48-(I52+I53) -> 1284548.8 | J54: =J48-(J52+J53) -> 1280178.5 | ... O54: =O48-(O52+O53) -> 15389514
A55: SALDO ACUMULADO | C55: =+C54 -> 1286387.9 | D55: =+D54+C55 -> 2568442.2 | E55: =+E54+D55 -> 3854916.7 | F55: =+F54+E55 -> 5134893.5 | G55: =+G54+F55 -> 6410408.6 | H55: =+H54+G55 -> 7692750.2 | I55: =+I54+H55 -> 8977298.9 | J55: =+J54+I55 -> 10257477 | K55: =+K54+J55 -> 11542114 | ... N55: =+N54+M55 -> 15389514 | O55: =+N55 -> 15389514
A57: QUINTO AÑO DE INVERSIÓN
A58: C O N C E P T O | C58: 1 MES | D58: 2 MES | E58: 3 MES | F58: 4 MES | G58: 5 MES | H58: 6 MES | I58: 7 MES | J58: 8 MES | K58: 9 MES | L58: 10 MES | M58: 11 MES | N58: 12 MES | O58: TOTAL
A59: INGRESOS POR VENTAS | C59: ='INGRESOS '!B104 -> 1864431.1 | D59: ='INGRESOS '!C104 -> 1864431.1 | E59: ='INGRESOS '!D104 -> 1864431.1 | F59: ='INGRESOS '!E104 -> 1864431.1 | G59: ='INGRESOS '!F104 -> 1864431.1 | H59: ='INGRESOS '!G104 -> 1864431.1 | I59: ='INGRESOS '!H104 -> 1864431.1 | J59: ='INGRESOS '!I104 -> 1864431.1 | ... N59: ='INGRESOS '!M104 -> 1864431.1 | O59: =SUM(C59:N59) -> 22373173
A60: TOTAL DE INGRESOS | C60: =C59 -> 1864431.1 | D60: =D59 -> 1864431.1 | E60: =E59 -> 1864431.1 | F60: =F59 -> 1864431.1 | G60: =G59 -> 1864431.1 | H60: =H59 -> 1864431.1 | I60: =I59 -> 1864431.1 | J60: =J59 -> 1864431.1 | ... N60: =N59 -> 1864431.1 | O60: =SUM(C60:N60) -> 22373173
K61: 0 | L61: 0 | M61: =+M59*A61 -> 0 | O61: =+J61 -> 0
A62: EGRESOS
A63: VARIABLE | C63: ='COSTOS '!B216 -> 224980.59 | D63: ='COSTOS '!C216 -> 229480.2 | E63: ='COSTOS '!D216 -> 224890.6 | F63: ='COSTOS '!E216 -> 231637.31 | G63: ='COSTOS '!F216 -> 236270.06 | H63: ='COSTOS '!G216 -> 229181.96 | I63: ='COSTOS '!H216 -> 226890.14 | J63: ='COSTOS '!I216 -> 231427.94 | ... N63: ='COSTOS '!M216 -> 233602.46 | O63: =SUM(C63:N63) -> 2748714 | P63: TOTAL DE EGRESOS
A64: FIJOS | C64: ='COSTOS '!B228 -> 207422.46 | D64: ='COSTOS '!C228 -> 207422.46 | E64: ='COSTOS '!D228 -> 207422.46 | F64: ='COSTOS '!E228 -> 207422.46 | G64: ='COSTOS '!F228 -> 207422.46 | H64: ='COSTOS '!G228 -> 207422.46 | I64: ='COSTOS '!H228 -> 207422.46 | J64: ='COSTOS '!I228 -> 207422.46 | ... N64: ='COSTOS '!M228 -> 207422.46 | O64: =SUM(C64:N64) -> 2489069.5 | P64: =O63+O64 -> 5237783.5
A65: SALDO | C65: =C59-(C63+C64) -> 1432028.1 | D65: =D59-(D63+D64) -> 1427528.5 | E65: =E59-(E63+E64) -> 1432118.1 | F65: =F59-(F63+F64) -> 1425371.3 | G65: =G59-(G63+G64) -> 1420738.6 | H65: =H59-(H63+H64) -> 1427826.7 | I65: =I59-(I63+I64) -> 1430118.5 | J65: =J59-(J63+J64) -> 1425580.7 | ... O65: =O59-(O63+O64) -> 17135390
A66: SALDO ACUMULADO | C66: =+C65 -> 1432028.1 | D66: =+D65+C66 -> 2859556.5 | E66: =+E65+D66 -> 4291674.6 | F66: =+F65+E66 -> 5717045.9 | G66: =+G65+F66 -> 7137784.5 | H66: =+H65+G66 -> 8565611.2 | I66: =+I65+H66 -> 9995729.7 | J66: =+J65+I66 -> 11421310 | K66: =+K65+J66 -> 12851520 | ... N66: =+N65+M66 -> 17135390 | O66: =+N66 -> 17135390
A72: CAPACIDAD DE PAGO
D73: =O38 -> 18831052
A74: CONCEPTO | B74: PRMER AÑO | C74: SEGUNDO AÑO | D74: TERCER AÑO | E74: CUARTO AÑO | F74: QUINTO AÑO
A75: INGRESOS | B75: =O13 -> 15123330 | C75: =O27 -> 17276195 | D75: =O38 -> 18831052 | E75: =O49 -> 20525847 | F75: =O60 -> 22373173
A76: EGRESOS | B76: =P16 -> 4853900.6 | C76: =P31 -> 4944527.3 | D76: =P42 -> 5038627.2 | E76: =P53 -> 5136333.2 | F76: =P64 -> 5237783.5
A77: TOTAL | B77: =B75-B76 -> 10269429 | C77: =C75-C76 -> 12331667 | D77: =D75-D76 -> 13792425 | E77: =E75-E76 -> 15389514 | F77: =F75-F76 -> 17135390

Sheet PUNTO DE EQUILIBRIO
A1: TAQUERIA TAKIRIN "LA CHIMENEA"
A3: PRECIO UNI | C3: 1135
A4: COSTO VARI UNI | C4: 685.9
A5: COSTO FIJO TOTAL | C5: ='COSTOS '!N16+AMORTIZACIONES!B49 -> 3074192.7
A9: P.E. UNI = | B9: COSTOS FIJOS | E9: = | F9: =C5 -> 3074192.7 | G9: = | H9: =F9 -> 3074192.7 | I9: = | J9: =H9/H10 -> 6845.2299
B10: PRECIO VENTA UNI - COSTO VARIABLE UNI | F10: =C3-C4 -> 449.1 | H10: =F10 -> 449.1
A12: P.E. s/= | B12: COSTOS FIJOS | E12: = | F12: =C5 -> 3074192.7 | G12: = | H12: =F12 -> 3074192.7 | I12: = | J12: =H12 -> 3074192.7 | L12: =J12/J13 -> 7769335.9
B13: 1- | C13: COSTO VARIABLE | F13: =C4 -> 685.9 | H13: =F13/F14 -> 0.60431718 | J13: =1-H13 -> 0.39568282
C14: PRECIO UNI | E14: 1- | F14: =C3 -> 1135
A16: OTRA FORMA | C16: P.E UNI * PRECIO UNI | E16: = | F16: =J9 -> 6845.2299 | G16: * | H16: =C3 -> 1135 | I16: = | J16: =F16*H16 -> 7769335.9
A21: UNIDADES | B21: 0 | C21: 1000 | D21: 2000 | E21: 3000 | F21: 4000 | G21: 5000 | H21: 6000 | I21: 7000 | J21: 8000 | K21: 9000 | L21: 10000 | M21: 11000 | N21: 12000 | O21: 13000 | P21: 14000 | Q21: 15000 | R21: 16000 | S21: 17000 | T21: 18000 | U21: 19000 | V21: 20000 | W21: 21000 | X21: 22000 | Y21: 23000 | Z21: 24000 | AA21: 25000 | AB21: 26000 | AC21: 27000 | AD21: 28000 | AE21: 29000 | AF21: 30000
A22: VENTAS | B22: =B21*$C$3 -> 0 | C22: =C21*$C$3 -> 1135000 | D22: =D21*$C$3 -> 2270000 | E22: =E21*$C$3 -> 3405000 | F22: =F21*$C$3 -> 4540000 | G22: =G21*$C$3 -> 5675000 | H22: =H21*$C$3 -> 6810000 | I22: =I21*$C$3 -> 7945000 | ... AF22: =AF21*$C$3 -> 34050000
A23: COSTOS VARIABLE | B23: =B21*$C$4 -> 0 | C23: =C21*$C$4 -> 685900 | D23: =D21*$C$4 -> 1371800 | E23: =E21*$C$4 -> 2057700 | F23: =F21*$C$4 -> 2743600 | G23: =G21*$C$4 -> 3429500 | H23: =H21*$C$4 -> 4115400 | I23: =I21*$C$4 -> 4801300 | ... AF23: =AF21*$C$4 -> 20577000
A24: MARGEN DE CONTRIBUCION | B24: =B22-B23 -> 0 | C24: =C22-C23 -> 449100 | D24: =D22-D23 -> 898200 | E24: =E22-E23 -> 1347300 | F24: =F22-F23 -> 1796400 | G24: =G22-G23 -> 2245500 | H24: =H22-H23 -> 2694600 | I24: =I22-I23 -> 3143700 | ... AF24: =AF22-AF23 -> 13473000
A25: COSTOS FIJO | B25: =$C$5 -> 3074192.7 | C25: =$C$5 -> 3074192.7 | D25: =$C$5 -> 3074192.7 | E25: =$C$5 -> 3074192.7 | F25: =$C$5 -> 3074192.7 | G25: =$C$5 -> 3074192.7 | H25: =$C$5 -> 3074192.7 | I25: =$C$5 -> 3074192.7 | ... AF25: =$C$5 -> 3074192.7
A26: COSTOS TOTALES | B26: =B25+B23 -> 3074192.7 | C26: =C25+C23 -> 3760092.7 | D26: =D25+D23 -> 4445992.7 | E26: =E25+E23 -> 5131892.7 | F26: =F25+F23 -> 5817792.7 | G26: =G25+G23 -> 6503692.7 | H26: =H25+H23 -> 7189592.7 | I26: =I25+I23 -> 7875492.7 | ... AF26: =AF25+AF23 -> 23651193
A27: UTILIDAD O PERDIDA | B27: =B22-B26 -> -3074192.7 | C27: =C22-C26 -> -2625092.7 | D27: =D22-D26 -> -2175992.7 | E27: =E22-E26 -> -1726892.7 | F27: =F22-F26 -> -1277792.7 | G27: =G22-G26 -> -828692.73 | H27: =H22-H26 -> -379592.73 | I27: =I22-I26 -> 69507.274 | ... AF27: =AF22-AF26 -> 10398807

Sheet M. DE CALCULO DE COSTOS VAR
A1: ESTRUCTURA DE INGRESOS Y EGERESOS
A3: MEMORIAS DE CALCULO COSTOS VARIABLES
A5: PROYECTO:
A6: SOCIEDAD
A7: BENEFICIARIOS:
A10: MEMORIA DE CALCULO MATERIA PRIMA E INSUMOS | G10: MEMORIA DE CALCULO MATERIA PRIMA E INSUMOS | M10: MEMORIA DE CALCULO MATERIA PRIMA E INSUMOS
A11: Taco al pastor | B11: MEDIDA | C11: CANT | D11: C.U. | E11: TOTAL | G11: Taco arabe gigante | H11: MEDIDA | I11: CANT | J11: C.U. | K11: TOTAL | M11: Matahambre | N11: MEDIDA | O11: CANT | P11: C.U. | Q11: TOTAL
A12: Carne de cerdo adobada al pastor | B12: Gramos | C12: 40-50 | D12: 6 | E12: =D12*$F$19 -> 72000 | G12: Carne de cerdo marinada estilo oriental | H12: Gramos | I12: 120 | J12: 50 | K12: =J12*$F$20 -> 45000 | M12: Carne de cerdo adobada al pastor | N12: Gramos | O12: 600 | P12: 70 | Q12: =P12*$F$21 -> 42000
A13: Tortilla de maíz | B13: Pieza | C13: 1 | D13: 0.2 | E13: =D13*$F$19 -> 2400 | G13: Pan árabe (Pita) | H13: Pieza | I13: 2 | J13: 4 | K13: =J13*$F$20 -> 3600 | M13: Tocino | N13: Gramos | O13: 50 | P13: 21 | Q13: =P13*$F$21 -> 12600
A14: Piña | B14: Gramos | C14: 5 | D14: 0.2 | E14: =D14*$F$19 -> 2400 | G14: Subtotal | J14: 54 | K14: =SUM(K12:K13) -> 48600 | L14: $ 100.00 | M14: Tortilla de maíz | N14: Pieza | O14: 18 | P14: 3.6 | Q14: =P14*$F$21 -> 2160
A15: Cebolla | B15: Gramos | C15: 2 | D15: 0.1 | E15: =D15*$F$19 -> 1200 | M15: Chile poblano | N15: Gramos | O15: 50 | P15: 6 | Q15: =P15*$F$21 -> 3600
A16: Cilantro | B16: Gramos | C16: 2 | D16: 0.1 | E16: =D16*$F$19 -> 1200 | K16: =J14/L14 -> #VALUE! | M16: Cebolla | N16: Gramos | O16: 50 | P16: 5 | Q16: =P16*$F$21 -> 3000
A17: Subtotal | D17: 6.6 | E17: =SUM(E12:E16) -> 79200 | F17: 14 | G17: =D17/F17 -> 0.47142857 | M17: Jitomate | N17: Gramos | O17: 50 | P17: 4 | Q17: =P17*$F$21 -> 2400
E18: DIARIO | F18: MENSUAL | M18: Subtotal | P18: $ 109.60 | Q18: =SUM(Q12:Q17) -> 65760 | R18: $ 220.00
D19: TACOS | E19: 400 | F19: =E19*30 -> 12000
D20: ARABE | E20: 30 | F20: =E20*30 -> 900 | Q20: =P18/R18 -> #VALUE!
D21: MATAHAMBRE | E21: 20 | F21: =E21*30 -> 600
A23: MEMORIA DE CALCULO GASTOS INDIRECTOS DE FABRICACION
B24: Porcentaje | C24: Medida | D24: CANT | E24: C.U. | F24: TOTAL MENSUAL
A25: Renta del local | B25: 0.6 | C25: Mes | D25: 1 | E25: 8000 | F25: =E25*0.6 -> 4800
A26: Energía eléctrica | B26: 0.8 | C26: Mes | D26: 1 | E26: 1200 | F26: 960
A27: Agua | B27: 0.7 | C27: Mes | D27: 1 | E27: 500 | F27: 350
A28: Gas LP | B28: 1 | C28: Mes | D28: 1 | E28: 1000 | F28: 1000
A29: Mantenimiento | B29: 0.7 | C29: Mes | D29: 1 | E29: 350 | F29: 350
A30: Depreciacion en eq. De producción | B30: 1 | C30: Mes | D30: 1 | E30: 1500 | F30: 1500
A31: Subtotal | F31: =SUM(F25:F30) -> 8960
A38: MEMORIA DE CALCULO MANO DE OBRA PARA LA INVERSION FIJA
A39: CONCEPTO | B39: MEDIDA | C39: CANT | D39: C.U. | E39: TOTAL
A40: Servicios profesionales de empresa constructora para adecuación del local (proyecto arquitectónico, obra civil, instalaciones eléctricas, plomería y acabados) | B40: Proyecto | C40: 1 | D40: $ 1,500,000.00 | E40: $ 1,500,000.00
A41: Supervisión y dirección de obra (incluida en contrato) | B41: Proyecto | C41: 1 | D41: Incluido
A42: Subtotal | E42: $ 1,500,000.00
A43: El monto corresponde al contrato global con la empresa de arquitectura encargada del diseño y construcción de la nueva sucursal. Incluye toda la mano de obra directa e indirecta del proyecto.
A51: MEMORIA DE CALCULO DE MOD
A52: Pago de salarios a personal de producción
B53: Sueldo semanal | C53: Sueldo neto semanal | D53: Sueldo neto mensual | E53: Sueldo neto bimestral
A54: Mesero | B54: 2100 | C54: 1691.61 | D54: 6766.43 | E54: 13532.87
A55: Verduras | B55: 1960 | C55: 1587.08 | D55: 6348.32 | E55: 12696.63
A56: Ensaladas | B56: 1960 | C56: 1587.08 | D56: 6348.32 | E56: 12696.63
A57: Guarniciones | B57: 1960 | C57: 1587.08 | D57: 6348.32 | E57: 12696.63
A58: Salsas y jarabes | B58: 1960 | C58: 1587.08 | D58: 6348.32 | E58: 12696.63
A59: Empaquetado | B59: 1960 | C59: 1587.08 | D59: 6348.32 | E59: 12696.63
A60: Parrillero | B60: 2800 | C60: 2223.75 | D60: 8895.01 | E60: 17790.02
A61: Parrillero auxiliar | B61: 2450 | C61: 1965.59 | D61: 7862.37 | E61: 15724.74
A62: Pastorero | B62: 2800 | C62: 2223.75 | D62: 8895.01 | E62: 17790.02
A63: Subtotal | D63: =SUM(D54:D62) -> 64160.42 | E63: $ 19,950.00

Sheet M. DE CALCULO DE GASTOS FIJO
A1: ESTRUCTURA DE INGRESOS Y EGRESOS
A3: MEMORIAS DE CALCULO GASTOS FIJOS
A5: PROYECTO: | B5: Taqueria Takirin "la chimenea"
A6: SOCIEDAD
A7: BENEFICIARIOS: | B7: Roberto Hernandez Lira
A8: MEMORIA DE CALCULO GASTOS DE ADMINISTRACIÓN | F8: MESES
B9: MEDIDA | C9: CANT | D9: C.U. | E9: TOTAL | F9: 1 | G9: 2 | H9: 3 | I9: 4 | J9: 5 | K9: 6 | L9: 7 | M9: 8 | N9: 9 | O9: 10 | P9: 11 | Q9: 12
A10: Renta del local | B10: Mes | C10: 2 | D10: 8000 | E10: =C10*D10 -> 16000 | F10: =$E$10 -> 16000 | G10: =$E$10 -> 16000 | H10: =$E$10 -> 16000 | I10: =$E$10 -> 16000 | J10: =$E$10 -> 16000 | K10: =$E$10 -> 16000 | L10: =$E$10 -> 16000 | M10: =$E$10 -> 16000 | ... Q10: =$E$10 -> 16000
A11: Internet / teléfono | B11: Mes | C11: 1 | D11: 600 | E11: 600 | F11: 600 | G11: 600 | H11: 600 | I11: 600 | J11: 600 | K11: 600 | L11: 600 | M11: 600 | N11: 600 | O11: 600 | P11: 600 | Q11: 600
A12: Permisos y licencias | B12: Mes | C12: 1 | D12: 400 | E12: 400 | F12: 400 | G12: 400 | H12: 400 | I12: 400 | J12: 400 | K12: 400 | L12: 400 | M12: 400 | N12: 400 | O12: 400 | P12: 400 | Q12: 400
A13: Mantenimiento | B13: Mes | C13: 1 | D13: 500 | E13: 500 | F13: 500 | G13: 500 | H13: 500 | I13: 500 | J13: 500 | K13: 500 | L13: 500 | M13: 500 | N13: 500 | O13: 500 | P13: 500 | Q13: 500
A14: Depreciaciones | B14: Mes | C14: 1 | D14: 1500 | E14: 1500 | F14: 1500 | G14: 1500 | H14: 1500 | I14: 1500 | J14: 1500 | K14: 1500 | L14: 1500 | M14: 1500 | N14: 1500 | O14: 1500 | P14: 1500 | Q14: 1500
A15: Subtotal | E15: =SUM(E10:E14) -> 19000 | F15: =SUM(F10:F14) -> 19000 | G15: =SUM(G10:G14) -> 19000 | H15: =SUM(H10:H14) -> 19000 | I15: =SUM(I10:I14) -> 19000 | J15: =SUM(J10:J14) -> 19000 | K15: =SUM(K10:K14) -> 19000 | L15: =SUM(L10:L14) -> 19000 | ... Q15: =SUM(Q10:Q14) -> 19000 | R15: =SUM(F15:Q15) -> 228000
A18: MEMORIA DE CALCULO GASTOS DE VENTA | F18: MESES
F19: 1 | G19: 2 | H19: 3 | I19: 4 | J19: 5 | K19: 6 | L19: 7 | M19: 8 | N19: 9 | O19: 10 | P19: 11 | Q19: 12
A20: Energía eléctrica (Pago bimestral) | B20: Mes | C20: 1 | D20: 700 | E20: 700 | F20: 700 | G20: 700 | H20: 700 | I20: 700 | J20: 700 | K20: 700 | L20: 700 | M20: 700 | N20: 700 | O20: 700 | P20: 700 | Q20: 700
A21: Agua | B21: Mes | C21: 1 | D21: 400 | E21: 400 | F21: 400 | G21: 400 | H21: 400 | I21: 400 | J21: 400 | K21: 400 | L21: 400 | M21: 400 | N21: 400 | O21: 400 | P21: 400 | Q21: 400
A22: Gas estacionario | B22: Mes | C22: 1 | D22: 1200 | E22: 1200 | F22: 1200 | G22: 1200 | H22: 1200 | I22: 1200 | J22: 1200 | K22: 1200 | L22: 1200 | M22: 1200 | N22: 1200 | O22: 1200 | P22: 1200 | Q22: 1200
A23: Limpieza / fumigación | B23: Mes | C23: 1 | D23: 300 | E23: 300 | F23: 300 | G23: 300 | H23: 300 | I23: 300 | J23: 300 | K23: 300 | L23: 300 | M23: 300 | N23: 300 | O23: 300 | P23: 300 | Q23: 300
A24: Nómina operativa | B24: Mes | C24: 16 | D24: 8000 | E24: =D24*C24 -> 128000 | F24: =$E$24 -> 128000 | G24: =$E$24 -> 128000 | H24: =$E$24 -> 128000 | I24: =$E$24 -> 128000 | J24: =$E$24 -> 128000 | K24: =$E$24 -> 128000 | L24: =$E$24 -> 128000 | M24: =$E$24 -> 128000 | ... Q24: =$E$24 -> 128000
A25: Subtotal | E25: =SUM(E20:E23) -> 2600 | F25: =SUM(F20:F23) -> 2600 | G25: =SUM(G20:G23) -> 2600 | H25: =SUM(H20:H23) -> 2600 | I25: =SUM(I20:I23) -> 2600 | J25: =SUM(J20:J23) -> 2600 | K25: =SUM(K20:K23) -> 2600 | L25: =SUM(L20:L23) -> 2600 | ... Q25: =SUM(Q20:Q23) -> 2600 | R25: =SUM(F25:Q25) -> 31200
A28: MEMORIA DE CALCULO GASTOS SOCIALES | F28: MESES
D29: C.U. | E29: TOTAL | F29: 1 | G29: 2 | H29: 3 | I29: 4 | J29: 5 | K29: 6 | L29: 7 | M29: 8 | N29: 9 | O29: 10 | P29: 11 | Q29: 12
A30: Nómina Operativa
A31: Mesero | C31: 3 | D31: =1691.61*4 -> 6766.44 | E31: =D31*C31 -> 20299.32 | F31: =$C$31*$D$31 -> 20299.32 | G31: =$C$31*$D$31 -> 20299.32 | H31: =$C$31*$D$31 -> 20299.32 | I31: =$C$31*$D$31 -> 20299.32 | J31: =$C$31*$D$31 -> 20299.32 | K31: =$C$31*$D$31 -> 20299.32 | L31: =$C$31*$D$31 -> 20299.32 | M31: =$C$31*$D$31 -> 20299.32 | ... Q31: =$C$31*$D$31 -> 20299.32
A32: Verduras, ensaladas y guarniciones | C32: 1 | D32: =1587.08*4 -> 6348.32 | E32: =$C$32*$D$32 -> 6348.32 | F32: =$C$32*$D$32 -> 6348.32 | G32: =$C$32*$D$32 -> 6348.32 | H32: =$C$32*$D$32 -> 6348.32 | I32: =$C$32*$D$32 -> 6348.32 | J32: =$C$32*$D$32 -> 6348.32 | K32: =$C$32*$D$32 -> 6348.32 | L32: =$C$32*$D$32 -> 6348.32 | ... Q32: =$C$32*$D$32 -> 6348.32
A33: Salsas y Járabes | C33: 1 | D33: =1587.08*4 -> 6348.32 | E33: =$C$33*$D$33 -> 6348.32 | F33: =$C$33*$D$33 -> 6348.32 | G33: =$C$33*$D$33 -> 6348.32 | H33: =$C$33*$D$33 -> 6348.32 | I33: =$C$33*$D$33 -> 6348.32 | J33: =$C$33*$D$33 -> 6348.32 | K33: =$C$33*$D$33 -> 6348.32 | L33: =$C$33*$D$33 -> 6348.32 | ... Q33: =$C$33*$D$33 -> 6348.32
A34: Coordinador de parrilla | C34: 1 | D34: =2776.69*4 -> 11106.76 | E34: =$C$34*$D$34 -> 11106.76 | F34: =$C$34*$D$34 -> 11106.76 | G34: =$C$34*$D$34 -> 11106.76 | H34: =$C$34*$D$34 -> 11106.76 | I34: =$C$34*$D$34 -> 11106.76 | J34: =$C$34*$D$34 -> 11106.76 | K34: =$C$34*$D$34 -> 11106.76 | L34: =$C$34*$D$34 -> 11106.76 | ... Q34: =$C$34*$D$34 -> 11106.76
A35: Parrillero plancha | C35: 1 | D35: =2223.75*4 -> 8895 | E35: =$C$35*$D$35 -> 8895 | F35: =$C$35*$D$35 -> 8895 | G35: =$C$35*$D$35 -> 8895 | H35: =$C$35*$D$35 -> 8895 | I35: =$C$35*$D$35 -> 8895 | J35: =$C$35*$D$35 -> 8895 | K35: =$C$35*$D$35 -> 8895 | L35: =$C$35*$D$35 -> 8895 | ... Q35: =$C$35*$D$35 -> 8895
A36: Parrillero vapor | C36: 1 | D36: =1965.59*4 -> 7862.36 | E36: =$C$36*$D$36 -> 7862.36 | F36: =$C$36*$D$36 -> 7862.36 | G36: =$C$36*$D$36 -> 7862.36 | H36: =$C$36*$D$36 -> 7862.36 | I36: =$C$36*$D$36 -> 7862.36 | J36: =$C$36*$D$36 -> 7862.36 | K36: =$C$36*$D$36 -> 7862.36 | L36: =$C$36*$D$36 -> 7862.36 | ... Q36: =$C$36*$D$36 -> 7862.36
A37: Pastorero | C37: 1 | D37: =2223.75*4 -> 8895 | E37: =$C$37*$D$37 -> 8895 | F37: =$C$37*$D$37 -> 8895 | G37: =$C$37*$D$37 -> 8895 | H37: =$C$37*$D$37 -> 8895 | I37: =$C$37*$D$37 -> 8895 | J37: =$C$37*$D$37 -> 8895 | K37: =$C$37*$D$37 -> 8895 | L37: =$C$37*$D$37 -> 8895 | ... Q37: =$C$37*$D$37 -> 8895
A38: Lavatrastes | C38: 1 | D38: =1587.08*4 -> 6348.32 | E38: =$C$38*$D$38 -> 6348.32 | F38: =$C$38*$D$38 -> 6348.32 | G38: =$C$38*$D$38 -> 6348.32 | H38: =$C$38*$D$38 -> 6348.32 | I38: =$C$38*$D$38 -> 6348.32 | J38: =$C$38*$D$38 -> 6348.32 | K38: =$C$38*$D$38 -> 6348.32 | L38: =$C$38*$D$38 -> 6348.32 | ... Q38: =$C$38*$D$38 -> 6348.32
A39: Nómina Administrativa
A40: Gerente general | C40: 1 | D40: =4315.99*4 -> 17263.96 | E40: =$C$40*$D$40 -> 17263.96 | F40: =$C$40*$D$40 -> 17263.96 | G40: =$C$40*$D$40 -> 17263.96 | H40: =$C$40*$D$40 -> 17263.96 | I40: =$C$40*$D$40 -> 17263.96 | J40: =$C$40*$D$40 -> 17263.96 | K40: =$C$40*$D$40 -> 17263.96 | L40: =$C$40*$D$40 -> 17263.96 | ... Q40: =$C$40*$D$40 -> 17263.96
A41: Asesor | C41: 1 | D41: =4301.08*4 -> 17204.32 | E41: =$C$41*$D$41 -> 17204.32 | F41: =$C$41*$D$41 -> 17204.32 | G41: =$C$41*$D$41 -> 17204.32 | H41: =$C$41*$D$41 -> 17204.32 | I41: =$C$41*$D$41 -> 17204.32 | J41: =$C$41*$D$41 -> 17204.32 | K41: =$C$41*$D$41 -> 17204.32 | L41: =$C$41*$D$41 -> 17204.32 | ... Q41: =$C$41*$D$41 -> 17204.32
A42: Cajero | C42: 1 | D42: =2094.39*4 -> 8377.56 | E42: =$C$42*$D$42 -> 8377.56 | F42: =$C$42*$D$42 -> 8377.56 | G42: =$C$42*$D$42 -> 8377.56 | H42: =$C$42*$D$42 -> 8377.56 | I42: =$C$42*$D$42 -> 8377.56 | J42: =$C$42*$D$42 -> 8377.56 | K42: =$C$42*$D$42 -> 8377.56 | L42: =$C$42*$D$42 -> 8377.56 | ... Q42: =$C$42*$D$42 -> 8377.56
A43: Contador | C43: 1 | D43: =3648.64*4 -> 14594.56 | E43: =$C$43*$D$43 -> 14594.56 | F43: =$C$43*$D$43 -> 14594.56 | G43: =$C$43*$D$43 -> 14594.56 | H43: =$C$43*$D$43 -> 14594.56 | I43: =$C$43*$D$43 -> 14594.56 | J43: =$C$43*$D$43 -> 14594.56 | K43: =$C$43*$D$43 -> 14594.56 | L43: =$C$43*$D$43 -> 14594.56 | ... Q43: =$C$43*$D$43 -> 14594.56
A44: Compras | C44: 1 | D44: =3974.86*4 -> 15899.44 | E44: =$C$44*$D$44 -> 15899.44 | F44: =$C$44*$D$44 -> 15899.44 | G44: =$C$44*$D$44 -> 15899.44 | H44: =$C$44*$D$44 -> 15899.44 | I44: =$C$44*$D$44 -> 15899.44 | J44: =$C$44*$D$44 -> 15899.44 | K44: =$C$44*$D$44 -> 15899.44 | L44: =$C$44*$D$44 -> 15899.44 | ... Q44: =$C$44*$D$44 -> 15899.44
A45: Supervisor de envios y calidad | C45: 1 | D45: =2996.21*4 -> 11984.84 | E45: =$C$45*$D$45 -> 11984.84 | F45: =$C$45*$D$45 -> 11984.84 | G45: =$C$45*$D$45 -> 11984.84 | H45: =$C$45*$D$45 -> 11984.84 | I45: =$C$45*$D$45 -> 11984.84 | J45: =$C$45*$D$45 -> 11984.84 | K45: =$C$45*$D$45 -> 11984.84 | L45: =$C$45*$D$45 -> 11984.84 | ... Q45: =$C$45*$D$45 -> 11984.84
A47: Seguro social (IMSS) | B47: Mes | C47: 16 | D47: 192.25 | E47: =$C$47*$D$47 -> 3076 | F47: =$C$47*$D$47 -> 3076 | G47: =$C$47*$D$47 -> 3076 | H47: =$C$47*$D$47 -> 3076 | I47: =$C$47*$D$47 -> 3076 | J47: =$C$47*$D$47 -> 3076 | K47: =$C$47*$D$47 -> 3076 | L47: =$C$47*$D$47 -> 3076 | ... Q47: =$C$47*$D$47 -> 3076
A48: INFONAVIT | B48: Mes | C48: 16 | D48: 1269.8985 | E48: =$C$48*$D$48 -> 20318.376 | F48: =$C$48*$D$48 -> 20318.376 | G48: =$C$48*$D$48 -> 20318.376 | H48: =$C$48*$D$48 -> 20318.376 | I48: =$C$48*$D$48 -> 20318.376 | J48: =$C$48*$D$48 -> 20318.376 | K48: =$C$48*$D$48 -> 20318.376 | L48: =$C$48*$D$48 -> 20318.376 | ... Q48: =$C$48*$D$48 -> 20318.376
A49: Seguro de retiro y cesantía | B49: Mes | C49: 16 | D49: 1085.76 | E49: =$C$49*$D$49 -> 17372.16 | F49: =$C$49*$D$49 -> 17372.16 | G49: =$C$49*$D$49 -> 17372.16 | H49: =$C$49*$D$49 -> 17372.16 | I49: =$C$49*$D$49 -> 17372.16 | J49: =$C$49*$D$49 -> 17372.16 | K49: =$C$49*$D$49 -> 17372.16 | L49: =$C$49*$D$49 -> 17372.16 | ... Q49: =$C$49*$D$49 -> 17372.16
A50: ISR | B50: Mes | C50: 16 | D50: 320.73 | E50: =$C$50*$D$50 -> 5131.68 | F50: =$C$50*$D$50 -> 5131.68 | G50: =$C$50*$D$50 -> 5131.68 | H50: =$C$50*$D$50 -> 5131.68 | I50: =$C$50*$D$50 -> 5131.68 | J50: =$C$50*$D$50 -> 5131.68 | K50: =$C$50*$D$50 -> 5131.68 | L50: =$C$50*$D$50 -> 5131.68 | ... Q50: =$C$50*$D$50 -> 5131.68 | R50: =SUM(E50:Q50) -> 66711.84
A51: Uniformes y protección | B51: Mes | C51: 16 | D51: =400 -> 400 | E51: =400*$C$51 -> 6400 | F51: =$C$51*$D$51 -> 6400 | G51: =$C$51*$D$51 -> 6400 | H51: =$C$51*$D$51 -> 6400 | I51: =$C$51*$D$51 -> 6400 | J51: =$C$51*$D$51 -> 6400 | K51: =$C$51*$D$51 -> 6400 | L51: =$C$51*$D$51 -> 6400 | M51: =$C$51*$D$51 -> 6400 | ... Q51: =$C$51*$D$51 -> 6400
A52: Subtotal | F52: =SUM(F31:F51) -> 213726.3 | G52: =SUM(G31:G51) -> 213726.3 | H52: =SUM(H31:H51) -> 213726.3 | I52: =SUM(I31:I51) -> 213726.3 | J52: =SUM(J31:J51) -> 213726.3 | K52: =SUM(K31:K51) -> 213726.3 | L52: =SUM(L31:L51) -> 213726.3 | M52: =SUM(M31:M51) -> 213726.3 | ... Q52: =SUM(Q31:Q51) -> 213726.3 | R52: =SUM(F52:Q52) -> 2564715.6
A55: MEMORIA DE CALCULO GASTOS FIJOS PARA LA INVERSION FIJA | F55: MESES
A56: CONCEPTO | B56: MEDIDA | C56: CANT | D56: C.U. | E56: TOTAL | F56: 1 | G56: 2 | H56: 3 | I56: 4 | J56: 5 | K56: 6 | L56: 7 | M56: 8 | N56: 9 | O56: 10 | P56: 11 | Q56: 12
A57: Mantenimiento de equipo | B57: Mes | C57: 1 | D57: 300 | E57: 300 | F57: 300 | G57: 300 | H57: 300 | I57: 300 | J57: 300 | K57: 300 | L57: 300 | M57: 300 | N57: 300 | O57: 300 | P57: 300 | Q57: 300
A58: Sustitución de mobiliario | B58: Mes | C58: 1 | D58: 200 | E58: 200 | F58: 200 | G58: 200 | H58: 200 | I58: 200 | J58: 200 | K58: 200 | L58: 200 | M58: 200 | N58: 200 | O58: 200 | P58: 200 | Q58: 200
A59: Herramientas menores | B59: Mes | C59: 1 | D59: 250 | E59: 250 | F59: 250 | G59: 250 | H59: 250 | I59: 250 | J59: 250 | K59: 250 | L59: 250 | M59: 250 | N59: 250 | O59: 250 | P59: 250 | Q59: 250
A60: Pintura / remodelaciones | B60: Mes | C60: 1 | D60: 150 | E60: 150 | F60: 150 | G60: 150 | H60: 150 | I60: 150 | J60: 150 | K60: 150 | L60: 150 | M60: 150 | N60: 150 | O60: 150 | P60: 150 | Q60: 150
A61: Repuestos / accesorios | B61: Mes | C61: 1 | D61: 100 | E61: 100 | F61: 100 | G61: 100 | H61: 100 | I61: 100 | J61: 100 | K61: 100 | L61: 100 | M61: 100 | N61: 100 | O61: 100 | P61: 100 | Q61: 100
A62: Subtotal | E62: =SUM(E57:E61) -> 1000 | F62: =SUM(F57:F61) -> 1000 | G62: =SUM(G57:G61) -> 1000 | H62: =SUM(H57:H61) -> 1000 | I62: =SUM(I57:I61) -> 1000 | J62: =SUM(J57:J61) -> 1000 | K62: =SUM(K57:K61) -> 1000 | L62: =SUM(L57:L61) -> 1000 | ... Q62: =SUM(Q57:Q61) -> 1000 | R62: =SUM(F62:Q62) -> 12000
Q65: TOTAL | R65: =SUM(R62+R52+R25+R15) -> 2835915.6

Sheet COSTOS 
A2: COSTOS DE PRODUCCION AÑO 1
A3: VARIABLES | B3: 1 | C3: 2 | D3: 3 | E3: 4 | F3: 5 | G3: 6 | H3: 7 | I3: 8 | J3: 9 | K3: 10 | L3: 11 | M3: 12 | N3: TOTAL | Q3: VARIABLES | R3: AÑO 1 | S3: AÑO 2 | T3: AÑO 3 | U3: AÑO 4 | V3: AÑO 5
A4: TOTAL VARIABLES | B4: =SUM(B5:B15) -> 193560 | C4: =SUM(C5:C15) -> 197431.2 | D4: =SUM(D5:D15) -> 193482.58 | E4: =SUM(E5:E15) -> 199287.05 | F4: =SUM(F5:F15) -> 203272.79 | G4: =SUM(G5:G15) -> 197174.61 | H4: =SUM(H5:H15) -> 195202.86 | I4: =SUM(I5:I15) -> 199106.92 | ... N4: =SUM(N5:N15) -> 2364831.1 | Q4: TOTAL VARIABLES | R4: =SUM(R5:R16) -> 2364831.1 | S4: =SUM(S5:S16) -> 2455457.9 | T4: =SUM(T5:T16) -> 2549557.7 | U4: =SUM(U5:U16) -> 2647263.7 | V4: =SUM(V5:V16) -> 2748714
A5: ='M. DE CALCULO DE COSTOS VAR'!A12 -> Carne de cerdo adobada al pastor | B5: ='M. DE CALCULO DE COSTOS VAR'!E12+'M. DE CALCULO DE COSTOS VAR'!Q12 -> 114000 | C5: =B5*1.02 -> 116280 | D5: =C5*0.98 -> 113954.4 | E5: =D5*1.03 -> 117373.03 | F5: =E5*1.02 -> 119720.49 | G5: =F5*0.97 -> 116128.88 | H5: =G5*0.99 -> 114967.59 | I5: =H5*1.02 -> 117266.94 | J5: =I5*0.98 -> 114921.6 | K5: =J5*0.99 -> 113772.39 | L5: =K5*1.02 -> 116047.83 | M5: =1.02*L5 -> 118368.79 | N5: =SUM(B5:M5) -> 1392801.9 | Q5: =A5 -> Carne de cerdo adobada al pastor | R5: =N5 -> 1392801.9 | S5: =N58 -> 1446177.9 | T5: =N111 -> 1501599.4 | U5: =N164 -> 1559144.8 | V5: =N217 -> 1618895.4
A6: ='M. DE CALCULO DE COSTOS VAR'!A13 -> Tortilla de maíz | B6: ='M. DE CALCULO DE COSTOS VAR'!E13+'M. DE CALCULO DE COSTOS VAR'!Q14 -> 4560 | C6: =B6*1.02 -> 4651.2 | D6: =C6*0.98 -> 4558.176 | E6: =D6*1.03 -> 4694.9213 | F6: =E6*1.02 -> 4788.8197 | G6: =F6*0.97 -> 4645.1551 | H6: =G6*0.99 -> 4598.7036 | I6: =H6*1.02 -> 4690.6776 | J6: =I6*0.98 -> 4596.8641 | K6: =J6*0.99 -> 4550.8954 | L6: =K6*1.02 -> 4641.9133 | M6: =1.02*L6 -> 4734.7516 | N6: =SUM(B6:M6) -> 55712.078 | Q6: =A6 -> Tortilla de maíz | R6: =N6 -> 55712.078 | S6: =N59 -> 57847.116 | T6: =N112 -> 60063.975 | U6: =N165 -> 62365.79 | V6: =N218 -> 64755.817
A7: ='M. DE CALCULO DE COSTOS VAR'!A14 -> Piña | B7: ='M. DE CALCULO DE COSTOS VAR'!E14 -> 2400 | C7: =B7*1.02 -> 2448 | D7: =C7*0.98 -> 2399.04 | E7: =D7*1.03 -> 2471.0112 | F7: =E7*1.02 -> 2520.4314 | G7: =F7*0.97 -> 2444.8185 | H7: =G7*0.99 -> 2420.3703 | I7: =H7*1.02 -> 2468.7777 | J7: =I7*0.98 -> 2419.4021 | K7: =J7*0.99 -> 2395.2081 | L7: =K7*1.02 -> 2443.1123 | M7: =1.02*L7 -> 2491.9745 | N7: =SUM(B7:M7) -> 29322.146 | Q7: =A7 -> Piña | R7: =N7 -> 29322.146 | S7: =N60 -> 30445.851 | T7: =N113 -> 31612.619 | U7: =N166 -> 32824.1 | V7: =N219 -> 34082.009
A8: ='M. DE CALCULO DE COSTOS VAR'!A15 -> Cebolla | B8: ='M. DE CALCULO DE COSTOS VAR'!E15 -> 1200 | C8: =B8*1.02 -> 1224 | D8: =C8*0.98 -> 1199.52 | E8: =D8*1.03 -> 1235.5056 | F8: =E8*1.02 -> 1260.2157 | G8: =F8*0.97 -> 1222.4092 | H8: =G8*0.99 -> 1210.1851 | I8: =H8*1.02 -> 1234.3889 | J8: =I8*0.98 -> 1209.7011 | K8: =J8*0.99 -> 1197.6041 | L8: =K8*1.02 -> 1221.5561 | M8: =1.02*L8 -> 1245.9873 | N8: =SUM(B8:M8) -> 14661.073 | Q8: =A8 -> Cebolla | R8: =N8 -> 14661.073 | S8: =N61 -> 15222.925 | T8: =N114 -> 15806.309 | U8: =N167 -> 16412.05 | V8: =N220 -> 17041.005
A9: ='M. DE CALCULO DE COSTOS VAR'!A16 -> Cilantro | B9: ='M. DE CALCULO DE COSTOS VAR'!E16 -> 1200 | C9: =B9*1.02 -> 1224 | D9: =C9*0.98 -> 1199.52 | E9: =D9*1.03 -> 1235.5056 | F9: =E9*1.02 -> 1260.2157 | G9: =F9*0.97 -> 1222.4092 | H9: =G9*0.99 -> 1210.1851 | I9: =H9*1.02 -> 1234.3889 | J9: =I9*0.98 -> 1209.7011 | K9: =J9*0.99 -> 1197.6041 | L9: =K9*1.02 -> 1221.5561 | M9: =1.02*L9 -> 1245.9873 | N9: =SUM(B9:M9) -> 14661.073 | Q9: =A9 -> Cilantro | R9: =N9 -> 14661.073 | S9: =N62 -> 15222.925 | T9: =N115 -> 15806.309 | U9: =N168 -> 16412.05 | V9: =N221 -> 17041.005
A10: {='M. DE CALCULO DE COSTOS VAR'!G12:G13} -> Carne de cerdo marinada estilo oriental | B10: ='M. DE CALCULO DE COSTOS VAR'!K12 -> 45000 | C10: =B10*1.02 -> 45900 | D10: =C10*0.98 -> 44982 | E10: =D10*1.03 -> 46331.46 | F10: =E10*1.02 -> 47258.089 | G10: =F10*0.97 -> 45840.347 | H10: =G10*0.99 -> 45381.943 | I10: =H10*1.02 -> 46289.582 | J10: =I10*0.98 -> 45363.79 | K10: =J10*0.99 -> 44910.152 | L10: =K10*1.02 -> 45808.355 | M10: =1.02*L10 -> 46724.523 | N10: =SUM(B10:M10) -> 549790.24 | Q10: =A10 -> Carne de cerdo marinada estilo oriental | R10: =N10 -> 549790.24 | S10: =N63 -> 570859.7 | T10: =N116 -> 592736.6 | U10: =N169 -> 615451.88 | V10: =N222 -> 639037.67
A11: Pan árabe (Pita) | B11: ='M. DE CALCULO DE COSTOS VAR'!K13 -> 3600 | C11: =B11*1.02 -> 3672 | D11: =C11*0.98 -> 3598.56 | E11: =D11*1.03 -> 3706.5168 | F11: =E11*1.02 -> 3780.6471 | G11: =F11*0.97 -> 3667.2277 | H11: =G11*0.99 -> 3630.5554 | I11: =H11*1.02 -> 3703.1666 | J11: =I11*0.98 -> 3629.1032 | K11: =J11*0.99 -> 3592.8122 | L11: =K11*1.02 -> 3664.6684 | M11: =1.02*L11 -> 3737.9618 | N11: =SUM(B11:M11) -> 43983.219 | Q11: =A11 -> Pan árabe (Pita) | R11: =N11 -> 43983.219 | S11: =N64 -> 45668.776 | T11: =N117 -> 47418.928 | U11: =N170 -> 49236.15 | V11: =N223 -> 51123.014
A12: ='M. DE CALCULO DE COSTOS VAR'!M13 -> Tocino | B12: ='M. DE CALCULO DE COSTOS VAR'!Q13 -> 12600 | C12: =B12*1.02 -> 12852 | D12: =C12*0.98 -> 12594.96 | E12: =D12*1.03 -> 12972.809 | F12: =E12*1.02 -> 13232.265 | G12: =F12*0.97 -> 12835.297 | H12: =G12*0.99 -> 12706.944 | I12: =H12*1.02 -> 12961.083 | J12: =I12*0.98 -> 12701.861 | K12: =J12*0.99 -> 12574.843 | L12: =K12*1.02 -> 12826.34 | M12: =1.02*L12 -> 13082.866 | N12: =SUM(B12:M12) -> 153941.27 | Q12: =A12 -> Tocino | R12: =N12 -> 153941.27 | S12: =N65 -> 159840.72 | T12: =N118 -> 165966.25 | U12: =N171 -> 172326.53 | V12: =N224 -> 178930.55
A13: {='M. DE CALCULO DE COSTOS VAR'!M15:M17} -> Chile poblano | B13: ='M. DE CALCULO DE COSTOS VAR'!Q15 -> 3600 | C13: =B13*1.02 -> 3672 | D13: =C13*0.98 -> 3598.56 | E13: =D13*1.03 -> 3706.5168 | F13: =E13*1.02 -> 3780.6471 | G13: =F13*0.97 -> 3667.2277 | H13: =G13*0.99 -> 3630.5554 | I13: =H13*1.02 -> 3703.1666 | J13: =I13*0.98 -> 3629.1032 | K13: =J13*0.99 -> 3592.8122 | L13: =K13*1.02 -> 3664.6684 | M13: =1.02*L13 -> 3737.9618 | N13: =SUM(B13:M13) -> 43983.219 | Q13: =A13 -> Chile poblano | R13: =N13 -> 43983.219 | S13: =N66 -> 45668.776 | T13: =N119 -> 47418.928 | U13: =N172 -> 49236.15 | V13: =N225 -> 51123.014
A14: Cebolla | B14: ='M. DE CALCULO DE COSTOS VAR'!Q16 -> 3000 | C14: =B14*1.02 -> 3060 | D14: =C14*0.98 -> 2998.8 | E14: =D14*1.03 -> 3088.764 | F14: =E14*1.02 -> 3150.5393 | G14: =F14*0.97 -> 3056.0231 | H14: =G14*0.99 -> 3025.4629 | I14: =H14*1.02 -> 3085.9721 | J14: =I14*0.98 -> 3024.2527 | K14: =J14*0.99 -> 2994.0102 | L14: =K14*1.02 -> 3053.8904 | M14: =1.02*L14 -> 3114.9682 | N14: =SUM(B14:M14) -> 36652.683 | Q14: =A14 -> Cebolla | R14: =N14 -> 36652.683 | S14: =N67 -> 38057.313 | T14: =N120 -> 39515.773 | U14: =N173 -> 41030.125 | V14: =N226 -> 42602.511
A15: Jitomate | B15: ='M. DE CALCULO DE COSTOS VAR'!Q17 -> 2400 | C15: =B15*1.02 -> 2448 | D15: =C15*0.98 -> 2399.04 | E15: =D15*1.03 -> 2471.0112 | F15: =E15*1.02 -> 2520.4314 | G15: =F15*0.97 -> 2444.8185 | H15: =G15*0.99 -> 2420.3703 | I15: =H15*1.02 -> 2468.7777 | J15: =I15*0.98 -> 2419.4021 | K15: =J15*0.99 -> 2395.2081 | L15: =K15*1.02 -> 2443.1123 | M15: =1.02*L15 -> 2491.9745 | N15: =SUM(B15:M15) -> 29322.146 | Q15: =A15 -> Jitomate | R15: =N15 -> 29322.146 | S15: =N68 -> 30445.851 | T15: =N121 -> 31612.619 | U15: =N174 -> 32824.1 | V15: =N227 -> 34082.009
A16: TOTAL FIJOS | B16: =SUM(B17:B41,B46:B52) -> 207422.46 | C16: =SUM(C17:C41,C46:C52) -> 207422.46 | D16: =SUM(D17:D41,D46:D52) -> 207422.46 | E16: =SUM(E17:E41,E46:E52) -> 207422.46 | F16: =SUM(F17:F41,F46:F52) -> 207422.46 | G16: =SUM(G17:G41,G46:G52) -> 207422.46 | H16: =SUM(H17:H41,H46:H52) -> 207422.46 | I16: =SUM(I17:I41,I46:I52) -> 207422.46 | ... N16: =SUM(N17:N41,N46:N52) -> 2489069.5
A17: ='M. DE CALCULO DE GASTOS FIJO'!A10 -> Renta del local | B17: {='M. DE CALCULO DE GASTOS FIJO'!E10:E14} -> 16000 | C17: =B17 -> 16000 | D17: =C17 -> 16000 | E17: =D17 -> 16000 | F17: =E17 -> 16000 | G17: =F17 -> 16000 | H17: =G17 -> 16000 | I17: =H17 -> 16000 | J17: =I17 -> 16000 | ... M17: =L17 -> 16000 | N17: =SUM(B17:M17) -> 192000 | Q17: TOTAL FIJOS | R17: =N16 -> 2489069.5 | S17: =N69 -> 2489069.5 | T17: =N122 -> 2489069.5 | U17: =N175 -> 2489069.5 | V17: =N228 -> 2489069.5
A18: ='M. DE CALCULO DE GASTOS FIJO'!A11 -> Internet / teléfono | B18: 600 | C18: =B18 -> 600 | D18: =C18 -> 600 | E18: =D18 -> 600 | F18: =E18 -> 600 | G18: =F18 -> 600 | H18: =G18 -> 600 | I18: =H18 -> 600 | J18: =I18 -> 600 | ... M18: =L18 -> 600 | N18: =SUM(B18:M18) -> 7200 | Q18: =A17 -> Renta del local | R18: =M17 -> 16000 | S18: =R18 -> 16000 | T18: =S18 -> 16000 | U18: =T18 -> 16000 | V18: =U18 -> 16000
A19: ='M. DE CALCULO DE GASTOS FIJO'!A12 -> Permisos y licencias | B19: 400 | C19: =B19 -> 400 | D19: =C19 -> 400 | E19: =D19 -> 400 | F19: =E19 -> 400 | G19: =F19 -> 400 | H19: =G19 -> 400 | I19: =H19 -> 400 | J19: =I19 -> 400 | ... M19: =L19 -> 400 | N19: =SUM(B19:M19) -> 4800 | Q19: =A18 -> Internet / teléfono | R19: =M18 -> 600 | S19: =R19 -> 600 | T19: =S19 -> 600 | U19: =T19 -> 600 | V19: =U19 -> 600
A20: ='M. DE CALCULO DE GASTOS FIJO'!A13 -> Mantenimiento | B20: 500 | C20: =B20 -> 500 | D20: =C20 -> 500 | E20: =D20 -> 500 | F20: =E20 -> 500 | G20: =F20 -> 500 | H20: =G20 -> 500 | I20: =H20 -> 500 | J20: =I20 -> 500 | ... M20: =L20 -> 500 | N20: =SUM(B20:M20) -> 6000 | Q20: =A19 -> Permisos y licencias | R20: =M19 -> 400 | S20: =R20 -> 400 | T20: =S20 -> 400 | U20: =T20 -> 400 | V20: =U20 -> 400
A21: ='M. DE CALCULO DE GASTOS FIJO'!A14 -> Depreciaciones | B21: 1500 | C21: =B21 -> 1500 | D21: =C21 -> 1500 | E21: =D21 -> 1500 | F21: =E21 -> 1500 | G21: =F21 -> 1500 | H21: =G21 -> 1500 | I21: =H21 -> 1500 | J21: =I21 -> 1500 | ... M21: =L21 -> 1500 | N21: =SUM(B21:M21) -> 18000 | Q21: =A20 -> Mantenimiento | R21: =M20 -> 500 | S21: =R21 -> 500 | T21: =S21 -> 500 | U21: =T21 -> 500 | V21: =U21 -> 500
A22: {='M. DE CALCULO DE GASTOS FIJO'!A20:A23} -> Energía eléctrica (Pago bimestral) | B22: {='M. DE CALCULO DE GASTOS FIJO'!E20:E23} -> 700 | C22: =B22 -> 700 | D22: =C22 -> 700 | E22: =D22 -> 700 | F22: =E22 -> 700 | G22: =F22 -> 700 | H22: =G22 -> 700 | I22: =H22 -> 700 | J22: =I22 -> 700 | ... M22: =L22 -> 700 | N22: =SUM(B22:M22) -> 8400 | Q22: =A21 -> Depreciaciones | R22: =M21 -> 1500 | S22: =R22 -> 1500 | T22: =S22 -> 1500 | U22: =T22 -> 1500 | V22: =U22 -> 1500 | Y22: v
A23: Agua | B23: 400 | C23: =B23 -> 400 | D23: =C23 -> 400 | E23: =D23 -> 400 | F23: =E23 -> 400 | G23: =F23 -> 400 | H23: =G23 -> 400 | I23: =H23 -> 400 | J23: =I23 -> 400 | ... M23: =L23 -> 400 | N23: =SUM(B23:M23) -> 4800 | Q23: =A22 -> Energía eléctrica (Pago bimestral) | R23: =M22 -> 700 | S23: =R23 -> 700 | T23: =S23 -> 700 | U23: =T23 -> 700 | V23: =U23 -> 700
A24: Gas estacionario | B24: 1200 | C24: =B24 -> 1200 | D24: =C24 -> 1200 | E24: =D24 -> 1200 | F24: =E24 -> 1200 | G24: =F24 -> 1200 | H24: =G24 -> 1200 | I24: =H24 -> 1200 | J24: =I24 -> 1200 | ... M24: =L24 -> 1200 | N24: =SUM(B24:M24) -> 14400 | Q24: =A23 -> Agua | R24: =M23 -> 400 | S24: =R24 -> 400 | T24: =S24 -> 400 | U24: =T24 -> 400 | V24: =U24 -> 400
A25: Limpieza / fumigación | B25: 300 | C25: =B25 -> 300 | D25: =C25 -> 300 | E25: =D25 -> 300 | F25: =E25 -> 300 | G25: =F25 -> 300 | H25: =G25 -> 300 | I25: =H25 -> 300 | J25: =I25 -> 300 | ... M25: =L25 -> 300 | N25: =SUM(B25:M25) -> 3600 | Q25: =A24 -> Gas estacionario | R25: =M24 -> 1200 | S25: =R25 -> 1200 | T25: =S25 -> 1200 | U25: =T25 -> 1200 | V25: =U25 -> 1200
A26: {='M. DE CALCULO DE GASTOS FIJO'!A31:A38} -> Mesero | B26: {='M. DE CALCULO DE GASTOS FIJO'!E31:E38} -> 20299.32 | C26: =B26 -> 20299.32 | D26: =C26 -> 20299.32 | E26: =D26 -> 20299.32 | F26: =E26 -> 20299.32 | G26: =F26 -> 20299.32 | H26: =G26 -> 20299.32 | I26: =H26 -> 20299.32 | J26: =I26 -> 20299.32 | ... M26: =L26 -> 20299.32 | N26: =SUM(B26:M26) -> 243591.84 | Q26: =A25 -> Limpieza / fumigación | R26: =M25 -> 300 | S26: =R26 -> 300 | T26: =S26 -> 300 | U26: =T26 -> 300 | V26: =U26 -> 300
A27: Verduras, ensaladas y guarniciones | B27: 6348.32 | C27: =B27 -> 6348.32 | D27: =C27 -> 6348.32 | E27: =D27 -> 6348.32 | F27: =E27 -> 6348.32 | G27: =F27 -> 6348.32 | H27: =G27 -> 6348.32 | I27: =H27 -> 6348.32 | J27: =I27 -> 6348.32 | ... M27: =L27 -> 6348.32 | N27: =SUM(B27:M27) -> 76179.84 | Q27: =A26 -> Mesero | R27: =M26 -> 20299.32 | S27: =R27 -> 20299.32 | T27: =S27 -> 20299.32 | U27: =T27 -> 20299.32 | V27: =U27 -> 20299.32
A28: Salsas y Járabes | B28: 6348.32 | C28: =B28 -> 6348.32 | D28: =C28 -> 6348.32 | E28: =D28 -> 6348.32 | F28: =E28 -> 6348.32 | G28: =F28 -> 6348.32 | H28: =G28 -> 6348.32 | I28: =H28 -> 6348.32 | J28: =I28 -> 6348.32 | ... M28: =L28 -> 6348.32 | N28: =SUM(B28:M28) -> 76179.84 | Q28: =A27 -> Verduras, ensaladas y guarniciones | R28: =M27 -> 6348.32 | S28: =R28 -> 6348.32 | T28: =S28 -> 6348.32 | U28: =T28 -> 6348.32 | V28: =U28 -> 6348.32
A29: Coordinador de parrilla | B29: 11106.76 | C29: =B29 -> 11106.76 | D29: =C29 -> 11106.76 | E29: =D29 -> 11106.76 | F29: =E29 -> 11106.76 | G29: =F29 -> 11106.76 | H29: =G29 -> 11106.76 | I29: =H29 -> 11106.76 | J29: =I29 -> 11106.76 | ... M29: =L29 -> 11106.76 | N29: =SUM(B29:M29) -> 133281.12 | Q29: =A28 -> Salsas y Járabes | R29: =M28 -> 6348.32 | S29: =R29 -> 6348.32 | T29: =S29 -> 6348.32 | U29: =T29 -> 6348.32 | V29: =U29 -> 6348.32
A30: Parrillero plancha | B30: 8895 | C30: =B30 -> 8895 | D30: =C30 -> 8895 | E30: =D30 -> 8895 | F30: =E30 -> 8895 | G30: =F30 -> 8895 | H30: =G30 -> 8895 | I30: =H30 -> 8895 | J30: =I30 -> 8895 | ... M30: =L30 -> 8895 | N30: =SUM(B30:M30) -> 106740 | Q30: =A29 -> Coordinador de parrilla | R30: =M29 -> 11106.76 | S30: =R30 -> 11106.76 | T30: =S30 -> 11106.76 | U30: =T30 -> 11106.76 | V30: =U30 -> 11106.76
A31: Parrillero vapor | B31: 7862.36 | C31: =B31 -> 7862.36 | D31: =C31 -> 7862.36 | E31: =D31 -> 7862.36 | F31: =E31 -> 7862.36 | G31: =F31 -> 7862.36 | H31: =G31 -> 7862.36 | I31: =H31 -> 7862.36 | J31: =I31 -> 7862.36 | ... M31: =L31 -> 7862.36 | N31: =SUM(B31:M31) -> 94348.32 | Q31: =A30 -> Parrillero plancha | R31: =M30 -> 8895 | S31: =R31 -> 8895 | T31: =S31 -> 8895 | U31: =T31 -> 8895 | V31: =U31 -> 8895
A32: Pastorero | B32: 8895 | C32: =B32 -> 8895 | D32: =C32 -> 8895 | E32: =D32 -> 8895 | F32: =E32 -> 8895 | G32: =F32 -> 8895 | H32: =G32 -> 8895 | I32: =H32 -> 8895 | J32: =I32 -> 8895 | ... M32: =L32 -> 8895 | N32: =SUM(B32:M32) -> 106740 | Q32: =A31 -> Parrillero vapor | R32: =M31 -> 7862.36 | S32: =R32 -> 7862.36 | T32: =S32 -> 7862.36 | U32: =T32 -> 7862.36 | V32: =U32 -> 7862.36
A33: Lavatrastes | B33: 6348.32 | C33: =B33 -> 6348.32 | D33: =C33 -> 6348.32 | E33: =D33 -> 6348.32 | F33: =E33 -> 6348.32 | G33: =F33 -> 6348.32 | H33: =G33 -> 6348.32 | I33: =H33 -> 6348.32 | J33: =I33 -> 6348.32 | ... M33: =L33 -> 6348.32 | N33: =SUM(B33:M33) -> 76179.84 | Q33: =A32 -> Pastorero | R33: =M32 -> 8895 | S33: =R33 -> 8895 | T33: =S33 -> 8895 | U33: =T33 -> 8895 | V33: =U33 -> 8895
A34: {='M. DE CALCULO DE GASTOS FIJO'!A40:A45} -> Gerente general | B34: {='M. DE CALCULO DE GASTOS FIJO'!E40:E45} -> 17263.96 | C34: =B34 -> 17263.96 | D34: =C34 -> 17263.96 | E34: =D34 -> 17263.96 | F34: =E34 -> 17263.96 | G34: =F34 -> 17263.96 | H34: =G34 -> 17263.96 | I34: =H34 -> 17263.96 | J34: =I34 -> 17263.96 | ... M34: =L34 -> 17263.96 | N34: =SUM(B34:M34) -> 207167.52 | Q34: =A33 -> Lavatrastes | R34: =M33 -> 6348.32 | S34: =R34 -> 6348.32 | T34: =S34 -> 6348.32 | U34: =T34 -> 6348.32 | V34: =U34 -> 6348.32
A35: Asesor | B35: 17204.32 | C35: =B35 -> 17204.32 | D35: =C35 -> 17204.32 | E35: =D35 -> 17204.32 | F35: =E35 -> 17204.32 | G35: =F35 -> 17204.32 | H35: =G35 -> 17204.32 | I35: =H35 -> 17204.32 | J35: =I35 -> 17204.32 | ... M35: =L35 -> 17204.32 | N35: =SUM(B35:M35) -> 206451.84 | Q35: =A34 -> Gerente general | R35: =M34 -> 17263.96 | S35: =R35 -> 17263.96 | T35: =S35 -> 17263.96 | U35: =T35 -> 17263.96 | V35: =U35 -> 17263.96
A36: Cajero | B36: 8377.56 | C36: =B36 -> 8377.56 | D36: =C36 -> 8377.56 | E36: =D36 -> 8377.56 | F36: =E36 -> 8377.56 | G36: =F36 -> 8377.56 | H36: =G36 -> 8377.56 | I36: =H36 -> 8377.56 | J36: =I36 -> 8377.56 | ... M36: =L36 -> 8377.56 | N36: =SUM(B36:M36) -> 100530.72 | Q36: =A35 -> Asesor | R36: =M35 -> 17204.32 | S36: =R36 -> 17204.32 | T36: =S36 -> 17204.32 | U36: =T36 -> 17204.32 | V36: =U36 -> 17204.32
A37: Contador | B37: 14594.56 | C37: =B37 -> 14594.56 | D37: =C37 -> 14594.56 | E37: =D37 -> 14594.56 | F37: =E37 -> 14594.56 | G37: =F37 -> 14594.56 | H37: =G37 -> 14594.56 | I37: =H37 -> 14594.56 | J37: =I37 -> 14594.56 | ... M37: =L37 -> 14594.56 | N37: =SUM(B37:M37) -> 175134.72 | Q37: =A36 -> Cajero | R37: =M36 -> 8377.56 | S37: =R37 -> 8377.56 | T37: =S37 -> 8377.56 | U37: =T37 -> 8377.56 | V37: =U37 -> 8377.56
A38: Compras | B38: 15899.44 | C38: =B38 -> 15899.44 | D38: =C38 -> 15899.44 | E38: =D38 -> 15899.44 | F38: =E38 -> 15899.44 | G38: =F38 -> 15899.44 | H38: =G38 -> 15899.44 | I38: =H38 -> 15899.44 | J38: =I38 -> 15899.44 | ... M38: =L38 -> 15899.44 | N38: =SUM(B38:M38) -> 190793.28 | Q38: =A37 -> Contador | R38: =M37 -> 14594.56 | S38: =R38 -> 14594.56 | T38: =S38 -> 14594.56 | U38: =T38 -> 14594.56 | V38: =U38 -> 14594.56
A39: Supervisor de envios y calidad | B39: 11984.84 | C39: =B39 -> 11984.84 | D39: =C39 -> 11984.84 | E39: =D39 -> 11984.84 | F39: =E39 -> 11984.84 | G39: =F39 -> 11984.84 | H39: =G39 -> 11984.84 | I39: =H39 -> 11984.84 | J39: =I39 -> 11984.84 | ... M39: =L39 -> 11984.84 | N39: =SUM(B39:M39) -> 143818.08 | Q39: =A38 -> Compras | R39: =M38 -> 15899.44 | S39: =R39 -> 15899.44 | T39: =S39 -> 15899.44 | U39: =T39 -> 15899.44 | V39: =U39 -> 15899.44
A40: {='M. DE CALCULO DE GASTOS FIJO'!A47:A51} -> Seguro social (IMSS) | B40: {='M. DE CALCULO DE GASTOS FIJO'!E47:E51} -> 3076 | C40: =B40 -> 3076 | D40: =C40 -> 3076 | E40: =D40 -> 3076 | F40: =E40 -> 3076 | G40: =F40 -> 3076 | H40: =G40 -> 3076 | I40: =H40 -> 3076 | J40: =I40 -> 3076 | ... M40: =L40 -> 3076 | N40: =SUM(B40:M40) -> 36912 | Q40: =A39 -> Supervisor de envios y calidad | R40: =M39 -> 11984.84 | S40: =R40 -> 11984.84 | T40: =S40 -> 11984.84 | U40: =T40 -> 11984.84 | V40: =U40 -> 11984.84
A41: INFONAVIT | B41: 20318.376 | C41: =B41 -> 20318.376 | D41: =C41 -> 20318.376 | E41: =D41 -> 20318.376 | F41: =E41 -> 20318.376 | G41: =F41 -> 20318.376 | H41: =G41 -> 20318.376 | I41: =H41 -> 20318.376 | J41: =I41 -> 20318.376 | ... M41: =L41 -> 20318.376 | N41: =SUM(B41:M41) -> 243820.51 | Q41: =A40 -> Seguro social (IMSS) | R41: =M40 -> 3076 | S41: =R41 -> 3076 | T41: =S41 -> 3076 | U41: =T41 -> 3076 | V41: =U41 -> 3076
A42: Seguro de retiro y cesantía | B42: 17372.16 | C42: =B42 -> 17372.16 | D42: =C42 -> 17372.16 | E42: =D42 -> 17372.16 | F42: =E42 -> 17372.16 | G42: =F42 -> 17372.16 | H42: =G42 -> 17372.16 | I42: =H42 -> 17372.16 | J42: =I42 -> 17372.16 | ... M42: =L42 -> 17372.16 | N42: =SUM(B42:M42) -> 208465.92 | Q42: =A41 -> INFONAVIT | R42: =M41 -> 20318.376 | S42: =R42 -> 20318.376 | T42: =S42 -> 20318.376 | U42: =T42 -> 20318.376 | V42: =U42 -> 20318.376
A43: ISR | B43: 5131.68 | C43: =B43 -> 5131.68 | D43: =C43 -> 5131.68 | E43: =D43 -> 5131.68 | F43: =E43 -> 5131.68 | G43: =F43 -> 5131.68 | H43: =G43 -> 5131.68 | I43: =H43 -> 5131.68 | J43: =I43 -> 5131.68 | ... M43: =L43 -> 5131.68 | N43: =SUM(B43:M43) -> 61580.16 | Q43: =A42 -> Seguro de retiro y cesantía | R43: =M42 -> 17372.16 | S43: =R43 -> 17372.16 | T43: =S43 -> 17372.16 | U43: =T43 -> 17372.16 | V43: =U43 -> 17372.16
A44: Uniformes y protección | B44: 6400 | C44: =B44 -> 6400 | D44: =C44 -> 6400 | E44: =D44 -> 6400 | F44: =E44 -> 6400 | G44: =F44 -> 6400 | H44: =G44 -> 6400 | I44: =H44 -> 6400 | J44: =I44 -> 6400 | ... M44: =L44 -> 6400 | N44: =SUM(B44:M44) -> 76800 | Q44: =A43 -> ISR | R44: =M43 -> 5131.68 | S44: =R44 -> 5131.68 | T44: =S44 -> 5131.68 | U44: =T44 -> 5131.68 | V44: =U44 -> 5131.68
C45: =B45 -> 0 | D45: =C45 -> 0 | E45: =D45 -> 0 | F45: =E45 -> 0 | G45: =F45 -> 0 | H45: =G45 -> 0 | I45: =H45 -> 0 | J45: =I45 -> 0 | ... M45: =L45 -> 0 | N45: =SUM(B45:M45) -> 0 | Q45: =A44 -> Uniformes y protección | R45: =M44 -> 6400 | S45: =R45 -> 6400 | T45: =S45 -> 6400 | U45: =T45 -> 6400 | V45: =U45 -> 6400
C46: =B46 -> 0 | D46: =C46 -> 0 | E46: =D46 -> 0 | F46: =E46 -> 0 | G46: =F46 -> 0 | H46: =G46 -> 0 | I46: =H46 -> 0 | J46: =I46 -> 0 | ... M46: =L46 -> 0 | N46: =SUM(B46:M46) -> 0 | Q46: =A45 -> 0 | R46: =M45 -> 0 | S46: =R46 -> 0 | T46: =S46 -> 0 | U46: =T46 -> 0 | V46: =U46 -> 0
C47: =B47 -> 0 | D47: =C47 -> 0 | E47: =D47 -> 0 | F47: =E47 -> 0 | G47: =F47 -> 0 | H47: =G47 -> 0 | I47: =H47 -> 0 | J47: =I47 -> 0 | ... M47: =L47 -> 0 | N47: =SUM(B47:M47) -> 0 | Q47: =A46 -> 0 | R47: =M46 -> 0 | S47: =R47 -> 0 | T47: =S47 -> 0 | U47: =T47 -> 0 | V47: =U47 -> 0
A48: {='M. DE CALCULO DE GASTOS FIJO'!A57:A61} -> Mantenimiento de equipo | B48: {='M. DE CALCULO DE GASTOS FIJO'!E57:E61} -> 300 | C48: =B48 -> 300 | D48: =C48 -> 300 | E48: =D48 -> 300 | F48: =E48 -> 300 | G48: =F48 -> 300 | H48: =G48 -> 300 | I48: =H48 -> 300 | J48: =I48 -> 300 | ... M48: =L48 -> 300 | N48: =SUM(B48:M48) -> 3600 | Q48: =A47 -> 0 | R48: =M47 -> 0 | S48: =R48 -> 0 | T48: =S48 -> 0 | U48: =T48 -> 0 | V48: =U48 -> 0
A49: Sustitución de mobiliario | B49: 200 | C49: =B49 -> 200 | D49: =C49 -> 200 | E49: =D49 -> 200 | F49: =E49 -> 200 | G49: =F49 -> 200 | H49: =G49 -> 200 | I49: =H49 -> 200 | J49: =I49 -> 200 | ... M49: =L49 -> 200 | N49: =SUM(B49:M49) -> 2400 | Q49: =A48 -> Mantenimiento de equipo | R49: =M48 -> 300 | S49: =R49 -> 300 | T49: =S49 -> 300 | U49: =T49 -> 300 | V49: =U49 -> 300
A50: Herramientas menores | B50: 250 | C50: =B50 -> 250 | D50: =C50 -> 250 | E50: =D50 -> 250 | F50: =E50 -> 250 | G50: =F50 -> 250 | H50: =G50 -> 250 | I50: =H50 -> 250 | J50: =I50 -> 250 | ... M50: =L50 -> 250 | N50: =SUM(B50:M50) -> 3000 | Q50: =A49 -> Sustitución de mobiliario | R50: =M49 -> 200 | S50: =R50 -> 200 | T50: =S50 -> 200 | U50: =T50 -> 200 | V50: =U50 -> 200
A51: Pintura / remodelaciones | B51: 150 | C51: =B51 -> 150 | D51: =C51 -> 150 | E51: =D51 -> 150 | F51: =E51 -> 150 | G51: =F51 -> 150 | H51: =G51 -> 150 | I51: =H51 -> 150 | J51: =I51 -> 150 | ... M51: =L51 -> 150 | N51: =SUM(B51:M51) -> 1800 | Q51: =A50 -> Herramientas menores | R51: =M50 -> 250 | S51: =R51 -> 250 | T51: =S51 -> 250 | U51: =T51 -> 250 | V51: =U51 -> 250
A52: Repuestos / accesorios | B52: 100 | C52: =B52 -> 100 | D52: =C52 -> 100 | E52: =D52 -> 100 | F52: =E52 -> 100 | G52: =F52 -> 100 | H52: =G52 -> 100 | I52: =H52 -> 100 | J52: =I52 -> 100 | ... M52: =L52 -> 100 | N52: =SUM(B52:M52) -> 1200 | Q52: =A51 -> Pintura / remodelaciones | R52: =M51 -> 150 | S52: =R52 -> 150 | T52: =S52 -> 150 | U52: =T52 -> 150 | V52: =U52 -> 150
A53: TOTAL COSTO OPERACIÓN | B53: =+B16+B4 -> 400982.46 | C53: =+C16+C4 -> 404853.66 | D53: =+D16+D4 -> 400905.03 | E53: =+E16+E4 -> 406709.51 | F53: =+F16+F4 -> 410695.25 | G53: =+G16+G4 -> 404597.07 | H53: =+H16+H4 -> 402625.32 | I53: =+I16+I4 -> 406529.38 | ... N53: =+N16+N4 -> 4853900.6 | Q53: =A52 -> Repuestos / accesorios | R53: =M52 -> 100 | S53: =R53 -> 100 | T53: =S53 -> 100 | U53: =T53 -> 100 | V53: =U53 -> 100
Q54: TOTAL COSTO OPERACIÓN | R54: =SUM(R17+R4) -> 4853900.6 | S54: =+S17+S4 -> 4944527.3 | T54: =SUM(T17+T4) -> 5038627.2 | U54: =SUM(U17+U4) -> 5136333.2 | V54: =SUM(V17+V4) -> 5237783.5
A55: COSTOS DE PRODUCCION AÑO 2
A56: VARIABLES | B56: 1 | C56: 2 | D56: 3 | E56: 4 | F56: 5 | G56: 6 | H56: 7 | I56: 8 | J56: 9 | K56: 10 | L56: 11 | M56: 12 | N56: TOTAL
A57: TOTAL VARIABLES | B57: =SUM(B58:B68) -> 200977.75 | C57: =SUM(C58:C68) -> 204997.3 | D57: =SUM(D58:D68) -> 200897.36 | E57: =SUM(E58:E68) -> 206924.28 | F57: =SUM(F58:F68) -> 211062.76 | G57: =SUM(G58:G68) -> 204730.88 | H57: =SUM(H58:H68) -> 202683.57 | I57: =SUM(I58:I68) -> 206737.24 | ... N57: =SUM(N58:N68) -> 2455457.9
A58: =A5 -> Carne de cerdo adobada al pastor | B58: =M5 -> 118368.79 | C58: =B58*1.02 -> 120736.17 | D58: =C58*0.98 -> 118321.44 | E58: =D58*1.03 -> 121871.09 | F58: =E58*1.02 -> 124308.51 | G58: =F58*0.97 -> 120579.25 | H58: =G58*0.99 -> 119373.46 | I58: =H58*1.02 -> 121760.93 | J58: =I58*0.98 -> 119325.71 | K58: =J58*0.99 -> 118132.45 | L58: =K58*1.02 -> 120495.1 | M58: =1.02*L58 -> 122905 | N58: =SUM(B58:M58) -> 1446177.9
A59: =A6 -> Tortilla de maíz | B59: =M6 -> 4734.7516 | C59: =B59*1.02 -> 4829.4466 | D59: =C59*0.98 -> 4732.8577 | E59: =D59*1.03 -> 4874.8434 | F59: =E59*1.02 -> 4972.3403 | G59: =F59*0.97 -> 4823.1701 | H59: =G59*0.99 -> 4774.9384 | I59: =H59*1.02 -> 4870.4372 | J59: =I59*0.98 -> 4773.0284 | K59: =J59*0.99 -> 4725.2981 | L59: =K59*1.02 -> 4819.8041 | M59: =1.02*L59 -> 4916.2002 | N59: =SUM(B59:M59) -> 57847.116
A60: =A7 -> Piña | B60: =M7 -> 2491.9745 | C60: =B60*1.02 -> 2541.814 | D60: =C60*0.98 -> 2490.9777 | E60: =D60*1.03 -> 2565.7071 | F60: =E60*1.02 -> 2617.0212 | G60: =F60*0.97 -> 2538.5106 | H60: =G60*0.99 -> 2513.1255 | I60: =H60*1.02 -> 2563.388 | J60: =I60*0.98 -> 2512.1202 | K60: =J60*0.99 -> 2486.999 | L60: =K60*1.02 -> 2536.739 | M60: =1.02*L60 -> 2587.4738 | N60: =SUM(B60:M60) -> 30445.851
A61: =A8 -> Cebolla | B61: =M8 -> 1245.9873 | C61: =B61*1.02 -> 1270.907 | D61: =C61*0.98 -> 1245.4889 | E61: =D61*1.03 -> 1282.8535 | F61: =E61*1.02 -> 1308.5106 | G61: =F61*0.97 -> 1269.2553 | H61: =G61*0.99 -> 1256.5627 | I61: =H61*1.02 -> 1281.694 | J61: =I61*0.98 -> 1256.0601 | K61: =J61*0.99 -> 1243.4995 | L61: =K61*1.02 -> 1268.3695 | M61: =1.02*L61 -> 1293.7369 | N61: =SUM(B61:M61) -> 15222.925
A62: =A9 -> Cilantro | B62: =M9 -> 1245.9873 | C62: =B62*1.02 -> 1270.907 | D62: =C62*0.98 -> 1245.4889 | E62: =D62*1.03 -> 1282.8535 | F62: =E62*1.02 -> 1308.5106 | G62: =F62*0.97 -> 1269.2553 | H62: =G62*0.99 -> 1256.5627 | I62: =H62*1.02 -> 1281.694 | J62: =I62*0.98 -> 1256.0601 | K62: =J62*0.99 -> 1243.4995 | L62: =K62*1.02 -> 1268.3695 | M62: =1.02*L62 -> 1293.7369 | N62: =SUM(B62:M62) -> 15222.925
A63: =A10 -> Carne de cerdo marinada estilo oriental | B63: =M10 -> 46724.523 | C63: =B63*1.02 -> 47659.013 | D63: =C63*0.98 -> 46705.833 | E63: =D63*1.03 -> 48107.008 | F63: =E63*1.02 -> 49069.148 | G63: =F63*0.97 -> 47597.073 | H63: =G63*0.99 -> 47121.103 | I63: =H63*1.02 -> 48063.525 | J63: =I63*0.98 -> 47102.254 | K63: =J63*0.99 -> 46631.232 | L63: =K63*1.02 -> 47563.856 | M63: =1.02*L63 -> 48515.133 | N63: =SUM(B63:M63) -> 570859.7
A64: =A11 -> Pan árabe (Pita) | B64: =M11 -> 3737.9618 | C64: =B64*1.02 -> 3812.721 | D64: =C64*0.98 -> 3736.4666 | E64: =D64*1.03 -> 3848.5606 | F64: =E64*1.02 -> 3925.5318 | G64: =F64*0.97 -> 3807.7659 | H64: =G64*0.99 -> 3769.6882 | I64: =H64*1.02 -> 3845.082 | J64: =I64*0.98 -> 3768.1803 | K64: =J64*0.99 -> 3730.4985 | L64: =K64*1.02 -> 3805.1085 | M64: =1.02*L64 -> 3881.2107 | N64: =SUM(B64:M64) -> 45668.776
A65: =A12 -> Tocino | B65: =M12 -> 13082.866 | C65: =B65*1.02 -> 13344.524 | D65: =C65*0.98 -> 13077.633 | E65: =D65*1.03 -> 13469.962 | F65: =E65*1.02 -> 13739.361 | G65: =F65*0.97 -> 13327.181 | H65: =G65*0.99 -> 13193.909 | I65: =H65*1.02 -> 13457.787 | J65: =I65*0.98 -> 13188.631 | K65: =J65*0.99 -> 13056.745 | L65: =K65*1.02 -> 13317.88 | M65: =1.02*L65 -> 13584.237 | N65: =SUM(B65:M65) -> 159840.72
A66: =A13 -> Chile poblano | B66: =M13 -> 3737.9618 | C66: =B66*1.02 -> 3812.721 | D66: =C66*0.98 -> 3736.4666 | E66: =D66*1.03 -> 3848.5606 | F66: =E66*1.02 -> 3925.5318 | G66: =F66*0.97 -> 3807.7659 | H66: =G66*0.99 -> 3769.6882 | I66: =H66*1.02 -> 3845.082 | J66: =I66*0.98 -> 3768.1803 | K66: =J66*0.99 -> 3730.4985 | L66: =K66*1.02 -> 3805.1085 | M66: =1.02*L66 -> 3881.2107 | N66: =SUM(B66:M66) -> 45668.776
A67: =A14 -> Cebolla | B67: =M14 -> 3114.9682 | C67: =B67*1.02 -> 3177.2675 | D67: =C67*0.98 -> 3113.7222 | E67: =D67*1.03 -> 3207.1338 | F67: =E67*1.02 -> 3271.2765 | G67: =F67*0.97 -> 3173.1382 | H67: =G67*0.99 -> 3141.4068 | I67: =H67*1.02 -> 3204.235 | J67: =I67*0.98 -> 3140.1503 | K67: =J67*0.99 -> 3108.7488 | L67: =K67*1.02 -> 3170.9238 | M67: =1.02*L67 -> 3234.3422 | N67: =SUM(B67:M67) -> 38057.313
A68: =A15 -> Jitomate | B68: =M15 -> 2491.9745 | C68: =B68*1.02 -> 2541.814 | D68: =C68*0.98 -> 2490.9777 | E68: =D68*1.03 -> 2565.7071 | F68: =E68*1.02 -> 2617.0212 | G68: =F68*0.97 -> 2538.5106 | H68: =G68*0.99 -> 2513.1255 | I68: =H68*1.02 -> 2563.388 | J68: =I68*0.98 -> 2512.1202 | K68: =J68*0.99 -> 2486.999 | L68: =K68*1.02 -> 2536.739 | M68: =1.02*L68 -> 2587.4738 | N68: =SUM(B68:M68) -> 30445.851
A69: TOTAL FIJOS | B69: =SUM(B70:B94,B99:B105) -> 207422.46 | C69: =SUM(C70:C94,C99:C105) -> 207422.46 | D69: =SUM(D70:D94,D99:D105) -> 207422.46 | E69: =SUM(E70:E94,E99:E105) -> 207422.46 | F69: =SUM(F70:F94,F99:F105) -> 207422.46 | G69: =SUM(G70:G94,G99:G105) -> 207422.46 | H69: =SUM(H70:H94,H99:H105) -> 207422.46 | I69: =SUM(I70:I94,I99:I105) -> 207422.46 | ... N69: =SUM(N70:N94,N99:N105) -> 2489069.5
A70: =A17 -> Renta del local | B70: =M17 -> 16000 | C70: =B70 -> 16000 | D70: =C70 -> 16000 | E70: =D70 -> 16000 | F70: =E70 -> 16000 | G70: =F70 -> 16000 | H70: =G70 -> 16000 | I70: =H70 -> 16000 | J70: =I70 -> 16000 | ... M70: =L70 -> 16000 | N70: =SUM(B70:M70) -> 192000
A71: =A18 -> Internet / teléfono | B71: =M18 -> 600 | C71: =B71 -> 600 | D71: =C71 -> 600 | E71: =D71 -> 600 | F71: =E71 -> 600 | G71: =F71 -> 600 | H71: =G71 -> 600 | I71: =H71 -> 600 | J71: =I71 -> 600 | ... M71: =L71 -> 600 | N71: =SUM(B71:M71) -> 7200
A72: =A19 -> Permisos y licencias | B72: =M19 -> 400 | C72: =B72 -> 400 | D72: =C72 -> 400 | E72: =D72 -> 400 | F72: =E72 -> 400 | G72: =F72 -> 400 | H72: =G72 -> 400 | I72: =H72 -> 400 | J72: =I72 -> 400 | ... M72: =L72 -> 400 | N72: =SUM(B72:M72) -> 4800
A73: =A20 -> Mantenimiento | B73: =M20 -> 500 | C73: =B73 -> 500 | D73: =C73 -> 500 | E73: =D73 -> 500 | F73: =E73 -> 500 | G73: =F73 -> 500 | H73: =G73 -> 500 | I73: =H73 -> 500 | J73: =I73 -> 500 | ... M73: =L73 -> 500 | N73: =SUM(B73:M73) -> 6000
A74: =A21 -> Depreciaciones | B74: =M21 -> 1500 | C74: =B74 -> 1500 | D74: =C74 -> 1500 | E74: =D74 -> 1500 | F74: =E74 -> 1500 | G74: =F74 -> 1500 | H74: =G74 -> 1500 | I74: =H74 -> 1500 | J74: =I74 -> 1500 | ... M74: =L74 -> 1500 | N74: =SUM(B74:M74) -> 18000
A75: =A22 -> Energía eléctrica (Pago bimestral) | B75: =M22 -> 700 | C75: =B75 -> 700 | D75: =C75 -> 700 | E75: =D75 -> 700 | F75: =E75 -> 700 | G75: =F75 -> 700 | H75: =G75 -> 700 | I75: =H75 -> 700 | J75: =I75 -> 700 | ... M75: =L75 -> 700 | N75: =SUM(B75:M75) -> 8400
A76: =A23 -> Agua | B76: =M23 -> 400 | C76: =B76 -> 400 | D76: =C76 -> 400 | E76: =D76 -> 400 | F76: =E76 -> 400 | G76: =F76 -> 400 | H76: =G76 -> 400 | I76: =H76 -> 400 | J76: =I76 -> 400 | ... M76: =L76 -> 400 | N76: =SUM(B76:M76) -> 4800
A77: =A24 -> Gas estacionario | B77: =M24 -> 1200 | C77: =B77 -> 1200 | D77: =C77 -> 1200 | E77: =D77 -> 1200 | F77: =E77 -> 1200 | G77: =F77 -> 1200 | H77: =G77 -> 1200 | I77: =H77 -> 1200 | J77: =I77 -> 1200 | ... M77: =L77 -> 1200 | N77: =SUM(B77:M77) -> 14400
A78: =A25 -> Limpieza / fumigación | B78: =M25 -> 300 | C78: =B78 -> 300 | D78: =C78 -> 300 | E78: =D78 -> 300 | F78: =E78 -> 300 | G78: =F78 -> 300 | H78: =G78 -> 300 | I78: =H78 -> 300 | J78: =I78 -> 300 | ... M78: =L78 -> 300 | N78: =SUM(B78:M78) -> 3600
A79: =A26 -> Mesero | B79: =M26 -> 20299.32 | C79: =B79 -> 20299.32 | D79: =C79 -> 20299.32 | E79: =D79 -> 20299.32 | F79: =E79 -> 20299.32 | G79: =F79 -> 20299.32 | H79: =G79 -> 20299.32 | I79: =H79 -> 20299.32 | J79: =I79 -> 20299.32 | ... M79: =L79 -> 20299.32 | N79: =SUM(B79:M79) -> 243591.84
A80: =A27 -> Verduras, ensaladas y guarniciones | B80: =M27 -> 6348.32 | C80: =B80 -> 6348.32 | D80: =C80 -> 6348.32 | E80: =D80 -> 6348.32 | F80: =E80 -> 6348.32 | G80: =F80 -> 6348.32 | H80: =G80 -> 6348.32 | I80: =H80 -> 6348.32 | J80: =I80 -> 6348.32 | ... M80: =L80 -> 6348.32 | N80: =SUM(B80:M80) -> 76179.84
A81: =A28 -> Salsas y Járabes | B81: =M28 -> 6348.32 | C81: =B81 -> 6348.32 | D81: =C81 -> 6348.32 | E81: =D81 -> 6348.32 | F81: =E81 -> 6348.32 | G81: =F81 -> 6348.32 | H81: =G81 -> 6348.32 | I81: =H81 -> 6348.32 | J81: =I81 -> 6348.32 | ... M81: =L81 -> 6348.32 | N81: =SUM(B81:M81) -> 76179.84
... A105: =A52 -> Repuestos / accesorios | B105: =M52 -> 100 | C105: =B105 -> 100 | D105: =C105 -> 100 | E105: =D105 -> 100 | F105: =E105 -> 100 | G105: =F105 -> 100 | H105: =G105 -> 100 | I105: =H105 -> 100 | J105: =I105 -> 100 | ... M105: =L105 -> 100 | N105: =SUM(B105:M105) -> 1200
A106: TOTAL COSTO OPERACIÓN | B106: =+B69+B57 -> 408400.2 | C106: =+C69+C57 -> 412419.76 | D106: =+D69+D57 -> 408319.81 | E106: =+E69+E57 -> 414346.73 | F106: =+F69+F57 -> 418485.22 | G106: =+G69+G57 -> 412153.33 | H106: =+H69+H57 -> 410106.03 | I106: =+I69+I57 -> 414159.7 | ... N106: =+N69+N57 -> 4944527.3
A108: COSTOS DE PRODUCCION AÑO 3
A109: VARIABLES | B109: 1 | C109: 2 | D109: 3 | E109: 4 | F109: 5 | G109: 6 | H109: 7 | I109: 8 | J109: 9 | K109: 10 | L109: 11 | M109: 12 | N109: TOTAL
A110: TOTAL VARIABLES | B110: =SUM(B111:B121) -> 208679.76 | C110: =SUM(C111:C121) -> 212853.36 | D110: =SUM(D111:D121) -> 208596.29 | E110: =SUM(E111:E121) -> 214854.18 | F110: =SUM(F111:F121) -> 219151.26 | G110: =SUM(G111:G121) -> 212576.72 | H110: =SUM(H111:H121) -> 210450.96 | I110: =SUM(I111:I121) -> 214659.98 | ... N110: =SUM(N111:N121) -> 2549557.7
A111: =A58 -> Carne de cerdo adobada al pastor | B111: =M58 -> 122905 | C111: =B111*1.02 -> 125363.1 | D111: =C111*0.98 -> 122855.84 | E111: =D111*1.03 -> 126541.52 | F111: =E111*1.02 -> 129072.35 | G111: =F111*0.97 -> 125200.18 | H111: =G111*0.99 -> 123948.18 | I111: =H111*1.02 -> 126427.14 | J111: =I111*0.98 -> 123898.6 | K111: =J111*0.99 -> 122659.61 | L111: =K111*1.02 -> 125112.8 | M111: =1.02*L111 -> 127615.06 | N111: =SUM(B111:M111) -> 1501599.4
A112: =A59 -> Tortilla de maíz | B112: =M59 -> 4916.2002 | C112: =B112*1.02 -> 5014.5242 | D112: =C112*0.98 -> 4914.2337 | E112: =D112*1.03 -> 5061.6607 | F112: =E112*1.02 -> 5162.8939 | G112: =F112*0.97 -> 5008.0071 | H112: =G112*0.99 -> 4957.927 | I112: =H112*1.02 -> 5057.0856 | J112: =I112*0.98 -> 4955.9439 | K112: =J112*0.99 -> 4906.3844 | L112: =K112*1.02 -> 5004.5121 | M112: =1.02*L112 -> 5104.6024 | N112: =SUM(B112:M112) -> 60063.975
A113: =A60 -> Piña | B113: =M60 -> 2587.4738 | C113: =B113*1.02 -> 2639.2233 | D113: =C113*0.98 -> 2586.4388 | E113: =D113*1.03 -> 2664.032 | F113: =E113*1.02 -> 2717.3126 | G113: =F113*0.97 -> 2635.7932 | H113: =G113*0.99 -> 2609.4353 | I113: =H113*1.02 -> 2661.624 | J113: =I113*0.98 -> 2608.3915 | K113: =J113*0.99 -> 2582.3076 | L113: =K113*1.02 -> 2633.9538 | M113: =1.02*L113 -> 2686.6328 | N113: =SUM(B113:M113) -> 31612.619
A114: =A61 -> Cebolla | B114: =M61 -> 1293.7369 | C114: =B114*1.02 -> 1319.6116 | D114: =C114*0.98 -> 1293.2194 | E114: =D114*1.03 -> 1332.016 | F114: =E114*1.02 -> 1358.6563 | G114: =F114*0.97 -> 1317.8966 | H114: =G114*0.99 -> 1304.7176 | I114: =H114*1.02 -> 1330.812 | J114: =I114*0.98 -> 1304.1958 | K114: =J114*0.99 -> 1291.1538 | L114: =K114*1.02 -> 1316.9769 | M114: =1.02*L114 -> 1343.3164 | N114: =SUM(B114:M114) -> 15806.309
A115: =A62 -> Cilantro | B115: =M62 -> 1293.7369 | C115: =B115*1.02 -> 1319.6116 | D115: =C115*0.98 -> 1293.2194 | E115: =D115*1.03 -> 1332.016 | F115: =E115*1.02 -> 1358.6563 | G115: =F115*0.97 -> 1317.8966 | H115: =G115*0.99 -> 1304.7176 | I115: =H115*1.02 -> 1330.812 | J115: =I115*0.98 -> 1304.1958 | K115: =J115*0.99 -> 1291.1538 | L115: =K115*1.02 -> 1316.9769 | M115: =1.02*L115 -> 1343.3164 | N115: =SUM(B115:M115) -> 15806.309
A116: =A63 -> Carne de cerdo marinada estilo oriental | B116: =M63 -> 48515.133 | C116: =B116*1.02 -> 49485.436 | D116: =C116*0.98 -> 48495.727 | E116: =D116*1.03 -> 49950.599 | F116: =E116*1.02 -> 50949.611 | G116: =F116*0.97 -> 49421.123 | H116: =G116*0.99 -> 48926.912 | I116: =H116*1.02 -> 49905.45 | J116: =I116*0.98 -> 48907.341 | K116: =J116*0.99 -> 48418.267 | L116: =K116*1.02 -> 49386.633 | M116: =1.02*L116 -> 50374.365 | N116: =SUM(B116:M116) -> 592736.6
A117: =A64 -> Pan árabe (Pita) | B117: =M64 -> 3881.2107 | C117: =B117*1.02 -> 3958.8349 | D117: =C117*0.98 -> 3879.6582 | E117: =D117*1.03 -> 3996.0479 | F117: =E117*1.02 -> 4075.9689 | G117: =F117*0.97 -> 3953.6898 | H117: =G117*0.99 -> 3914.1529 | I117: =H117*1.02 -> 3992.436 | J117: =I117*0.98 -> 3912.5873 | K117: =J117*0.99 -> 3873.4614 | L117: =K117*1.02 -> 3950.9306 | M117: =1.02*L117 -> 4029.9492 | N117: =SUM(B117:M117) -> 47418.928
A118: =A65 -> Tocino | B118: =M65 -> 13584.237 | C118: =B118*1.02 -> 13855.922 | D118: =C118*0.98 -> 13578.804 | E118: =D118*1.03 -> 13986.168 | F118: =E118*1.02 -> 14265.891 | G118: =F118*0.97 -> 13837.914 | H118: =G118*0.99 -> 13699.535 | I118: =H118*1.02 -> 13973.526 | J118: =I118*0.98 -> 13694.055 | K118: =J118*0.99 -> 13557.115 | L118: =K118*1.02 -> 13828.257 | M118: =1.02*L118 -> 14104.822 | N118: =SUM(B118:M118) -> 165966.25
A119: =A66 -> Chile poblano | B119: =M66 -> 3881.2107 | C119: =B119*1.02 -> 3958.8349 | D119: =C119*0.98 -> 3879.6582 | E119: =D119*1.03 -> 3996.0479 | F119: =E119*1.02 -> 4075.9689 | G119: =F119*0.97 -> 3953.6898 | H119: =G119*0.99 -> 3914.1529 | I119: =H119*1.02 -> 3992.436 | J119: =I119*0.98 -> 3912.5873 | K119: =J119*0.99 -> 3873.4614 | L119: =K119*1.02 -> 3950.9306 | M119: =1.02*L119 -> 4029.9492 | N119: =SUM(B119:M119) -> 47418.928
A120: =A67 -> Cebolla | B120: =M67 -> 3234.3422 | C120: =B120*1.02 -> 3299.0291 | D120: =C120*0.98 -> 3233.0485 | E120: =D120*1.03 -> 3330.0399 | F120: =E120*1.02 -> 3396.6407 | G120: =F120*0.97 -> 3294.7415 | H120: =G120*0.99 -> 3261.7941 | I120: =H120*1.02 -> 3327.03 | J120: =I120*0.98 -> 3260.4894 | K120: =J120*0.99 -> 3227.8845 | L120: =K120*1.02 -> 3292.4422 | M120: =1.02*L120 -> 3358.291 | N120: =SUM(B120:M120) -> 39515.773
A121: =A68 -> Jitomate | B121: =M68 -> 2587.4738 | C121: =B121*1.02 -> 2639.2233 | D121: =C121*0.98 -> 2586.4388 | E121: =D121*1.03 -> 2664.032 | F121: =E121*1.02 -> 2717.3126 | G121: =F121*0.97 -> 2635.7932 | H121: =G121*0.99 -> 2609.4353 | I121: =H121*1.02 -> 2661.624 | J121: =I121*0.98 -> 2608.3915 | K121: =J121*0.99 -> 2582.3076 | L121: =K121*1.02 -> 2633.9538 | M121: =1.02*L121 -> 2686.6328 | N121: =SUM(B121:M121) -> 31612.619
A122: TOTAL FIJOS | B122: =SUM(B123:B147,B152:B158) -> 207422.46 | C122: =SUM(C123:C147,C152:C158) -> 207422.46 | D122: =SUM(D123:D147,D152:D158) -> 207422.46 | E122: =SUM(E123:E147,E152:E158) -> 207422.46 | F122: =SUM(F123:F147,F152:F158) -> 207422.46 | G122: =SUM(G123:G147,G152:G158) -> 207422.46 | H122: =SUM(H123:H147,H152:H158) -> 207422.46 | I122: =SUM(I123:I147,I152:I158) -> 207422.46 | ... N122: =SUM(N123:N147,N152:N158) -> 2489069.5
A123: =A70 -> Renta del local | B123: =M70 -> 16000 | C123: =B123 -> 16000 | D123: =C123 -> 16000 | E123: =D123 -> 16000 | F123: =E123 -> 16000 | G123: =F123 -> 16000 | H123: =G123 -> 16000 | I123: =H123 -> 16000 | J123: =I123 -> 16000 | ... M123: =L123 -> 16000 | N123: =SUM(B123:M123) -> 192000
A124: =A71 -> Internet / teléfono | B124: =M71 -> 600 | C124: =B124 -> 600 | D124: =C124 -> 600 | E124: =D124 -> 600 | F124: =E124 -> 600 | G124: =F124 -> 600 | H124: =G124 -> 600 | I124: =H124 -> 600 | J124: =I124 -> 600 | ... M124: =L124 -> 600 | N124: =SUM(B124:M124) -> 7200
A125: =A72 -> Permisos y licencias | B125: =M72 -> 400 | C125: =B125 -> 400 | D125: =C125 -> 400 | E125: =D125 -> 400 | F125: =E125 -> 400 | G125: =F125 -> 400 | H125: =G125 -> 400 | I125: =H125 -> 400 | J125: =I125 -> 400 | ... M125: =L125 -> 400 | N125: =SUM(B125:M125) -> 4800
...

Sheet INGRESOS 
A2: MEMORIAS DE INGRESOS
A4: PROYECTO:
A5: SOCIEDAD
A6: BENEFICIARIOS:
A8: CONCEPTOS | B8: INGRESOS POR VENTA MENSUAL AÑO 1
A9: MES | B9: 1 | C9: 2 | D9: 3 | E9: 4 | F9: 5 | G9: 6 | H9: 7 | I9: 8 | J9: 9 | K9: 10 | L9: 11 | M9: 12 | N9: TOTAL
A10: Productos del local | N10: ANUAL
A11: Tacos al pastor | B11: =(16*(400*30)) -> 192000 | C11: =16*(400*30) -> 192000 | D11: =16*(400*30) -> 192000 | E11: =16*(412*30) -> 197760 | F11: =16*(412*30) -> 197760 | G11: =16*(412*30) -> 197760 | H11: =16*(425*30) -> 204000 | I11: =16*(425*30) -> 204000 | J11: =16*(425*30) -> 204000 | K11: =16*(438*30) -> 210240 | L11: =16*(438*30) -> 210240 | M11: =16*(438*30) -> 210240 | N11: =SUM(B11:M11) -> 2412000
A12: Taco arabe gigante | B12: =100*(130*30) -> 390000 | C12: =100*(130*30) -> 390000 | D12: =100*(130*30) -> 390000 | E12: =100*(134*30) -> 402000 | F12: =100*(134*30) -> 402000 | G12: =100*(134*30) -> 402000 | H12: =100*(138*30) -> 414000 | I12: =100*(138*30) -> 414000 | J12: =100*(138*30) -> 414000 | K12: =100*(143*30) -> 429000 | L12: =100*(143*30) -> 429000 | M12: =100*(143*30) -> 429000 | N12: =SUM(B12:M12) -> 4905000
A13: Matahambre | B13: =220*(50*30) -> 330000 | C13: =220*(50*30) -> 330000 | D13: =220*(50*30) -> 330000 | E13: =220*(52*30) -> 343200 | F13: =220*(52*30) -> 343200 | G13: =220*(52*30) -> 343200 | H13: =(220)*(54*30) -> 356400 | I13: =(220)*(54*30) -> 356400 | J13: =(220)*(54*30) -> 356400 | K13: =(220)*(56*30) -> 369600 | L13: =(220)*(56*30) -> 369600 | M13: =(220)*(56*30) -> 369600 | N13: =SUM(B13:M13) -> 4197600
A14: 1 litro de agua de horchata | B14: =(45)*(280*4) -> 50400 | C14: =(45)*(280*4) -> 50400 | D14: =(45)*(280*4) -> 50400 | E14: =(45)*(288*4) -> 51840 | F14: =(45)*(288*4) -> 51840 | G14: =(45)*(288*4) -> 51840 | H14: =(45)*(295*4) -> 53100 | I14: =(45)*(295*4) -> 53100 | J14: =(45)*(295*4) -> 53100 | K14: =(45)*(303*4) -> 54540 | L14: =(45)*(303*4) -> 54540 | M14: =(45)*(303*4) -> 54540 | N14: =SUM(B14:M14) -> 629640
A15: Una tazas de cafe americano | B15: =(20)*(5*30) -> 3000 | C15: =(20)*(5*30) -> 3000 | D15: =(20)*(5*30) -> 3000 | E15: =(20)*(5*30) -> 3000 | F15: =(20)*(5*30) -> 3000 | G15: =(20)*(5*30) -> 3000 | H15: =(20)*(5*30) -> 3000 | I15: =(20)*(5*30) -> 3000 | ... M15: =(20)*(5*30) -> 3000 | N15: =SUM(B15:M15) -> 36000
A16: Tortas hawaiana | B16: =(75)*(15*30) -> 33750 | C16: =(75)*(15*30) -> 33750 | D16: =(75)*(15*30) -> 33750 | E16: =(75)*(15*30) -> 33750 | F16: =(75)*(15*30) -> 33750 | G16: =(75)*(15*30) -> 33750 | H16: =(75)*(16*30) -> 36000 | I16: =(75)*(16*30) -> 36000 | J16: =(75)*(16*30) -> 36000 | K16: =(75)*(16*30) -> 36000 | L16: =(75)*(16*30) -> 36000 | M16: =(75)*(16*30) -> 36000 | N16: =SUM(B16:M16) -> 418500
A17: Hamburguesa Hawaiana | B17: =(75)*(10*30) -> 22500 | C17: =(75)*(10*30) -> 22500 | D17: =(75)*(10*30) -> 22500 | E17: =(75)*(10*30) -> 22500 | F17: =(75)*(10*30) -> 22500 | G17: =(75)*(10*30) -> 22500 | H17: =(75)*(10*30) -> 22500 | I17: =(75)*(10*30) -> 22500 | J17: =(75)*(10*30) -> 22500 | K17: =(75)*(11*30) -> 24750 | L17: =(75)*(11*30) -> 24750 | M17: =(75)*(11*30) -> 24750 | N17: =SUM(B17:M17) -> 276750
A18: Ballenita | B18: =(280)*(5*30) -> 42000 | C18: =(280)*(5*30) -> 42000 | D18: =(280)*(5*30) -> 42000 | E18: =(280)*(5*30) -> 42000 | F18: =(280)*(5*30) -> 42000 | G18: =(280)*(5*30) -> 42000 | H18: =(280)*(5*30) -> 42000 | I18: =(280)*(5*30) -> 42000 | ... M18: =(280)*(5*30) -> 42000 | N18: =SUM(B18:M18) -> 504000
A19: Norteño | B19: =(240)*(5*30) -> 36000 | C19: =(240)*(5*30) -> 36000 | D19: =(240)*(5*30) -> 36000 | E19: =(240)*(5*30) -> 36000 | F19: =(240)*(5*30) -> 36000 | G19: =(240)*(5*30) -> 36000 | H19: =(240)*(5*30) -> 36000 | I19: =(240)*(5*30) -> 36000 | ... M19: =(240)*(5*30) -> 36000 | N19: =SUM(B19:M19) -> 432000
A20: Taco de Suadero | B20: =(16)*(50*30) -> 24000 | C20: =(16)*(50*30) -> 24000 | D20: =(16)*(50*30) -> 24000 | E20: =(16)*(52*30) -> 24960 | F20: =(16)*(52*30) -> 24960 | G20: =(16)*(52*30) -> 24960 | H20: =(16)*(54*30) -> 25920 | I20: =(16)*(54*30) -> 25920 | J20: =(16)*(54*30) -> 25920 | K20: =(16)*(56*30) -> 26880 | L20: =(16)*(56*30) -> 26880 | M20: =(16)*(56*30) -> 26880 | N20: =SUM(B20:M20) -> 305280
A21: Tacos de Bistec | B21: =(16)*(50*30) -> 24000 | C21: =(16)*(50*30) -> 24000 | D21: =(16)*(50*30) -> 24000 | E21: =(16)*(52*30) -> 24960 | F21: =(16)*(52*30) -> 24960 | G21: =(16)*(52*30) -> 24960 | H21: =(16)*(54*30) -> 25920 | I21: =(16)*(54*30) -> 25920 | J21: =(16)*(54*30) -> 25920 | K21: =(16)*(56*30) -> 26880 | L21: =(16)*(56*30) -> 26880 | M21: =(16)*(56*30) -> 26880 | N21: =SUM(B21:M21) -> 305280
A22: Tacos de Cabeza | B22: =(16)*(45*30) -> 21600 | C22: =(16)*(45*30) -> 21600 | D22: =(16)*(45*30) -> 21600 | E22: =(16)*(47*30) -> 22560 | F22: =(16)*(47*30) -> 22560 | G22: =(16)*(47*30) -> 22560 | H22: =(16)*(49*30) -> 23520 | I22: =(16)*(49*30) -> 23520 | J22: =(16)*(49*30) -> 23520 | K22: =(16)*(51*30) -> 24480 | L22: =(16)*(51*30) -> 24480 | M22: =(16)*(51*30) -> 24480 | N22: =SUM(B22:M22) -> 276480
A23: Taco de Maciza | B23: =(16)*(70*30) -> 33600 | C23: =(16)*(70*30) -> 33600 | D23: =(16)*(70*30) -> 33600 | E23: =(16)*(72*30) -> 34560 | F23: =(16)*(72*30) -> 34560 | G23: =(16)*(72*30) -> 34560 | H23: =(16)*(75*30) -> 36000 | I23: =(16)*(75*30) -> 36000 | J23: =(16)*(75*30) -> 36000 | K23: =(16)*(78*30) -> 37440 | L23: =(16)*(78*30) -> 37440 | M23: =(16)*(78*30) -> 37440 | N23: =SUM(B23:M23) -> 424800
A24: TOTAL DE INGRESOS | B24: =SUM(B11:B23) -> 1202850 | C24: =SUM(C11:C23) -> 1202850 | D24: =SUM(D11:D23) -> 1202850 | E24: =SUM(E11:E23) -> 1239090 | F24: =SUM(F11:F23) -> 1239090 | G24: =SUM(G11:G23) -> 1239090 | H24: =SUM(H11:H23) -> 1278360 | I24: =SUM(I11:I23) -> 1278360 | ... M24: =SUM(M11:M23) -> 1320810 | N24: =SUM(B24:M24) -> 15123330
A28: CONCEPTOS | B28: INGRESOS POR VENTA MENSUAL AÑO 2
A29: MES | B29: 1 | C29: 2 | D29: 3 | E29: 4 | F29: 5 | G29: 6 | H29: 7 | I29: 8 | J29: 9 | K29: 10 | L29: 11 | M29: 12 | N29: TOTAL
A30: Productos del local | N30: ANUAL
A31: Tacos al pastor | B31: =$Q$69*(438*30) -> 229161.6 | C31: =$Q$69*(438*30) -> 229161.6 | D31: =$Q$69*(438*30) -> 229161.6 | E31: =$Q$69*(438*30) -> 229161.6 | F31: =$Q$69*(438*30) -> 229161.6 | G31: =$Q$69*(438*30) -> 229161.6 | H31: =$Q$69*(438*30) -> 229161.6 | I31: =$Q$69*(438*30) -> 229161.6 | ... M31: =$Q$69*(438*30) -> 229161.6 | N31: =SUM(B31:M31) -> 2749939.2
A32: Taco arabe gigante | B32: =$Q$70*(143*30) -> 467610 | C32: =$Q$70*(143*30) -> 467610 | D32: =$Q$70*(143*30) -> 467610 | E32: =$Q$70*(143*30) -> 467610 | F32: =$Q$70*(143*30) -> 467610 | G32: =$Q$70*(143*30) -> 467610 | H32: =$Q$70*(143*30) -> 467610 | I32: =$Q$70*(143*30) -> 467610 | ... M32: =$Q$70*(143*30) -> 467610 | N32: =SUM(B32:M32) -> 5611320
A33: Matahambre | B33: =($Q$71)*(56*30) -> 402864 | C33: =($Q$71)*(56*30) -> 402864 | D33: =($Q$71)*(56*30) -> 402864 | E33: =($Q$71)*(56*30) -> 402864 | F33: =($Q$71)*(56*30) -> 402864 | G33: =($Q$71)*(56*30) -> 402864 | H33: =($Q$71)*(56*30) -> 402864 | I33: =($Q$71)*(56*30) -> 402864 | ... M33: =($Q$71)*(56*30) -> 402864 | N33: =SUM(B33:M33) -> 4834368
A34: 1 litro de agua de horchata | B34: =($Q$72)*(303*4) -> 59448.6 | C34: =($Q$72)*(303*4) -> 59448.6 | D34: =($Q$72)*(303*4) -> 59448.6 | E34: =($Q$72)*(303*4) -> 59448.6 | F34: =($Q$72)*(303*4) -> 59448.6 | G34: =($Q$72)*(303*4) -> 59448.6 | H34: =($Q$72)*(303*4) -> 59448.6 | I34: =($Q$72)*(303*4) -> 59448.6 | ... M34: =($Q$72)*(303*4) -> 59448.6 | N34: =SUM(B34:M34) -> 713383.2
A35: Una tazas de cafe americano | B35: =($Q$73)*(5*30) -> 3270 | C35: =($Q$73)*(5*30) -> 3270 | D35: =($Q$73)*(5*30) -> 3270 | E35: =($Q$73)*(5*30) -> 3270 | F35: =($Q$73)*(5*30) -> 3270 | G35: =($Q$73)*(5*30) -> 3270 | H35: =($Q$73)*(5*30) -> 3270 | I35: =($Q$73)*(5*30) -> 3270 | ... M35: =($Q$73)*(5*30) -> 3270 | N35: =SUM(B35:M35) -> 39240
A36: Tortas hawaiana | B36: =($Q$74)*(16*30) -> 39240 | C36: =($Q$74)*(16*30) -> 39240 | D36: =($Q$74)*(16*30) -> 39240 | E36: =($Q$74)*(16*30) -> 39240 | F36: =($Q$74)*(16*30) -> 39240 | G36: =($Q$74)*(16*30) -> 39240 | H36: =($Q$74)*(16*30) -> 39240 | I36: =($Q$74)*(16*30) -> 39240 | ... M36: =($Q$74)*(16*30) -> 39240 | N36: =SUM(B36:M36) -> 470880
A37: Hamburguesa Hawaiana | B37: =($Q$75)*(11*30) -> 26977.5 | C37: =($Q$75)*(11*30) -> 26977.5 | D37: =($Q$75)*(11*30) -> 26977.5 | E37: =($Q$75)*(11*30) -> 26977.5 | F37: =($Q$75)*(11*30) -> 26977.5 | G37: =($Q$75)*(11*30) -> 26977.5 | H37: =($Q$75)*(11*30) -> 26977.5 | I37: =($Q$75)*(11*30) -> 26977.5 | ... M37: =($Q$75)*(11*30) -> 26977.5 | N37: =SUM(B37:M37) -> 323730
A38: Ballenita | B38: =($Q$76)*(5*30) -> 45780 | C38: =($Q$76)*(5*30) -> 45780 | D38: =($Q$76)*(5*30) -> 45780 | E38: =($Q$76)*(5*30) -> 45780 | F38: =($Q$76)*(5*30) -> 45780 | G38: =($Q$76)*(5*30) -> 45780 | H38: =($Q$76)*(5*30) -> 45780 | I38: =($Q$76)*(5*30) -> 45780 | ... M38: =($Q$76)*(5*30) -> 45780 | N38: =SUM(B38:M38) -> 549360
A39: Norteño | B39: =($Q$77)*(5*30) -> 39240 | C39: =($Q$77)*(5*30) -> 39240 | D39: =($Q$77)*(5*30) -> 39240 | E39: =($Q$77)*(5*30) -> 39240 | F39: =($Q$77)*(5*30) -> 39240 | G39: =($Q$77)*(5*30) -> 39240 | H39: =($Q$77)*(5*30) -> 39240 | I39: =($Q$77)*(5*30) -> 39240 | ... M39: =($Q$77)*(5*30) -> 39240 | N39: =SUM(B39:M39) -> 470880
A40: Taco de Suadero | B40: =($Q$78)*(56*30) -> 29299.2 | C40: =($Q$78)*(56*30) -> 29299.2 | D40: =($Q$78)*(56*30) -> 29299.2 | E40: =($Q$78)*(56*30) -> 29299.2 | F40: =($Q$78)*(56*30) -> 29299.2 | G40: =($Q$78)*(56*30) -> 29299.2 | H40: =($Q$78)*(56*30) -> 29299.2 | I40: =($Q$78)*(56*30) -> 29299.2 | ... M40: =($Q$78)*(56*30) -> 29299.2 | N40: =SUM(B40:M40) -> 351590.4
A41: Tacos de Bistec | B41: =($Q$79)*(56*30) -> 29299.2 | C41: =($Q$79)*(56*30) -> 29299.2 | D41: =($Q$79)*(56*30) -> 29299.2 | E41: =($Q$79)*(56*30) -> 29299.2 | F41: =($Q$79)*(56*30) -> 29299.2 | G41: =($Q$79)*(56*30) -> 29299.2 | H41: =($Q$79)*(56*30) -> 29299.2 | I41: =($Q$79)*(56*30) -> 29299.2 | ... M41: =($Q$79)*(56*30) -> 29299.2 | N41: =SUM(B41:M41) -> 351590.4
A42: Tacos de Cabeza | B42: =($Q$80)*(51*30) -> 26683.2 | C42: =($Q$80)*(51*30) -> 26683.2 | D42: =($Q$80)*(51*30) -> 26683.2 | E42: =($Q$80)*(51*30) -> 26683.2 | F42: =($Q$80)*(51*30) -> 26683.2 | G42: =($Q$80)*(51*30) -> 26683.2 | H42: =($Q$80)*(51*30) -> 26683.2 | I42: =($Q$80)*(51*30) -> 26683.2 | ... M42: =($Q$80)*(51*30) -> 26683.2 | N42: =SUM(B42:M42) -> 320198.4
A43: Taco de Maciza | B43: =($Q$81)*(78*30) -> 40809.6 | C43: =($Q$81)*(78*30) -> 40809.6 | D43: =($Q$81)*(78*30) -> 40809.6 | E43: =($Q$81)*(78*30) -> 40809.6 | F43: =($Q$81)*(78*30) -> 40809.6 | G43: =($Q$81)*(78*30) -> 40809.6 | H43: =($Q$81)*(78*30) -> 40809.6 | I43: =($Q$81)*(78*30) -> 40809.6 | ... M43: =($Q$81)*(78*30) -> 40809.6 | N43: =SUM(B43:M43) -> 489715.2
A44: TOTAL DE INGRESOS | B44: =SUM(B31:B43) -> 1439682.9 | C44: =SUM(C31:C43) -> 1439682.9 | D44: =SUM(D31:D43) -> 1439682.9 | E44: =SUM(E31:E43) -> 1439682.9 | F44: =SUM(F31:F43) -> 1439682.9 | G44: =SUM(G31:G43) -> 1439682.9 | H44: =SUM(H31:H43) -> 1439682.9 | I44: =SUM(I31:I43) -> 1439682.9 | ... M44: =SUM(M31:M43) -> 1439682.9 | N44: =SUM(B44:M44) -> 17276195
A48: CONCEPTOS | B48: INGRESOS POR VENTA MENSUAL AÑO 3
A49: MES | B49: 1 | C49: 2 | D49: 3 | E49: 4 | F49: 5 | G49: 6 | H49: 7 | I49: 8 | J49: 9 | K49: 10 | L49: 11 | M49: 12 | N49: TOTAL
A50: Productos del local | N50: ANUAL
A51: Tacos al pastor | B51: =$R$69*(438*30) -> 249786.14 | C51: =$R$69*(438*30) -> 249786.14 | D51: =$R$69*(438*30) -> 249786.14 | E51: =$R$69*(438*30) -> 249786.14 | F51: =$R$69*(438*30) -> 249786.14 | G51: =$R$69*(438*30) -> 249786.14 | H51: =$R$69*(438*30) -> 249786.14 | I51: =$R$69*(438*30) -> 249786.14 | ... M51: =$R$69*(438*30) -> 249786.14 | N51: =SUM(B51:M51) -> 2997433.7
A52: Taco arabe gigante | B52: =$R$70*(143*30) -> 509694.9 | C52: =$R$70*(143*30) -> 509694.9 | D52: =$R$70*(143*30) -> 509694.9 | E52: =$R$70*(143*30) -> 509694.9 | F52: =$R$70*(143*30) -> 509694.9 | G52: =$R$70*(143*30) -> 509694.9 | H52: =$R$70*(143*30) -> 509694.9 | I52: =$R$70*(143*30) -> 509694.9 | ... M52: =$R$70*(143*30) -> 509694.9 | N52: =SUM(B52:M52) -> 6116338.8
A53: Matahambre | B53: =$R$71*(56*30) -> 439121.76 | C53: =$R$71*(56*30) -> 439121.76 | D53: =$R$71*(56*30) -> 439121.76 | E53: =$R$71*(56*30) -> 439121.76 | F53: =$R$71*(56*30) -> 439121.76 | G53: =$R$71*(56*30) -> 439121.76 | H53: =$R$71*(56*30) -> 439121.76 | I53: =$R$71*(56*30) -> 439121.76 | ... M53: =$R$71*(56*30) -> 439121.76 | N53: =SUM(B53:M53) -> 5269461.1
A54: 1 litro de agua de horchata | B54: =($R$72)*(303*4) -> 64798.974 | C54: =($R$72)*(303*4) -> 64798.974 | D54: =($R$72)*(303*4) -> 64798.974 | E54: =($R$72)*(303*4) -> 64798.974 | F54: =($R$72)*(303*4) -> 64798.974 | G54: =($R$72)*(303*4) -> 64798.974 | H54: =($R$72)*(303*4) -> 64798.974 | I54: =($R$72)*(303*4) -> 64798.974 | ... M54: =($R$72)*(303*4) -> 64798.974 | N54: =SUM(B54:M54) -> 777587.69
A55: Una tazas de cafe americano | B55: =($R$73)*(5*30) -> 3564.3 | C55: =($R$73)*(5*30) -> 3564.3 | D55: =($R$73)*(5*30) -> 3564.3 | E55: =($R$73)*(5*30) -> 3564.3 | F55: =($R$73)*(5*30) -> 3564.3 | G55: =($R$73)*(5*30) -> 3564.3 | H55: =($R$73)*(5*30) -> 3564.3 | I55: =($R$73)*(5*30) -> 3564.3 | ... M55: =($R$73)*(5*30) -> 3564.3 | N55: =SUM(B55:M55) -> 42771.6
A56: Tortas hawaiana | B56: =($R$75)*(16*30) -> 42771.6 | C56: =($R$75)*(16*30) -> 42771.6 | D56: =($R$75)*(16*30) -> 42771.6 | E56: =($R$75)*(16*30) -> 42771.6 | F56: =($R$75)*(16*30) -> 42771.6 | G56: =($R$75)*(16*30) -> 42771.6 | H56: =($R$75)*(16*30) -> 42771.6 | I56: =($R$75)*(16*30) -> 42771.6 | ... M56: =($R$75)*(16*30) -> 42771.6 | N56: =SUM(B56:M56) -> 513259.2
A57: Hamburguesa Hawaiana | B57: =($R$74)*(11*30) -> 29405.475 | C57: =($R$74)*(11*30) -> 29405.475 | D57: =($R$74)*(11*30) -> 29405.475 | E57: =($R$74)*(11*30) -> 29405.475 | F57: =($R$74)*(11*30) -> 29405.475 | G57: =($R$74)*(11*30) -> 29405.475 | H57: =($R$74)*(11*30) -> 29405.475 | I57: =($R$74)*(11*30) -> 29405.475 | ... M57: =($R$74)*(11*30) -> 29405.475 | N57: =SUM(B57:M57) -> 352865.7
A58: Ballenita | B58: =($R$76)*(5*30) -> 49900.2 | C58: =($R$76)*(5*30) -> 49900.2 | D58: =($R$76)*(5*30) -> 49900.2 | E58: =($R$76)*(5*30) -> 49900.2 | F58: =($R$76)*(5*30) -> 49900.2 | G58: =($R$76)*(5*30) -> 49900.2 | H58: =($R$76)*(5*30) -> 49900.2 | I58: =($R$76)*(5*30) -> 49900.2 | ... M58: =($R$76)*(5*30) -> 49900.2 | N58: =SUM(B58:M58) -> 598802.4
A59: Norteño | B59: =($R$77)*(5*30) -> 42771.6 | C59: =($R$77)*(5*30) -> 42771.6 | D59: =($R$77)*(5*30) -> 42771.6 | E59: =($R$77)*(5*30) -> 42771.6 | F59: =($R$77)*(5*30) -> 42771.6 | G59: =($R$77)*(5*30) -> 42771.6 | H59: =($R$77)*(5*30) -> 42771.6 | I59: =($R$77)*(5*30) -> 42771.6 | ... M59: =($R$77)*(5*30) -> 42771.6 | N59: =SUM(B59:M59) -> 513259.2
A60: Taco de Suadero | B60: =($R$78)*(56*30) -> 31936.128 | C60: =($R$78)*(56*30) -> 31936.128 | D60: =($R$78)*(56*30) -> 31936.128 | E60: =($R$78)*(56*30) -> 31936.128 | F60: =($R$78)*(56*30) -> 31936.128 | G60: =($R$78)*(56*30) -> 31936.128 | H60: =($R$78)*(56*30) -> 31936.128 | I60: =($R$78)*(56*30) -> 31936.128 | ... M60: =($R$78)*(56*30) -> 31936.128 | N60: =SUM(B60:M60) -> 383233.54
A61: Tacos de Bistec | B61: =($R$79)*(56*30) -> 31936.128 | C61: =($R$79)*(56*30) -> 31936.128 | D61: =($R$79)*(56*30) -> 31936.128 | E61: =($R$79)*(56*30) -> 31936.128 | F61: =($R$79)*(56*30) -> 31936.128 | G61: =($R$79)*(56*30) -> 31936.128 | H61: =($R$79)*(56*30) -> 31936.128 | I61: =($R$79)*(56*30) -> 31936.128 | ... M61: =($R$79)*(56*30) -> 31936.128 | N61: =SUM(B61:M61) -> 383233.54
A62: Tacos de Cabeza | B62: =($R$80)*(51*30) -> 29084.688 | C62: =($R$80)*(51*30) -> 29084.688 | D62: =($R$80)*(51*30) -> 29084.688 | E62: =($R$80)*(51*30) -> 29084.688 | F62: =($R$80)*(51*30) -> 29084.688 | G62: =($R$80)*(51*30) -> 29084.688 | H62: =($R$80)*(51*30) -> 29084.688 | I62: =($R$80)*(51*30) -> 29084.688 | ... M62: =($R$80)*(51*30) -> 29084.688 | N62: =SUM(B62:M62) -> 349016.26
A63: Taco de Maciza | B63: =($R$81)*(78*30) -> 44482.464 | C63: =($R$81)*(78*30) -> 44482.464 | D63: =($R$81)*(78*30) -> 44482.464 | E63: =($R$81)*(78*30) -> 44482.464 | F63: =($R$81)*(78*30) -> 44482.464 | G63: =($R$81)*(78*30) -> 44482.464 | H63: =($R$81)*(78*30) -> 44482.464 | I63: =($R$81)*(78*30) -> 44482.464 | ... M63: =($R$81)*(78*30) -> 44482.464 | N63: =SUM(B63:M63) -> 533789.57
A64: TOTAL DE INGRESOS | B64: =SUM(B51:B63) -> 1569254.4 | C64: =SUM(C51:C63) -> 1569254.4 | D64: =SUM(D51:D63) -> 1569254.4 | E64: =SUM(E51:E63) -> 1569254.4 | F64: =SUM(F51:F63) -> 1569254.4 | G64: =SUM(G51:G63) -> 1569254.4 | H64: =SUM(H51:H63) -> 1569254.4 | I64: =SUM(I51:I63) -> 1569254.4 | ... M64: =SUM(M51:M63) -> 1569254.4 | N64: =(B64+C64+D64+E64+F64+G64)+(H64+I64+J64+K64+L64+M64)*1.18 -> 20525847
A68: CONCEPTOS | B68: INGRESOS POR VENTA MENSUAL AÑO 4 | P68: Incremeneto del 9% del precio unitario anual
A69: MES | B69: 1 | C69: 2 | D69: 3 | E69: 4 | F69: 5 | G69: 6 | H69: 7 | I69: 8 | J69: 9 | K69: 10 | L69: 11 | M69: 12 | N69: TOTAL | P69: 16 | Q69: =P69*1.09 -> 17.44 | R69: =Q69*1.09 -> 19.0096 | S69: =R69*1.09 -> 20.720464 | T69: =S69*1.09 -> 22.585306
A70: Productos del local | N70: ANUAL | P70: 100 | Q70: =P70*1.09 -> 109 | R70: =Q70*1.09 -> 118.81 | S70: =R70*1.09 -> 129.5029 | T70: =S70*1.09 -> 141.15816
A71: Tacos al pastor | B71: =$S$69*(438*30) -> 272266.9 | C71: =$S$69*(438*30) -> 272266.9 | D71: =$S$69*(438*30) -> 272266.9 | E71: =$S$69*(438*30) -> 272266.9 | F71: =$S$69*(438*30) -> 272266.9 | G71: =$S$69*(438*30) -> 272266.9 | H71: =$S$69*(438*30) -> 272266.9 | I71: =$S$69*(438*30) -> 272266.9 | ... M71: =$S$69*(438*30) -> 272266.9 | N71: =SUM(B71:M71) -> 3267202.8 | P71: 220 | Q71: =P71*1.09 -> 239.8 | R71: =Q71*1.09 -> 261.382 | S71: =R71*1.09 -> 284.90638 | T71: =S71*1.09 -> 310.54795
A72: Taco arabe gigante | B72: =$S$70*(143*30) -> 555567.44 | C72: =$S$70*(143*30) -> 555567.44 | D72: =$S$70*(143*30) -> 555567.44 | E72: =$S$70*(143*30) -> 555567.44 | F72: =$S$70*(143*30) -> 555567.44 | G72: =$S$70*(143*30) -> 555567.44 | H72: =$S$70*(143*30) -> 555567.44 | I72: =$S$70*(143*30) -> 555567.44 | ... M72: =$S$70*(143*30) -> 555567.44 | N72: =SUM(B72:M72) -> 6666809.3 | P72: 45 | Q72: =P72*1.09 -> 49.05 | R72: =Q72*1.09 -> 53.4645 | S72: =R72*1.09 -> 58.276305 | T72: =S72*1.09 -> 63.521172
A73: Matahambre | B73: =$S$71*(56*30) -> 478642.72 | C73: =$S$71*(56*30) -> 478642.72 | D73: =$S$71*(56*30) -> 478642.72 | E73: =$S$71*(56*30) -> 478642.72 | F73: =$S$71*(56*30) -> 478642.72 | G73: =$S$71*(56*30) -> 478642.72 | H73: =$S$71*(56*30) -> 478642.72 | I73: =$S$71*(56*30) -> 478642.72 | ... M73: =$S$71*(56*30) -> 478642.72 | N73: =SUM(B73:M73) -> 5743712.6 | P73: 20 | Q73: =P73*1.09 -> 21.8 | R73: =Q73*1.09 -> 23.762 | S73: =R73*1.09 -> 25.90058 | T73: =S73*1.09 -> 28.231632
A74: 1 litro de agua de horchata | B74: =($S$72)*(303*4) -> 70630.882 | C74: =($S$72)*(303*4) -> 70630.882 | D74: =($S$72)*(303*4) -> 70630.882 | E74: =($S$72)*(303*4) -> 70630.882 | F74: =($S$72)*(303*4) -> 70630.882 | G74: =($S$72)*(303*4) -> 70630.882 | H74: =($S$72)*(303*4) -> 70630.882 | I74: =($S$72)*(303*4) -> 70630.882 | ... M74: =($S$72)*(303*4) -> 70630.882 | N74: =SUM(B74:M74) -> 847570.58 | P74: 75 | Q74: =P74*1.09 -> 81.75 | R74: =Q74*1.09 -> 89.1075 | S74: =R74*1.09 -> 97.127175 | T74: =S74*1.09 -> 105.86862
A75: Una tazas de cafe americano | B75: =($S$73)*(5*30) -> 3885.087 | C75: =($S$73)*(5*30) -> 3885.087 | D75: =($S$73)*(5*30) -> 3885.087 | E75: =($S$73)*(5*30) -> 3885.087 | F75: =($S$73)*(5*30) -> 3885.087 | G75: =($S$73)*(5*30) -> 3885.087 | H75: =($S$73)*(5*30) -> 3885.087 | I75: =($S$73)*(5*30) -> 3885.087 | ... M75: =($S$73)*(5*30) -> 3885.087 | N75: =SUM(B75:M75) -> 46621.044 | P75: 75 | Q75: =P75*1.09 -> 81.75 | R75: =Q75*1.09 -> 89.1075 | S75: =R75*1.09 -> 97.127175 | T75: =S75*1.09 -> 105.86862
A76: Tortas hawaiana | B76: =($S$75)*(16*30) -> 46621.044 | C76: =($S$75)*(16*30) -> 46621.044 | D76: =($S$75)*(16*30) -> 46621.044 | E76: =($S$75)*(16*30) -> 46621.044 | F76: =($S$75)*(16*30) -> 46621.044 | G76: =($S$75)*(16*30) -> 46621.044 | H76: =($S$75)*(16*30) -> 46621.044 | I76: =($S$75)*(16*30) -> 46621.044 | ... M76: =($S$75)*(16*30) -> 46621.044 | N76: =SUM(B76:M76) -> 559452.53 | P76: 280 | Q76: =P76*1.09 -> 305.2 | R76: =Q76*1.09 -> 332.668 | S76: =R76*1.09 -> 362.60812 | T76: =S76*1.09 -> 395.24285
A77: Hamburguesa Hawaiana | B77: =($S$74)*(11*30) -> 32051.968 | C77: =($S$74)*(11*30) -> 32051.968 | D77: =($S$74)*(11*30) -> 32051.968 | E77: =($S$74)*(11*30) -> 32051.968 | F77: =($S$74)*(11*30) -> 32051.968 | G77: =($S$74)*(11*30) -> 32051.968 | H77: =($S$74)*(11*30) -> 32051.968 | I77: =($S$74)*(11*30) -> 32051.968 | ... M77: =($S$74)*(11*30) -> 32051.968 | N77: =SUM(B77:M77) -> 384623.61 | P77: 240 | Q77: =P77*1.09 -> 261.6 | R77: =Q77*1.09 -> 285.144 | S77: =R77*1.09 -> 310.80696 | T77: =S77*1.09 -> 338.77959
A78: Ballenita | B78: =($S$76)*(5*30) -> 54391.218 | C78: =($S$76)*(5*30) -> 54391.218 | D78: =($S$76)*(5*30) -> 54391.218 | E78: =($S$76)*(5*30) -> 54391.218 | F78: =($S$76)*(5*30) -> 54391.218 | G78: =($S$76)*(5*30) -> 54391.218 | H78: =($S$76)*(5*30) -> 54391.218 | I78: =($S$76)*(5*30) -> 54391.218 | ... M78: =($S$76)*(5*30) -> 54391.218 | N78: =SUM(B78:M78) -> 652694.62 | P78: 16 | Q78: =P78*1.09 -> 17.44 | R78: =Q78*1.09 -> 19.0096 | S78: =R78*1.09 -> 20.720464 | T78: =S78*1.09 -> 22.585306
A79: Norteño | B79: =($S$77)*(5*30) -> 46621.044 | C79: =($S$77)*(5*30) -> 46621.044 | D79: =($S$77)*(5*30) -> 46621.044 | E79: =($S$77)*(5*30) -> 46621.044 | F79: =($S$77)*(5*30) -> 46621.044 | G79: =($S$77)*(5*30) -> 46621.044 | H79: =($S$77)*(5*30) -> 46621.044 | I79: =($S$77)*(5*30) -> 46621.044 | ... M79: =($S$77)*(5*30) -> 46621.044 | N79: =SUM(B79:M79) -> 559452.53 | P79: 16 | Q79: =P79*1.09 -> 17.44 | R79: =Q79*1.09 -> 19.0096 | S79: =R79*1.09 -> 20.720464 | T79: =S79*1.09 -> 22.585306
A80: Taco de Suadero | B80: =($S$78)*(56*30) -> 34810.38 | C80: =($S$78)*(56*30) -> 34810.38 | D80: =($S$78)*(56*30) -> 34810.38 | E80: =($S$78)*(56*30) -> 34810.38 | F80: =($S$78)*(56*30) -> 34810.38 | G80: =($S$78)*(56*30) -> 34810.38 | H80: =($S$78)*(56*30) -> 34810.38 | I80: =($S$78)*(56*30) -> 34810.38 | ... M80: =($S$78)*(56*30) -> 34810.38 | N80: =SUM(B80:M80) -> 417724.55 | P80: 16 | Q80: =P80*1.09 -> 17.44 | R80: =Q80*1.09 -> 19.0096 | S80: =R80*1.09 -> 20.720464 | T80: =S80*1.09 -> 22.585306
A81: Tacos de Bistec | B81: =($S$79)*(56*30) -> 34810.38 | C81: =($S$79)*(56*30) -> 34810.38 | D81: =($S$79)*(56*30) -> 34810.38 | E81: =($S$79)*(56*30) -> 34810.38 | F81: =($S$79)*(56*30) -> 34810.38 | G81: =($S$79)*(56*30) -> 34810.38 | H81: =($S$79)*(56*30) -> 34810.38 | I81: =($S$79)*(56*30) -> 34810.38 | ... M81: =($S$79)*(56*30) -> 34810.38 | N81: =SUM(B81:M81) -> 417724.55 | P81: 16 | Q81: =P81*1.09 -> 17.44 | R81: =Q81*1.09 -> 19.0096 | S81: =R81*1.09 -> 20.720464 | T81: =S81*1.09 -> 22.585306
A82: Tacos de Cabeza | B82: =($S$80)*(51*30) -> 31702.31 | C82: =($S$80)*(51*30) -> 31702.31 | D82: =($S$80)*(51*30) -> 31702.31 | E82: =($S$80)*(51*30) -> 31702.31 | F82: =($S$80)*(51*30) -> 31702.31 | G82: =($S$80)*(51*30) -> 31702.31 | H82: =($S$80)*(51*30) -> 31702.31 | I82: =($S$80)*(51*30) -> 31702.31 | ... M82: =($S$80)*(51*30) -> 31702.31 | N82: =SUM(B82:M82) -> 380427.72
A83: Taco de Maciza | B83: =($S$81)*(78*30) -> 48485.886 | C83: =($S$81)*(78*30) -> 48485.886 | D83: =($S$81)*(78*30) -> 48485.886 | E83: =($S$81)*(78*30) -> 48485.886 | F83: =($S$81)*(78*30) -> 48485.886 | G83: =($S$81)*(78*30) -> 48485.886 | H83: =($S$81)*(78*30) -> 48485.886 | I83: =($S$81)*(78*30) -> 48485.886 | ... M83: =($S$81)*(78*30) -> 48485.886 | N83: =SUM(B83:M83) -> 581830.63
A84: TOTAL DE INGRESOS | B84: =SUM(B71:B83) -> 1710487.3 | C84: =SUM(C71:C83) -> 1710487.3 | D84: =SUM(D71:D83) -> 1710487.3 | E84: =SUM(E71:E83) -> 1710487.3 | F84: =SUM(F71:F83) -> 1710487.3 | G84: =SUM(G71:G83) -> 1710487.3 | H84: =SUM(H71:H83) -> 1710487.3 | I84: =SUM(I71:I83) -> 1710487.3 | ... M84: =SUM(M71:M83) -> 1710487.3 | N84: =(B84+C84+D84+E84+F84+G84)+(H84+I84+J84+K84+L84+M84)*1.27 -> 23296836
A88: CONCEPTOS | B88: INGRESOS POR VENTA MENSUAL AÑO 5
A89: MES | B89: 1 | C89: 2 | D89: 3 | E89: 4 | F89: 5 | G89: 6 | H89: 7 | I89: 8 | J89: 9 | K89: 10 | L89: 11 | M89: 12 | N89: TOTAL
A90: Productos del local | N90: ANUAL
A91: Tacos al pastor | B91: =$T$69*(438*30) -> 296770.92 | C91: =$T$69*(438*30) -> 296770.92 | D91: =$T$69*(438*30) -> 296770.92 | E91: =$T$69*(438*30) -> 296770.92 | F91: =$T$69*(438*30) -> 296770.92 | G91: =$T$69*(438*30) -> 296770.92 | H91: =$T$69*(438*30) -> 296770.92 | I91: =$T$69*(438*30) -> 296770.92 | ... M91: =$T$69*(438*30) -> 296770.92 | N91: =SUM(B91:M91) -> 3561251
A92: Taco arabe gigante | B92: =$T$70*(143*30) -> 605568.51 | C92: =$T$70*(143*30) -> 605568.51 | D92: =$T$70*(143*30) -> 605568.51 | E92: =$T$70*(143*30) -> 605568.51 | F92: =$T$70*(143*30) -> 605568.51 | G92: =$T$70*(143*30) -> 605568.51 | H92: =$T$70*(143*30) -> 605568.51 | I92: =$T$70*(143*30) -> 605568.51 | ... M92: =$T$70*(143*30) -> 605568.51 | N92: =SUM(B92:M92) -> 7266822.1
A93: Matahambre | B93: =$T$71*(56*30) -> 521720.56 | C93: =$T$71*(56*30) -> 521720.56 | D93: =$T$71*(56*30) -> 521720.56 | E93: =$T$71*(56*30) -> 521720.56 | F93: =$T$71*(56*30) -> 521720.56 | G93: =$T$71*(56*30) -> 521720.56 | H93: =$T$71*(56*30) -> 521720.56 | I93: =$T$71*(56*30) -> 521720.56 | ... M93: =$T$71*(56*30) -> 521720.56 | N93: =SUM(B93:M93) -> 6260646.8
A94: 1 litro de agua de horchata | B94: =($T$72)*(303*4) -> 76987.661 | C94: =($T$72)*(303*4) -> 76987.661 | D94: =($T$72)*(303*4) -> 76987.661 | E94: =($T$72)*(303*4) -> 76987.661 | F94: =($T$72)*(303*4) -> 76987.661 | G94: =($T$72)*(303*4) -> 76987.661 | H94: =($T$72)*(303*4) -> 76987.661 | I94: =($T$72)*(303*4) -> 76987.661 | ... M94: =($T$72)*(303*4) -> 76987.661 | N94: =SUM(B94:M94) -> 923851.93
A95: Una tazas de cafe americano | B95: =($T$73)*(5*30) -> 4234.7448 | C95: =($T$73)*(5*30) -> 4234.7448 | D95: =($T$73)*(5*30) -> 4234.7448 | E95: =($T$73)*(5*30) -> 4234.7448 | F95: =($T$73)*(5*30) -> 4234.7448 | G95: =($T$73)*(5*30) -> 4234.7448 | H95: =($T$73)*(5*30) -> 4234.7448 | I95: =($T$73)*(5*30) -> 4234.7448 | ... M95: =($T$73)*(5*30) -> 4234.7448 | N95: =SUM(B95:M95) -> 50816.938
A96: Tortas hawaiana | B96: =($T$74)*(16*30) -> 50816.938 | C96: =($T$74)*(16*30) -> 50816.938 | D96: =($T$74)*(16*30) -> 50816.938 | E96: =($T$74)*(16*30) -> 50816.938 | F96: =($T$74)*(16*30) -> 50816.938 | G96: =($T$74)*(16*30) -> 50816.938 | H96: =($T$74)*(16*30) -> 50816.938 | I96: =($T$74)*(16*30) -> 50816.938 | ... M96: =($T$74)*(16*30) -> 50816.938 | N96: =SUM(B96:M96) -> 609803.26
A97: Hamburguesa Hawaiana | B97: =($T$75)*(11*30) -> 34936.645 | C97: =($T$75)*(11*30) -> 34936.645 | D97: =($T$75)*(11*30) -> 34936.645 | E97: =($T$75)*(11*30) -> 34936.645 | F97: =($T$75)*(11*30) -> 34936.645 | G97: =($T$75)*(11*30) -> 34936.645 | H97: =($T$75)*(11*30) -> 34936.645 | I97: =($T$75)*(11*30) -> 34936.645 | ... M97: =($T$75)*(11*30) -> 34936.645 | N97: =SUM(B97:M97) -> 419239.74
A98: Ballenita | B98: =($T$76)*(5*30) -> 59286.428 | C98: =($T$76)*(5*30) -> 59286.428 | D98: =($T$76)*(5*30) -> 59286.428 | E98: =($T$76)*(5*30) -> 59286.428 | F98: =($T$76)*(5*30) -> 59286.428 | G98: =($T$76)*(5*30) -> 59286.428 | H98: =($T$76)*(5*30) -> 59286.428 | I98: =($T$76)*(5*30) -> 59286.428 | ... M98: =($T$76)*(5*30) -> 59286.428 | N98: =SUM(B98:M98) -> 711437.13
A99: Norteño | B99: =($T$77)*(5*30) -> 50816.938 | C99: =($T$77)*(5*30) -> 50816.938 | D99: =($T$77)*(5*30) -> 50816.938 | E99: =($T$77)*(5*30) -> 50816.938 | F99: =($T$77)*(5*30) -> 50816.938 | G99: =($T$77)*(5*30) -> 50816.938 | H99: =($T$77)*(5*30) -> 50816.938 | I99: =($T$77)*(5*30) -> 50816.938 | ... M99: =($T$77)*(5*30) -> 50816.938 | N99: =SUM(B99:M99) -> 609803.26
A100: Taco de Suadero | B100: =($T$78)*(56*30) -> 37943.314 | C100: =($T$78)*(56*30) -> 37943.314 | D100: =($T$78)*(56*30) -> 37943.314 | E100: =($T$78)*(56*30) -> 37943.314 | F100: =($T$78)*(56*30) -> 37943.314 | G100: =($T$78)*(56*30) -> 37943.314 | H100: =($T$78)*(56*30) -> 37943.314 | I100: =($T$78)*(56*30) -> 37943.314 | ... M100: =($T$78)*(56*30) -> 37943.314 | N100: =SUM(B100:M100) -> 455319.76
A101: Tacos de Bistec | B101: =($T$79)*(56*30) -> 37943.314 | C101: =($T$79)*(56*30) -> 37943.314 | D101: =($T$79)*(56*30) -> 37943.314 | E101: =($T$79)*(56*30) -> 37943.314 | F101: =($T$79)*(56*30) -> 37943.314 | G101: =($T$79)*(56*30) -> 37943.314 | H101: =($T$79)*(56*30) -> 37943.314 | I101: =($T$79)*(56*30) -> 37943.314 | ... M101: =($T$79)*(56*30) -> 37943.314 | N101: =SUM(B101:M101) -> 455319.76
A102: Tacos de Cabeza | B102: =($T$80)*(51*30) -> 34555.518 | C102: =($T$80)*(51*30) -> 34555.518 | D102: =($T$80)*(51*30) -> 34555.518 | E102: =($T$80)*(51*30) -> 34555.518 | F102: =($T$80)*(51*30) -> 34555.518 | G102: =($T$80)*(51*30) -> 34555.518 | H102: =($T$80)*(51*30) -> 34555.518 | I102: =($T$80)*(51*30) -> 34555.518 | ... M102: =($T$80)*(51*30) -> 34555.518 | N102: =SUM(B102:M102) -> 414666.21
A103: Taco de Maciza | B103: =($T$81)*(78*30) -> 52849.615 | C103: =($T$81)*(78*30) -> 52849.615 | D103: =($T$81)*(78*30) -> 52849.615 | E103: =($T$81)*(78*30) -> 52849.615 | F103: =($T$81)*(78*30) -> 52849.615 | G103: =($T$81)*(78*30) -> 52849.615 | H103: =($T$81)*(78*30) -> 52849.615 | I103: =($T$81)*(78*30) -> 52849.615 | ... M103: =($T$81)*(78*30) -> 52849.615 | N103: =SUM(B103:M103) -> 634195.39
A104: TOTAL DE INGRESOS | B104: =SUM(B91:B103) -> 1864431.1 | C104: =SUM(C91:C103) -> 1864431.1 | D104: =SUM(D91:D103) -> 1864431.1 | E104: =SUM(E91:E103) -> 1864431.1 | F104: =SUM(F91:F103) -> 1864431.1 | G104: =SUM(G91:G103) -> 1864431.1 | H104: =SUM(H91:H103) -> 1864431.1 | I104: =SUM(I91:I103) -> 1864431.1 | ... M104: =SUM(M91:M103) -> 1864431.1 | N104: =(B104+C104+D104+E104+F104+G104)+(H104+I104+J104+K104+L104+M104)*1.36 -> 26400344

Sheet DEPRECIACIONES
A1: CALCULO DE DEPRECIACIONES Y AMORTIZACIONES
A3: PROYECTO:
A4: SOCIEDAD
A7: MUEBLES Y EQUIPO | B7: VALOR | C7: VIDA UTIL (AÑOS) | D7: TASA DE DEPREC. | E7: DEPRECIACION (ANUAL) | F7: DEPRECIACION (MENSUAL) | G7: DEPRC. ACUM | H7: REMANENTE
A8: Edificio | B8: 500000 | C8: 20 | D8: 0.05 | E8: =B8*D8 -> 25000 | F8: =E8/12 -> 2083.3333 | G8: =E8*3 -> 75000 | H8: =B8-G8 -> 425000
A9: Terreno | B9: 820000 | C9: Indefinido | D9: 0 | E9: =B9*D9 -> 0 | F9: =E9/12 -> 0 | G9: =E9*3 -> 0 | H9: =B9-G9 -> 820000
A10: Campana | B10: 18348.88 | C10: 10 | D10: 0.1 | E10: =B10*D10 -> 1834.888 | F10: =E10/12 -> 152.90733 | G10: =E10*3 -> 5504.664 | H10: =B10-G10 -> 12844.216
A11: Juego de sillas y mesas | B11: 79020 | C11: 10 | D11: 0.1 | E11: =B11*D11 -> 7902 | F11: =E11/12 -> 658.5 | G11: =E11*3 -> 23706 | H11: =B11-G11 -> 55314
A12: Mesas de trabajo | B12: 85649.84 | C12: 10 | D12: 0.1 | E12: =B12*D12 -> 8564.984 | F12: =E12/12 -> 713.74867 | G12: =E12*3 -> 25694.952 | H12: =B12-G12 -> 59954.888
A13: Instrumentos de cocina | B13: ='CUADRO DE INVERSION'!F29 -> 3626.12 | C13: 10 | D13: 0.1 | E13: =B13*D13 -> 362.612 | F13: =E13/12 -> 30.217667 | G13: =E13*3 -> 1087.836 | H13: =B13-G13 -> 2538.284
B14: =SUM(B10:B13) -> 186644.84 | H14: =SUM(H8:H13) -> 1375651.4
A16: MAQUINARIA | C16: VIDA UTIL (AÑOS) | D16: TASA DE DEPREC. | E16: DEPRECIACION (ANUAL) | F16: DEPRECIACION (MENSUAL) | G16: DEPRC. ACUM | H16: REMANENTE
A17: Máquina de empaquetado | B17: 119816.32 | C17: 15 | D17: 0.1 | E17: =B17*D17 -> 11981.632 | F17: =E17/12 -> 998.46933 | G17: =E17*3 -> 35944.896 | H17: =B17-G17 -> 83871.424
A18: Planchas | B18: 84760 | C18: 15 | D18: 0.1 | E18: =B18*D18 -> 8476 | F18: =E18/12 -> 706.33333 | G18: =E18*3 -> 25428 | H18: =B18-G18 -> 59332
A19: Trampa de aceite | B19: 8131.73 | C19: 5 | D19: 0.1 | E19: =B19*D19 -> 813.173 | F19: =E19/12 -> 67.764417 | G19: =E19*3 -> 2439.519 | H19: =B19-G19 -> 5692.211
A20: Trompos | B20: 21888.5 | C20: 5 | D20: 0.1 | E20: =B20*D20 -> 2188.85 | F20: =E20/12 -> 182.40417 | G20: =E20*3 -> 6566.55 | H20: =B20-G20 -> 15321.95
A21: Molinos industriales | B21: 58271.44 | C21: 15 | D21: 0.1 | E21: =B21*D21 -> 5827.144 | F21: =E21/12 -> 485.59533 | G21: =E21*3 -> 17481.432 | H21: =B21-G21 -> 40790.008
A22: Congeladores | B22: 35398.56 | C22: 20 | D22: 0.1 | E22: =B22*D22 -> 3539.856 | F22: =E22/12 -> 294.988 | G22: =E22*3 -> 10619.568 | H22: =B22-G22 -> 24778.992
A23: Equipo de registro de venta | B23: ='CUADRO DE INVERSION'!G30 -> 3599 | C23: 3.3333333 | D23: 0.3 | E23: =B23*D23 -> 1079.7 | F23: =E23/12 -> 89.975 | G23: =E23*3 -> 3239.1 | H23: =B23-G23 -> 359.9
A24: EQUIPO DE REGISTRO DE VENTA TERMINAL | B24: ='CUADRO DE INVERSION'!F31 -> 4590 | C24: 4.3333333 | D24: 0.3 | E24: =B24*D24 -> 1377 | F24: =E24/12 -> 114.75 | G24: =E24*3 -> 4131 | H24: =B24-G24 -> 459
B25: =SUM(B17:B23) -> 331865.55 | H25: =SUM(H17:H23) -> 230146.49
E26: =SUM(E8:E13)+SUM(E17:E24) -> 78947.839

Sheet AMORTIZACIONES
A1: AMORTIZACIÓN DE LA DEUDA
I2: Número de cuotas | J2: 36
A3: PROYECTO: | C3: Takirin "La chimenea" | I3: Tasa de interes anual | J3: 0.219
A4: SOCIEDAD | C4: FIRA | I4: Tasa de interes mensual | J4: =J3/12 -> 0.01825
A5: BENEFICIARIOS: | C5: Takirin "La chimenea" | I5: Cantidad solicitada | J5: ='CUADRO DE INVERSION'!C10 -> 1127676.7
A6: TABLA DE AMORTIZACION DE LA DEUDA
A8: MESES | B8: Total de prestamo con interes | C8: TASA DE INTERES | D8: INTERES | E8: DEUDA ACUMULADA | F8: PAGO CAPITAL | G8: PAGO INTERES | H8: PAGO TOTAL | I8: SALDO | J8: FECHAS DE PAGO
A9: 1 | B9: =$H$45 -> 1508408.6 | C9: =$J$3/12 -> 0.01825 | D9: =J5*$C$9 -> 20580.1 | E9: =J5+D9 -> 1148256.8 | F9: =$J$5/36 -> 31324.353 | G9: =D9 -> 20580.1 | H9: =G9+F9 -> 51904.453 | I9: =E9-H9 -> 1096352.4
A10: 2 | B10: =$H$45 -> 1508408.6 | C10: =$J$3/12 -> 0.01825 | D10: =I9*$C$9 -> 20008.431 | E10: =I9+D10 -> 1116360.8 | F10: =$J$5/36 -> 31324.353 | G10: =D10 -> 20008.431 | H10: =G10+F10 -> 51332.784 | I10: =I9-F10 -> 1065028
A11: 3 | B11: =$H$45 -> 1508408.6 | C11: =$J$3/12 -> 0.01825 | D11: =I10*$C$9 -> 19436.761 | E11: =I10+D11 -> 1084464.8 | F11: =$J$5/36 -> 31324.353 | G11: =D11 -> 19436.761 | H11: =G11+F11 -> 50761.114 | I11: =I10-F11 -> 1033703.7
A12: 4 | B12: =$H$45 -> 1508408.6 | C12: =$J$3/12 -> 0.01825 | D12: =I11*$C$9 -> 18865.092 | E12: =I11+D12 -> 1052568.7 | F12: =$J$5/36 -> 31324.353 | G12: =D12 -> 18865.092 | H12: =G12+F12 -> 50189.445 | I12: =I11-F12 -> 1002379.3
A13: 5 | B13: =$H$45 -> 1508408.6 | C13: =$J$3/12 -> 0.01825 | D13: =I12*$C$9 -> 18293.422 | E13: =I12+D13 -> 1020672.7 | F13: =$J$5/36 -> 31324.353 | G13: =D13 -> 18293.422 | H13: =G13+F13 -> 49617.775 | I13: =I12-F13 -> 971054.94
A14: 6 | B14: =$H$45 -> 1508408.6 | C14: =$J$3/12 -> 0.01825 | D14: =I13*$C$9 -> 17721.753 | E14: =I13+D14 -> 988776.7 | F14: =$J$5/36 -> 31324.353 | G14: =D14 -> 17721.753 | H14: =G14+F14 -> 49046.106 | I14: =I13-F14 -> 939730.59
A15: 7 | B15: =$H$45 -> 1508408.6 | C15: =$J$3/12 -> 0.01825 | D15: =I14*$C$9 -> 17150.083 | E15: =I14+D15 -> 956880.67 | F15: =$J$5/36 -> 31324.353 | G15: =D15 -> 17150.083 | H15: =G15+F15 -> 48474.436 | I15: =I14-F15 -> 908406.24
A16: 8 | B16: =$H$45 -> 1508408.6 | C16: =$J$3/12 -> 0.01825 | D16: =I15*$C$9 -> 16578.414 | E16: =I15+D16 -> 924984.65 | F16: =$J$5/36 -> 31324.353 | G16: =D16 -> 16578.414 | H16: =G16+F16 -> 47902.767 | I16: =I15-F16 -> 877081.89
A17: 9 | B17: =$H$45 -> 1508408.6 | C17: =$J$3/12 -> 0.01825 | D17: =I16*$C$9 -> 16006.744 | E17: =I16+D17 -> 893088.63 | F17: =$J$5/36 -> 31324.353 | G17: =D17 -> 16006.744 | H17: =G17+F17 -> 47331.097 | I17: =I16-F17 -> 845757.53
A18: 10 | B18: =$H$45 -> 1508408.6 | C18: =$J$3/12 -> 0.01825 | D18: =I17*$C$9 -> 15435.075 | E18: =I17+D18 -> 861192.61 | F18: =$J$5/36 -> 31324.353 | G18: =D18 -> 15435.075 | H18: =G18+F18 -> 46759.428 | I18: =I17-F18 -> 814433.18
A19: 11 | B19: =$H$45 -> 1508408.6 | C19: =$J$3/12 -> 0.01825 | D19: =I18*$C$9 -> 14863.406 | E19: =I18+D19 -> 829296.58 | F19: =$J$5/36 -> 31324.353 | G19: =D19 -> 14863.406 | H19: =G19+F19 -> 46187.759 | I19: =I18-F19 -> 783108.83
A20: 12 | B20: =$H$45 -> 1508408.6 | C20: =$J$3/12 -> 0.01825 | D20: =I19*$C$9 -> 14291.736 | E20: =I19+D20 -> 797400.56 | F20: =$J$5/36 -> 31324.353 | G20: =D20 -> 14291.736 | H20: =G20+F20 -> 45616.089 | I20: =I19-F20 -> 751784.47
A21: 13 | B21: =$H$45 -> 1508408.6 | C21: =$J$3/12 -> 0.01825 | D21: =I20*$C$9 -> 13720.067 | E21: =I20+D21 -> 765504.54 | F21: =$J$5/36 -> 31324.353 | G21: =D21 -> 13720.067 | H21: =G21+F21 -> 45044.42 | I21: =I20-F21 -> 720460.12
... A26: 18 | B26: =$H$45 -> 1508408.6 | C26: =$J$3/12 -> 0.01825 | D26: =I25*$C$9 -> 10861.719 | E26: =I25+D26 -> 606024.43 | F26: =$J$5/36 -> 31324.353 | G26: =D26 -> 10861.719 | H26: =G26+F26 -> 42186.072 | I26: =I25-F26 -> 563838.35
A27: =A26+1 -> 19 | B27: =$H$45 -> 1508408.6 | C27: =$J$3/12 -> 0.01825 | D27: =I26*$C$9 -> 10290.05 | E27: =I26+D27 -> 574128.4 | F27: =$J$5/36 -> 31324.353 | G27: =D27 -> 10290.05 | H27: =G27+F27 -> 41614.403 | I27: =I26-F27 -> 532514
A28: =A27+1 -> 20 | B28: =$H$45 -> 1508408.6 | C28: =$J$3/12 -> 0.01825 | D28: =I27*$C$9 -> 9718.3805 | E28: =I27+D28 -> 542232.38 | F28: =$J$5/36 -> 31324.353 | G28: =D28 -> 9718.3805 | H28: =G28+F28 -> 41042.734 | I28: =I27-F28 -> 501189.65
A29: =A28+1 -> 21 | B29: =$H$45 -> 1508408.6 | C29: =$J$3/12 -> 0.01825 | D29: =I28*$C$9 -> 9146.7111 | E29: =I28+D29 -> 510336.36 | F29: =$J$5/36 -> 31324.353 | G29: =D29 -> 9146.7111 | H29: =G29+F29 -> 40471.064 | I29: =I28-F29 -> 469865.3
A30: =A29+1 -> 22 | B30: =$H$45 -> 1508408.6 | C30: =$J$3/12 -> 0.01825 | D30: =I29*$C$9 -> 8575.0416 | E30: =I29+D30 -> 478440.34 | F30: =$J$5/36 -> 31324.353 | G30: =D30 -> 8575.0416 | H30: =G30+F30 -> 39899.395 | I30: =I29-F30 -> 438540.94
A31: =A30+1 -> 23 | B31: =$H$45 -> 1508408.6 | C31: =$J$3/12 -> 0.01825 | D31: =I30*$C$9 -> 8003.3722 | E31: =I30+D31 -> 446544.31 | F31: =$J$5/36 -> 31324.353 | G31: =D31 -> 8003.3722 | H31: =G31+F31 -> 39327.725 | I31: =I30-F31 -> 407216.59
A32: =A31+1 -> 24 | B32: =$H$45 -> 1508408.6 | C32: =$J$3/12 -> 0.01825 | D32: =I31*$C$9 -> 7431.7028 | E32: =I31+D32 -> 414648.29 | F32: =$J$5/36 -> 31324.353 | G32: =D32 -> 7431.7028 | H32: =G32+F32 -> 38756.056 | I32: =I31-F32 -> 375892.24
A33: =A32+1 -> 25 | B33: =$H$45 -> 1508408.6 | C33: =$J$3/12 -> 0.01825 | D33: =I32*$C$9 -> 6860.0333 | E33: =I32+D33 -> 382752.27 | F33: =$J$5/36 -> 31324.353 | G33: =D33 -> 6860.0333 | H33: =G33+F33 -> 38184.386 | I33: =I32-F33 -> 344567.88
A34: =A33+1 -> 26 | B34: =$H$45 -> 1508408.6 | C34: =$J$3/12 -> 0.01825 | D34: =I33*$C$9 -> 6288.3639 | E34: =I33+D34 -> 350856.25 | F34: =$J$5/36 -> 31324.353 | G34: =D34 -> 6288.3639 | H34: =G34+F34 -> 37612.717 | I34: =I33-F34 -> 313243.53
A35: =A34+1 -> 27 | B35: =$H$45 -> 1508408.6 | C35: =$J$3/12 -> 0.01825 | D35: =I34*$C$9 -> 5716.6944 | E35: =I34+D35 -> 318960.22 | F35: =$J$5/36 -> 31324.353 | G35: =D35 -> 5716.6944 | H35: =G35+F35 -> 37041.047 | I35: =I34-F35 -> 281919.18
A36: =A35+1 -> 28 | B36: =$H$45 -> 1508408.6 | C36: =$J$3/12 -> 0.01825 | D36: =I35*$C$9 -> 5145.025 | E36: =I35+D36 -> 287064.2 | F36: =$J$5/36 -> 31324.353 | G36: =D36 -> 5145.025 | H36: =G36+F36 -> 36469.378 | I36: =I35-F36 -> 250594.82
A37: =A36+1 -> 29 | B37: =$H$45 -> 1508408.6 | C37: =$J$3/12 -> 0.01825 | D37: =I36*$C$9 -> 4573.3555 | E37: =I36+D37 -> 255168.18 | F37: =$J$5/36 -> 31324.353 | G37: =D37 -> 4573.3555 | H37: =G37+F37 -> 35897.709 | I37: =I36-F37 -> 219270.47
A38: =A37+1 -> 30 | B38: =$H$45 -> 1508408.6 | C38: =$J$3/12 -> 0.01825 | D38: =I37*$C$9 -> 4001.6861 | E38: =I37+D38 -> 223272.16 | F38: =$J$5/36 -> 31324.353 | G38: =D38 -> 4001.6861 | H38: =G38+F38 -> 35326.039 | I38: =I37-F38 -> 187946.12
... A44: =A43+1 -> 36 | B44: =$H$45 -> 1508408.6 | C44: =$J$3/12 -> 0.01825 | D44: =I43*$C$9 -> 571.66944 | E44: =I43+D44 -> 31896.022 | F44: =$J$5/36 -> 31324.353 | G44: =D44 -> 571.66944 | H44: =G44+F44 -> 31896.022 | I44: =I43-F44 -> -3.7107384e-10
A45: TOTAL | D45: =SUM(D9:D44) -> 380731.85 | F45: =SUM(F9:F44) -> 1127676.7 | G45: =SUM(G9:G44) -> 380731.85 | H45: =SUM(H9:H44) -> 1508408.6
A48: PRIMERA MINISTRACIÓN
A49: MONTO: | B49: =SUM(H9:H20) -> 585123.25
A50: FECHA:
A51: SEGUNDA MINISTRACIÓN
A52: MONTO:
A53: FECHA:

Sheet SENSIBILIDAD
A1: SENSIBILIZACION
A3: PROYECTO: | B3: Nueva Sucursal "Takirin"
A4: SOCIEDAD | B4: Taqueria la Chimenea "Takirin"
A5: BENEFICIARIOS:
A6: PARA EL PRIMER AÑO
C7: CAMBIO EN VENTAS | G7: CAMBIO EN COSTOS
A8: CONCEPTO | B8: TOTAL PROYECTO | C8: 0.05 | D8: 0.1 | E8: 0.15 | F8: 0.2 | G8: 0.05 | H8: 0.1 | I8: 0.15 | J8: 0.2
A9: VENTAS | B9: ='INGRESOS '!N24 -> 15123330 | C9: =(B9*0.05)+B9 -> 15879496 | D9: =($B$9*0.1)+$B$9 -> 16635663 | E9: =($B$9*0.15)+$B$9 -> 17391830 | F9: =($B$9*0.2)+$B$9 -> 18147996 | G9: =$B$9 -> 15123330 | H9: =$B$9 -> 15123330 | I9: =$B$9 -> 15123330 | J9: =$B$9 -> 15123330
A10: COSTOS TOTALES | B10: ='COSTOS '!R54 -> 4853900.6 | C10: =B10 -> 4853900.6 | D10: =C10 -> 4853900.6 | E10: =D10 -> 4853900.6 | F10: =E10 -> 4853900.6 | G10: =(F10*0.05)+F10 -> 5096595.6 | H10: =($B$10*0.1)+$B$10 -> 5339290.6 | I10: =($B$10*0.15)+$B$10 -> 5581985.6 | J10: =($B$10*0.2)+$B$10 -> 5824680.7 | L10: Impuestos
A11: TOTAL | B11: =SUM(B9-B10) -> 10269429 | C11: =C9-C10 -> 11025596 | D11: =D9-D10 -> 11781762 | E11: =E9-E10 -> 12537929 | F11: =F9-F10 -> 13294095 | G11: =G9-G10 -> 10026734 | H11: =H9-H10 -> 9784039.4 | I11: =I9-I10 -> 9541344.4 | J11: =J9-J10 -> 9298649.3 | L11: =B11*0.35 -> 3594300.3 | M11: Cont a fav
L12: =B11*0.16 -> 1643108.7 | M12: ='COSTOS '!N53*0.16 -> 776624.09 | N12: =L12-M12 -> 866484.62
A13: RELACION B/C | B13: =+B9/B10 -> 3.1157066 | C13: =+C9/C10 -> 3.2714919 | D13: =+D9/D10 -> 3.4272773 | E13: =+E9/E10 -> 3.5830626 | F13: =+F9/F10 -> 3.7388479 | G13: =+G9/G10 -> 2.9673396 | H13: =+H9/H10 -> 2.8324605 | I13: =+I9/I10 -> 2.7093101 | J13: =+J9/J10 -> 2.5964222 | N13: =L11+N12 -> 4460784.9
A15: PARA EL SEGUNDO AÑO
C16: CAMBIO EN VENTAS | G16: CAMBIO EN COSTOS
A17: CONCEPTO | B17: TOTAL PROYECTO | C17: 0.05 | D17: 0.1 | E17: 0.15 | F17: 0.2 | G17: 0.05 | H17: 0.1 | I17: 0.15 | J17: 0.2
A18: VENTAS | B18: ='INGRESOS '!N44 -> 17276195 | C18: =(B18*0.05)+B18 -> 18140005 | D18: =($B$18*0.1)+$B$18 -> 19003814 | E18: =($B$18*0.15)+$B$18 -> 19867624 | F18: =($B$18*0.2)+$B$18 -> 20731434 | G18: =$B$18 -> 17276195 | H18: =$B$18 -> 17276195 | I18: =$B$18 -> 17276195 | J18: =$B$18 -> 17276195
A19: COSTOS TOTALES | B19: ='COSTOS '!S54 -> 4944527.3 | C19: =B19 -> 4944527.3 | D19: =B19 -> 4944527.3 | E19: =B19 -> 4944527.3 | F19: =B19 -> 4944527.3 | G19: =(F19*0.05)+F19 -> 5191753.7 | H19: =($B$19*0.1)+$B$19 -> 5438980.1 | I19: =($B$19*0.15)+$B$19 -> 5686206.4 | J19: =($B$19*0.2)+$B$19 -> 5933432.8
A20: TOTAL | B20: =SUM(B18-B19) -> 12331667 | C20: =C18-C19 -> 13195477 | D20: =D18-D19 -> 14059287 | E20: =E18-E19 -> 14923097 | F20: =F18-F19 -> 15786906 | G20: =G18-G19 -> 12084441 | H20: =H18-H19 -> 11837215 | I20: =I18-I19 -> 11589988 | J20: =J18-J19 -> 11342762
A22: RELACION B/C | B22: =+B18/B19 -> 3.4940033 | C22: =+C18/C19 -> 3.6687035 | D22: =+D18/D19 -> 3.8434036 | E22: =+E18/E19 -> 4.0181038 | F22: =+F18/F19 -> 4.192804 | G22: =+G18/G19 -> 3.3276222 | H22: =+H18/H19 -> 3.1763666 | I22: =+I18/I19 -> 3.0382637 | J22: =+J18/J19 -> 2.9116694
A25: PARA EL TERCER AÑO
C26: CAMBIO EN VENTAS | G26: CAMBIO EN COSTOS
A27: CONCEPTO | B27: TOTAL PROYECTO | C27: 0.05 | D27: 0.1 | E27: 0.15 | F27: 0.2 | G27: 0.05 | H27: 0.1 | I27: 0.15 | J27: 0.2
A28: VENTAS | B28: ='INGRESOS '!N64 -> 20525847 | C28: =(B28*0.05)+B28 -> 21552139 | D28: =($B$28*0.1)+$B$28 -> 22578432 | E28: =($B$28*0.15)+$B$28 -> 23604724 | F28: =($B$28*0.2)+$B$28 -> 24631016 | G28: =$B$28 -> 20525847 | H28: =$B$28 -> 20525847 | I28: =$B$28 -> 20525847 | J28: =$B$28 -> 20525847
A29: COSTOS TOTALES | B29: ='COSTOS '!T54 -> 5038627.2 | C29: =$B$29 -> 5038627.2 | D29: =$B$29 -> 5038627.2 | E29: =$B$29 -> 5038627.2 | F29: =$B$29 -> 5038627.2 | G29: =(F29*0.05)+F29 -> 5290558.5 | H29: =($B$29*0.1)+$B$29 -> 5542489.9 | I29: =($B$29*0.15)+$B$29 -> 5794421.2 | J29: =($B$29*0.2)+$B$29 -> 6046352.6
A30: TOTAL | B30: =SUM(B28-B29) -> 15487220 | C30: =C28-C29 -> 16513512 | D30: =D28-D29 -> 17539805 | E30: =E28-E29 -> 18566097 | F30: =F28-F29 -> 19592389 | G30: =G28-G29 -> 15235289 | H30: =H28-H29 -> 14983357 | I30: =I28-I29 -> 14731426 | J30: =J28-J29 -> 14479494
A32: RELACION B/C | B32: =+B28/B29 -> 4.0736983 | C32: =+C28/C29 -> 4.2773832 | D32: =+D28/D29 -> 4.4810682 | E32: =+E28/E29 -> 4.6847531 | F32: =+F28/F29 -> 4.888438 | G32: =+G28/G29 -> 3.8797127 | H32: =+H28/H29 -> 3.7033621 | I32: =+I28/I29 -> 3.5423464 | J32: =+J28/J29 -> 3.3947486
A36: PARA EL CUARTO AÑO
C37: CAMBIO EN VENTAS | G37: CAMBIO EN COSTOS
A38: CONCEPTO | B38: TOTAL PROYECTO | C38: 0.05 | D38: 0.1 | E38: 0.15 | F38: 0.2 | G38: 0.05 | H38: 0.1 | I38: 0.15 | J38: 0.2
A39: VENTAS | B39: ='INGRESOS '!N84 -> 23296836 | C39: =(B39*0.05)+B39 -> 24461678 | D39: =($B$28*0.1)+$B$39 -> 25349421 | E39: =($B$28*0.15)+$B$39 -> 26375713 | F39: =($B$28*0.2)+$B$39 -> 27402006 | G39: =$B$39 -> 23296836 | H39: =$B$39 -> 23296836 | I39: =$B$39 -> 23296836 | J39: =$B$39 -> 23296836
A40: COSTOS TOTALES | B40: ='COSTOS '!U54 -> 5136333.2 | C40: =$B$40 -> 5136333.2 | D40: =$B$40 -> 5136333.2 | E40: =$B$40 -> 5136333.2 | F40: =$B$40 -> 5136333.2 | G40: =(F40*0.05)+F40 -> 5393149.8 | H40: =($B$40*0.1)+$B$40 -> 5649966.5 | I40: =($B$40*0.15)+$B$40 -> 5906783.1 | J40: =($B$40*0.2)+$B$40 -> 6163599.8
A41: TOTAL | B41: =SUM(B39-B40) -> 18160503 | C41: =SUM(C39-C40) -> 19325345 | D41: =SUM(D39-D40) -> 20213088 | E41: =SUM(E39-E40) -> 21239380 | F41: =SUM(F39-F40) -> 22265673 | G41: =SUM(G39-G40) -> 17903687 | H41: =SUM(H39-H40) -> 17646870 | I41: =SUM(I39-I40) -> 17390053 | J41: =SUM(J39-J40) -> 17133237
A43: RELACION B/C | B43: =+B39/B40 -> 4.5356942 | C43: =+C39/C40 -> 4.7624789 | D43: =+D39/D40 -> 4.9353148 | E43: =+E39/E40 -> 5.1351251 | F43: =+F39/F40 -> 5.3349354 | G43: =+G39/G40 -> 4.3197087 | H43: =+H39/H40 -> 4.1233583 | I43: =+I39/I40 -> 3.9440819 | J43: =+J39/J40 -> 3.7797451
A47: PARA EL QUINTO AÑO
C48: CAMBIO EN VENTAS | G48: CAMBIO EN COSTOS
A49: CONCEPTO | B49: TOTAL PROYECTO | C49: 0.05 | D49: 0.1 | E49: 0.15 | F49: 0.2 | G49: 0.05 | H49: 0.1 | I49: 0.15 | J49: 0.2
A50: VENTAS | B50: ='INGRESOS '!N104 -> 26400344 | C50: =(B50*0.05)+B50 -> 27720362 | D50: =(B50*0.1)+B50 -> 29040379 | E50: =(B50*0.15)+B50 -> 30360396 | F50: =(B50*0.2)+B50 -> 31680413 | G50: =$B$50 -> 26400344 | H50: =$B$50 -> 26400344 | I50: =$B$50 -> 26400344 | J50: =$B$50 -> 26400344
A51: COSTOS TOTALES | B51: ='COSTOS '!V54 -> 5237783.5 | C51: =$B$51 -> 5237783.5 | D51: =$B$51 -> 5237783.5 | E51: =$B$51 -> 5237783.5 | F51: =$B$51 -> 5237783.5 | G51: =(F51*0.05)+F51 -> 5499672.7 | H51: =($B$51*0.1)+$B$51 -> 5761561.9 | I51: =($B$51*0.15)+$B$51 -> 6023451 | J51: =($B$51*0.2)+$B$51 -> 6285340.2
A52: TOTAL | B52: =SUM(B50-B51) -> 21162561 | C52: =SUM(C50-C51) -> 22482578 | D52: =SUM(D50-D51) -> 23802595 | E52: =SUM(E50-E51) -> 25122613 | F52: =SUM(F50-F51) -> 26442630 | G52: =SUM(G50-G51) -> 20900672 | H52: =SUM(H50-H51) -> 20638783 | I52: =SUM(I50-I51) -> 20376893 | J52: =SUM(J50-J51) -> 20115004
A54: RELACION B/C | B54: =+B50/B51 -> 5.0403657 | C54: =+C50/C51 -> 5.292384 | D54: =+D50/D51 -> 5.5444023 | E54: =+E50/E51 -> 5.7964206 | F54: =+F50/F51 -> 6.0484389 | G54: =+G50/G51 -> 4.8003483 | H54: =+H50/H51 -> 4.5821507 | I54: =+I50/I51 -> 4.3829267 | J54: =+J50/J51 -> 4.2003048

Sheet TIR - VAN
B2: VAN, TIR Y B/C
C4: TASA DE ACTUALIZACIÓN | E4: 0.09
C6: AÑO | D6: INGRESOS | E6: COSTOS | F6: FLUJO DE EFECTIVO | G6: TASA | H6: INGRESOS | I6: EGRESOS
G7: (1+t)-n | H7: ACTUALIZADOS | I7: ACTUALIZADOS
C8: 0 | D8: ='INGRESOS '!N24 -> 15123330 | E8: ='COSTOS '!N53 -> 4853900.6 | F8: =D8-E8 -> 10269429 | G8: =1/(1+$E$4)^C8 -> 1 | H8: =G8*D8 -> 15123330 | I8: =G8*E8 -> 4853900.6
C9: 1 | D9: ='INGRESOS '!N44 -> 17276195 | E9: ='COSTOS '!N106 -> 4944527.3 | F9: =D9-E9 -> 12331667 | G9: =1/(1+$E$4)^C9 -> 0.91743119 | H9: =G9*D9 -> 15849720 | I9: =G9*E9 -> 4536263.6 | J9: =H9/I9 -> 3.4940033
C10: 2 | D10: ='INGRESOS '!N64 -> 20525847 | E10: ='COSTOS '!N159 -> 5038627.2 | F10: =D10-E10 -> 15487220 | G10: =1/(1+$E$4)^C10 -> 0.84167999 | H10: =G10*D10 -> 17276195 | I10: =G10*E10 -> 4240911.7 | J10: =H10/I10 -> 4.0736983
C11: 3 | D11: ='INGRESOS '!N84 -> 23296836 | E11: ='COSTOS '!N212 -> 5136333.2 | F11: =D11-E11 -> 18160503 | G11: =1/(1+$E$4)^C11 -> 0.77218348 | H11: =G11*D11 -> 17989432 | I11: =G11*E11 -> 3966191.6 | J11: =H11/I11 -> 4.5356942
C12: 4 | D12: ='INGRESOS '!N104 -> 26400344 | E12: ='COSTOS '!N265 -> 5237783.5 | F12: =D12-E12 -> 21162561 | G12: =1/(1+$E$4)^C12 -> 0.70842521 | H12: =G12*D12 -> 18702670 | I12: =G12*E12 -> 3710577.9 | J12: =H12/I12 -> 5.0403657
C13: 5 | G13: =1/(1+$E$4)^C13 -> 0.64993139
C14: TOTAL | D14: =SUM(D8:D12) -> 1.0262255e+08 | H14: =SUM(H8:H13) -> 84941347 | I14: =SUM(I8:I13) -> 21307845 | J14: =SUM(J9:J13) -> 17.143762
F17: VAN | G17: =H14-I14 -> 63633501
F18: TIR | G18: 0.15
F19: B/C | G19: =H14/I14 -> 3.9863884 | H19: 1.5

Sheet ESTADO DE RESULTADOS
B2: INICIO DE OPERACIONES 11 DE JULIO DEL 2002
B3: TAQUERIA TAKIRIN LA CHIMENEA
B4: ESTADO DE RESULTADOS DEL 01 DE ENERO AL 31 DE DICIEMBRE DEL 2025
B5: Ventas | C5: =BALANZA!Q33 -> 16975631 | D5: 1
B6: Costo de ventas | C6: =BALANZA!R34 -> 3018951.1 | D6: =C6/$C$5 -> 0.17784029
B7: Utilidad Bruta | C7: =C5-C6 -> 13956680
B8: Gastos Fijos | C8: =BALANZA!R35 -> 3588572.5 | D8: =C8/$C$5 -> 0.21139553
B9: Utilidad de Operación | C9: =C7-C8 -> 10368107
B10: Productos Financieros | C10: 0
B11: Gastos Financieros | C11: =BALANZA!R36 -> 389851.85 | D11: =C11/$C$5 -> 0.022965382
B12: Utilidad Financiera | C12: =C9+C10-C11 -> 9978255.5
B13: Otros Productos | C13: 0
B14: Otros Gastos | C14: 0
B15: Utilidad antes de Impuestos | C15: =C12+C13-C14 -> 9978255.5
B16: Impuestos | C16: =BALANZA!R37 -> 3594300.3 | D16: =C16/$C$5 -> 0.21173294
B17: UTILIDAD DEL EJERCICIO | C17: =C15-C16 -> 6383955.2 | D17: =C17/C5 -> 0.37606586 | E17: Mayor a 7%

Sheet ESTADO DE SITUACIÓN FINANCIERA
B1: TAQUERIA TAKIRIN | K1: TAQUERIA TAKIRIN
B2: ESTADO DE SITUACIÓN FINANCIERA | K2: ESTADO DE SITUACIÓN FINANCIERA
B3: AL 31 DE DICIEMBRE DE 2025 | K3: AL 31 DE DICIEMBRE DE 2025
M4: %
B5: ACTIVO | F5: PASIVO | K5: ACTIVO
B6: Activo Circulante | F6: Pasivo a Corto Plazo | K6: Activo Circulante
B7: Caja | C7: =BALANZA!$T$7 -> 10000 | F7: Proveedores Nacionales | G7: =BALANZA!$U$23 -> 360560 | K7: Caja | L7: =BALANZA!$T$7 -> 10000
B8: Bancos | C8: =BALANZA!$T$8 -> 3511169.7 | D8: =C8/C32 -> 0.53957231 | F8: Socios y Accionistas | K8: Bancos | L8: =BALANZA!$T$8 -> 3511169.7 | M8: =L8/L32 -> 0.53957231
B9: Inventarios | C9: =BALANZA!$T$10 -> 922417.64 | F9: Acreedores Diversos | G9: =BALANZA!$U$25 -> 32104 | K9: Inventarios | L9: =BALANZA!$T$10 -> 922417.64
B10: Deudores diversos | C10: =BALANZA!$T$11 -> 65800 | F10: Impuestos Por Pagar | G10: =-BALANZA!$T$26 -> -865534.62 | H10: =G7/G18 -> -0.46745043 | K10: Deudores diversos | L10: =BALANZA!$T$11 -> 65800
B11: Contribuciones a favor | C11: =BALANZA!$T$12 -> 72500 | F11: Otros Pasivos | G11: =BALANZA!$U$27 -> 13689 | K11: Contribuciones a favor | L11: =BALANZA!$T$12 -> 72500
B12: Anticipo a proveedores | C12: =BALANZA!$T$13 -> 165000 | F12: Total Pasivo a Corto Plazo | G12: =SUM(G7:G11) -> -459181.62 | H12: =G12/G18 -> 0.59530908 | K12: Anticipo a proveedores | L12: =BALANZA!$T$13 -> 165000
B13: Total Activo Circulante | C13: =SUM(C7:C12) -> 4746887.4 | D13: =C13/C32 -> 0.72946886 | K13: Total Activo Circulante | L13: =SUM(L7:L12) -> 4746887.4 | M13: =L13/L32 -> 0.72946886
F14: Pasivo a largo Plazo
F15: Documentos x pagar a largo plazo | G15: =-BALANZA!$T$28 -> -312151.51
F16: Total Pasivo a largo Plazo | G16: =G15 -> -312151.51
B17: Activo Fijo | K17: Activo Fijo
B18: Edificio | C18: =BALANZA!$T$14 -> 604576.32 | D18: =C18/C32 -> 0.092907113 | F18: TOTAL PASIVOS | G18: =G12+G16 -> -771333.13 | H18: =G18/G32 -> -0.11853315 | K18: Edificio | L18: =BALANZA!$T$14 -> 604576.32 | M18: =L18/L32 -> 0.092907113
B19: Maquinaria y equipos | C19: =BALANZA!$T$16 -> 452365.55 | K19: Maquinaria y equipos | L19: =BALANZA!$T$16 -> 452365.55
B20: Mobiliario y equipo | C20: =BALANZA!$T$17 -> 336644.84 | K20: Mobiliario y equipo | L20: =BALANZA!$T$17 -> 336644.84
B21: Equipo de transporte | C21: =BALANZA!$T$18 -> 250000 | F21: CAPITAL CONTABLE | K21: Equipo de transporte | L21: =BALANZA!$T$18 -> 250000
B22: Equipo de cómputo | C22: =BALANZA!$T$19 -> 35000 | F22: Capital social | G22: =BALANZA!$U$29 -> 200000 | K22: Equipo de cómputo | L22: =BALANZA!$T$19 -> 35000
B23: Otro activo | F23: Perdidas acumuladas | G23: =BALANZA!$U$30 -> 0 | K23: Otro activo
B24: Depreciación acumulada | C24: =-BALANZA!$T$22 -> 78154 | F24: Utilidades acumuladas | G24: =BALANZA!$U$31 -> 367638 | K24: Depreciación acumulada | L24: =-BALANZA!$T$22 -> 78154
B25: Total de fijo | C25: =SUM(C18:C22)-C24 -> 1600432.7 | D25: =C25/C32 -> 0.24594344 | F25: Otras cuentas de capital | G25: =BALANZA!$U$32 -> 327060 | K25: Total de fijo | L25: =SUM(L18:L22)-L24 -> 1600432.7 | M25: =L25/L32 -> 0.24594344
F26: Utilidad del ejercicio | G26: =BALANZA!$U$39 -> 6383955.2 | H26: =G26/G27 -> 0.87707918
B27: Activo Diferido | F27: Total Capital Contable | G27: =SUM(G22:G26) -> 7278653.2 | H27: =G27/G32 -> 1.1185331 | K27: Activo Diferido
B28: Gastos de intalación | C28: =BALANZA!$T$21 -> 160000 | K28: Gastos de intalación | L28: =BALANZA!$T$21 -> 160000
B29: Total de diferido | C29: =C28 -> 160000 | D29: =C29/C32 -> 0.024587695 | K29: Total de diferido | L29: =L28 -> 160000 | M29: =L29/L32 -> 0.024587695
B32: TOTAL ACTIVOS | C32: =C13+C25+C29 -> 6507320.1 | D32: =C32/C32 -> 1 | F32: TOTAL PASIVO Y CAPITAL | G32: =G18+G27 -> 6507320.1 | H32: =G32/G32 -> 1 | K32: TOTAL ACTIVOS | L32: =L13+L25+L29 -> 6507320.1 | M32: =L32/L32 -> 1
K34: PASIVO
K35: Pasivo a Corto Plazo
K36: Proveedores Nacionales | L36: =BALANZA!$U$23 -> 360560
K37: Socios y Accionistas
K38: Acreedores Diversos | L38: =BALANZA!$U$25 -> 32104
K39: Impuestos Por Pagar | L39: =-BALANZA!$T$26 -> -865534.62 | M39: =L36/L47 -> -0.46745043
K40: Otros Pasivos | L40: =BALANZA!$U$27 -> 13689
K41: Total Pasivo a Corto Plazo | L41: =SUM(L36:L40) -> -459181.62 | M41: =L41/L47 -> 0.59530908
K43: Pasivo a largo Plazo
K44: Documentos x pagar a largo plazo | L44: =-BALANZA!$T$28 -> -312151.51
K45: Total Pasivo a largo Plazo | L45: =L44 -> -312151.51
K47: TOTAL PASIVOS | L47: =L41+L45 -> -771333.13 | M47: =L47/L61 -> -0.11853315
K50: CAPITAL CONTABLE
K51: Capital social | L51: =BALANZA!$U$29 -> 200000
K52: Perdidas acumuladas | L52: =BALANZA!$U$30 -> 0
K53: Utilidades acumuladas | L53: =BALANZA!$U$31 -> 367638
K54: Otras cuentas de capital | L54: =BALANZA!$U$32 -> 327060
K55: Utilidad del ejercicio | L55: =BALANZA!$U$39 -> 6383955.2 | M55: =L55/L56 -> 0.87707918
K56: Total Capital Contable | L56: =SUM(L51:L55) -> 7278653.2 | M56: =L56/L61 -> 1.1185331
K61: TOTAL PASIVO Y CAPITAL | L61: =L47+L56 -> 6507320.1 | M61: =L61/L61 -> 1

Sheet BALANZA
C3: 1 | J3: SALDOS INICIALES | L3: MOVIMIENTOS | N3: SALDOS | Q3: AJUSTES | T3: SALDOS AJUSTADOS
C4: BANCOS | D4: 1127676.7
D5: DOC X PAG LP | F5: =D4 -> 1127676.7
C6: Para registrar el prestamo de FIRA | H6: FECHA | I6: CUENTA | J6: DEBE | K6: HABER | L6: DEBE | M6: HABER | N6: DEBE | O6: HABER | Q6: DEBE | R6: HABER | T6: DEBE | U6: HABER
C7: 2 | I7: Caja | J7: 10000 | N7: =J7 -> 10000 | T7: =N7 -> 10000
C8: EDIFICIO | D8: =F9 -> 604576.32 | I8: Bancos | J8: 133639 | L8: =D4+D20 -> 16251007 | M8: =F9+F13+F17+F25+F29+F33+F37+F41+F45+F49 -> 12873476 | N8: =J8+L8-M8 -> 3511169.7 | T8: =N8 -> 3511169.7
D9: BANCOS | F9: ='CUADRO DE INVERSION'!G18 -> 604576.32 | I9: Clientes | J9: 0 | T9: =N9 -> 0
C10: Para registrar la construcción del edificio | I10: Inventario | J10: 654120 | L10: =D44 -> 268297.64 | N10: =J10+L10 -> 922417.64 | T10: =N10 -> 922417.64
C11: 3 | I11: Deudores Diversos | J11: 65800 | N11: =J11 -> 65800 | T11: =N11 -> 65800
C12: MOBILIARIO Y EQUIPO | D12: 186644.84 | I12: Contribuciones a favor | J12: 72500 | N12: =J12 -> 72500 | T12: =N12 -> 72500
D13: BANCOS | F13: 186644.84 | I13: Anticipo a Proveedores | J13: 165000 | N13: =J13 -> 165000 | T13: =N13 -> 165000
C14: Para registrar la compra del equipo de cocina | I14: Edificios | J14: 0 | L14: =D8 -> 604576.32 | N14: =L14 -> 604576.32 | T14: =N14 -> 604576.32
C15: 4 | I15: Terrenos | T15: =N15 -> 0
C16: MAQUINARIA | D16: 331865.55 | I16: Maquinaria y equipos | J16: 120500 | L16: =D16 -> 331865.55 | N16: =J16+L16 -> 452365.55 | T16: =N16 -> 452365.55
D17: BANCOS | F17: 331865.55 | I17: Mobiliario y equipo | J17: 150000 | L17: =D12 -> 186644.84 | N17: =J17+L17 -> 336644.84 | T17: =N17 -> 336644.84
C18: Para registrar la compra de la nueva maquinaria | I18: Equipo de transporte | J18: 250000 | N18: =J18+L18 -> 250000 | T18: =N18 -> 250000
C19: 5 | I19: Equipo de cómputo | J19: 35000 | N19: =J19+L19 -> 35000 | T19: =N19 -> 35000
C20: BANCOS | D20: 15123330 | I20: Otro activo | J20: 0 | N20: =J20+L20 -> 0 | T20: =N20 -> 0
D21: VENTAS | F21: 15123330 | I21: Gastos de intalación | J21: =160000 -> 160000 | N21: =J21+L21 -> 160000 | T21: =N21 -> 160000
C22: Para registrar las ventas por tacos | I22: Depreciación acumulada | J22: -78154 | N22: =J22 -> -78154 | T22: =N22 -> -78154
C23: 6 | I23: Proveedores Nacionales | K23: 360560 | O23: =K23 -> 360560 | T23: =N23 -> 0 | U23: =O23 -> 360560
C24: CV | D24: 2364831.1 | I24: Socios y Accionistas | K24: 0 | O24: =K24 -> 0 | T24: =N24 -> 0 | U24: =O24 -> 0
D25: BANCOS | F25: 2364831.1 | I25: Acreedores Diversos | K25: 32104 | O25: =K25 -> 32104 | T25: =N25 -> 0 | U25: =O25 -> 32104
C26: Para registrar los costos variables | I26: Impuestos Por Pagar | K26: 950 | L26: =D48 -> 866484.62 | N26: =L26-K26 -> 865534.62 | T26: =N26 -> 865534.62 | U26: =O26 -> 0
C27: 7 | I27: Otros Pasivos | K27: 13689 | O27: =K27 -> 13689 | T27: =N27 -> 0 | U27: =O27 -> 13689
C28: GASTOS FIJOS | D28: 2835915.5 | I28: Documentos por pagar a largo plazo | K28: 0 | L28: =D32 -> 1439828.2 | M28: =F5 -> 1127676.7 | N28: =L28-M28 -> 312151.51 | T28: =N28 -> 312151.51 | U28: =O28 -> 0
D29: BANCOS | F29: 2835915.5 | I29: Capital social | K29: 200000 | O29: =K29 -> 200000 | T29: =N29 -> 0 | U29: =O29 -> 200000
C30: Para registrar los gastos fijos | I30: Pérdidas Acumuladas | K30: 0 | T30: =N30 -> 0 | U30: =O30 -> 0
C31: 8 | I31: Utilidades Acumuladas | K31: 367638 | O31: =K31 -> 367638 | T31: =N31 -> 0 | U31: =O31 -> 367638
C32: DOC X PAG LP | D32: 1439828.2 | I32: Otras cuentas de capital | K32: 327060 | O32: =K32 -> 327060 | T32: =N32 -> 0 | U32: =O32 -> 327060
D33: BANCOS | F33: =D32 -> 1439828.2 | I33: Ventas | K33: 1852301 | M33: ='LIBRO MAYOR'!C18 -> 15123330 | O33: =M33-L33+K33 -> 16975631 | Q33: ='LIBRO MAYOR'!$B$20 -> 16975631
C34: Para registrar el pago de la deuda | I34: CV | J34: 654120 | L34: =D24 -> 2364831.1 | N34: =L34+J34 -> 3018951.1 | R34: ='LIBRO MAYOR'!$K$18 -> 3018951.1 | U34: =N34-R34 -> 0
C35: 9 | I35: GF | J35: =385245+367412 -> 752657 | L35: ='LIBRO MAYOR'!N18 -> 2835915.5 | N35: =J35+L35 -> 3588572.5 | R35: ='LIBRO MAYOR'!$O$18 -> 3588572.5 | U35: =N35-R35 -> 0
C36: GASTOS FINC | D36: 380731.85 | I36: GFIN | J36: 9120 | L36: ='LIBRO MAYOR'!B27 -> 380731.85 | N36: =L36+J36 -> 389851.85 | R36: ='LIBRO MAYOR'!$C$27 -> 389851.85 | U36: =N36-R36 -> 0
D37: BANCOS | F37: 380731.85 | I37: ISR | L37: ='LIBRO MAYOR'!F27 -> 3594300.3 | N37: =L37 -> 3594300.3 | R37: ='LIBRO MAYOR'!$G$27 -> 3594300.3 | U37: =N37-R37 -> 0 | W37: s
C38: Para registrar los intereses de la deuda | I38: P Y G | Q38: ='LIBRO MAYOR'!$B$40 -> 13956680 | R38: =F57 -> 13956680 | U38: =Q38-R38 -> 0
C39: 10 | I39: Resul del ejercicio | J39: =436404 -> 436404 | K39: =436404 -> 436404 | R39: ='LIBRO MAYOR'!$G$35 -> 6383955.2 | U39: =R39 -> 6383955.2
C40: ISR | D40: =SENSIBILIDAD!L11 -> 3594300.3 | J40: =SUM(J7:J39) -> 3590706 | K40: =SUM(K7:K39) -> 3590706 | L40: =SUM(L7:L39) -> 29124483 | M40: =SUM(M7:M39) -> 29124483 | N40: =SUM(N7:N37) -> 18276682 | O40: =SUM(O7:O34) -> 18276682 | Q40: =SUM(L7:L39) -> 29124483 | R40: =SUM(M7:M39) -> 29124483 | T40: =SUM(T7:T39) -> 7685006.2 | U40: =SUM(U8:U39) -> 7685006.2
D41: BANCOS | F41: =D40 -> 3594300.3
C42: Para registrar el ISR
C43: 11
C44: INSUMOS | D44: =SUM('COSTOS '!R6:R9,'COSTOS '!R11,'COSTOS '!R13:R15) -> 268297.64
D45: BANCOS | F45: =D44 -> 268297.64
C46: Para el registro de los inventarios
C47: 12
C48: IVA | D48: =SENSIBILIDAD!N12 -> 866484.62
D49: BANCOS | F49: =D48 -> 866484.62
C50: Para el registro de los inventarios
C51: 13
C52: VENTAS | D52: ='LIBRO MAYOR'!B18 -> 3018951.1
D53: CV | F53: =D52 -> 3018951.1
C54: Para el registro de los inventarios
C55: 14
C56: VENTAS | D56: ='LIBRO MAYOR'!B19 -> 13956680
D57: PYG | F57: =D56 -> 13956680
C58: Para el registro de los inventarios
C59: 15
C60: PYG | D60: ='LIBRO MAYOR'!B35 -> 3588572.5
D61: GASTOS FIJOS | F61: =D60 -> 3588572.5
C62: Para el registro de los inventarios
C63: 16
C64: PYG | D64: ='LIBRO MAYOR'!B36 -> 389851.85
D65: GASTOS FINANCIEROS | F65: =D64 -> 389851.85
C66: Para el registro de los inventarios
C67: 17
C68: PYG | D68: ='LIBRO MAYOR'!B37 -> 3594300.3
D69: ISR | F69: =D68 -> 3594300.3
C70: Para el registro de los inventarios
C71: 18
C72: PYG | D72: ='LIBRO MAYOR'!B39 -> 6383955.2
D73: RESULTADO DEL EJ | F73: =D72 -> 6383955.2
C74: Para el registro de los inventarios

Sheet LIBRO MAYOR
B2: BANCOS | F2: DOC X PAG LP | J2: MOBILIARIO Y EQUIPO | N2: MAQUINARIA
A3: 1) | B3: 1127676.7 | C3: =BALANZA!F9 -> 604576.32 | D3: (2 | E3: 8) | F3: 1439828.2 | G3: =B3 -> 1127676.7 | H3: (1 | I3: 3) | J3: 186644.84 | M3: 4) | N3: 331865.55
A4: 5) | B4: 15123330 | C4: =J3 -> 186644.84 | D4: (3 | F4: =F3 -> 1439828.2 | G4: =G3 -> 1127676.7 | J4: =SUM(J3:J4) -> 186644.84
C5: =N3 -> 331865.55 | D5: (4
C6: =J18 -> 2364831.1 | D6: (6
C7: =N18 -> 2835915.5 | D7: (7
C8: =F3 -> 1439828.2 | D8: (8
C9: =B27 -> 380731.85 | D9: (9
C10: =F27 -> 3594300.3 | D10: (10
C11: =J27 -> 268297.64 | D11: (11
C12: =N27 -> 866484.62 | D12: (12
B14: =SUM(B3:B13) -> 16251007 | C14: =SUM(C3:C12) -> 12873476
B17: VENTAS | F17: EDIFICIO | J17: CV | N17: GASTOS FIJOS
A18: 13) | B18: =K18 -> 3018951.1 | C18: =B4 -> 15123330 | D18: 5) | E18: 2) | F18: =C3 -> 604576.32 | I18: 6) | J18: 2364831.1 | K18: =SUM(J18:J19) -> 3018951.1 | L18: (13 | M18: 7) | N18: 2835915.5 | O18: =SUM(N18:N19) -> 3588572.5 | P18: (15
A19: 14) | B19: =C20-B18 -> 13956680 | C19: =BALANZA!K33 -> 1852301 | J19: =BALANZA!J34 -> 654120 | N19: =BALANZA!J35 -> 752657
B20: =SUM(B18:B19) -> 16975631 | C20: =SUM(C18:C19) -> 16975631 | J20: =SUM(J18:J19) -> 3018951.1 | N20: =SUM(N18:N19) -> 3588572.5
B26: GASTOS FINANCIEROS | F26: ISR | J26: INSUMOS | N26: IVA
A27: 9) | B27: 380731.85 | C27: =SUM(B27:B28) -> 389851.85 | D27: (16 | E27: 10) | F27: 3594300.3 | G27: =F27 -> 3594300.3 | H27: (17 | I27: 11) | J27: 268297.64 | M27: 12) | N27: 866484.62
B28: =BALANZA!J36 -> 9120
B29: =SUM(B27:B28) -> 389851.85
B34: PERDIDAS Y GANACIAS | F34: RESULT DEL EJERC
A35: 15) | B35: =O18 -> 3588572.5 | C35: =B19 -> 13956680 | D35: (14 | G35: =B39 -> 6383955.2 | H35: (18
A36: 16) | B36: =C27 -> 389851.85
A37: 17) | B37: =F27 -> 3594300.3
B38: =SUM(B35:B37) -> 7572724.7
A39: 18) | B39: =C35-B38 -> 6383955.2
B40: =SUM(B38:B39) -> 13956680

Sheet CRONOGRAMA DE ACTIVIDADES 
A1: CRONOGRAMA DE ACTIVIDADES
A3: PROYECTO: | B3: Taqueria Takirin "la chimenea"
A4: SOCIEDAD
A5: BENEFICIARIOS: | B5: Roberto Lira Hernández
A7: CRONOGRAMA DE ACTIVIDADES
C8: MES
A9: CONCEPTO | C9: 1 | D9: 2 | E9: 3 | F9: 4 | G9: 5 | H9: 6 | I9: 7 | J9: 8 | K9: 9 | L9: 10 | M9: 11 | N9: 12
A10: Construir un local propio
A11: Analizar la demanda de delivery por zona
A12: Diseñar plítica de precios y tiempos de entrega
A13: Contratar y capacitar repartidores
A14: Implementar canales de pedido
A15: Optimizar rutas y tiempos de entrega
A16: Ampliar cobertura del servicio
A17: Medir la satisfacción del cliente
A18: Definir público objetivo por zona
A19: Crearun calendario de contenido en redes sociales
A20: Incentivar reseñas y recomendaciones de clientes
A21: Publicar contenido constante en redes sociales
... A27: CRONOGRAMA DE ACTIVIDADES SEGUNDO AÑO
A29: CONCEPTO | C29: 1 | D29: 2 | E29: 3 | F29: 4 | G29: 5 | H29: 6 | I29: 7 | J29: 8 | K29: 9 | L29: 10 | M29: 11 | N29: 12
A30: Identificar porgramas municipales, estatales y federales
A31: Aplicar a apoyos de capacitación
A32: Identificar insumos criticos
A33: Buscar proveesores alternos
A34: Negociar contratros o acuerdos con proveedores convenientes
A35: Diseñar un sistema de evaluación de proveedores
A36: Mantener una cartera diversificada y balanceada
A40: CRONOGRAMA DE ACTIVIDADES TERCER AÑO
A42: CONCEPTO | C42: 1 | D42: 2 | E42: 3 | F42: 4 | G42: 5 | H42: 6 | I42: 7 | J42: 8 | K42: 9 | L42: 10 | M42: 11 | N42: 12
A43: Estandarización total de recetas y procesos
A44: Capacitación continua del personal
A45: Programa de lealtad para clientes
A46: Participación en ferias nacionales fuera de la región
A47: Implementar un sistema de control de mermas KPI´s
A48: Optimizar layout de las distintas áreas
A52: CRONOGRAMA DE ACTIVIDADES CUARTO AÑO
A54: CONCEPTO | C54: 1 | D54: 2 | E54: 3 | F54: 4 | G54: 5 | H54: 6 | I54: 7 | J54: 8 | K54: 9 | L54: 10 | M54: 11 | N54: 12
A55: Poscicionamiento a nivel nacional
A56: Crear una cadena de restaurantes
A57: Implementar auditorias internas
A58: Capacitar al personal para mantenimiento a la maquinaria
